Workbook
Name AssocBook: Inputs!$F$161:$F$161
Name AssocClose: Inputs!$E$161:$E$161
Name AssocDiscount: Inputs!$H$159
Name AssocLines: Bridge!$C$17
Name AssocReplaced: Bridge!$C$19
Name AssocShares: Inputs!$D$161:$D$161
Name AssocValue: Bridge!$C$18
Name BetaL: WACC!$C$16
Name BetaPubN: Inputs!$B$130
Name BetaPubR2: Inputs!$B$132
Name BetaPubU: Inputs!$B$131
Name BetaR2Median: WACC!$C$7
Name BetaR2Warn: Inputs!$B$37
Name BetaU: WACC!$C$6
Name BetaWarn: WACC!$C$8
Name Block_q1: Premium!$C$23
Name Block_q2: Premium!$C$24
Name Block_q3: Premium!$C$25
Name BlumeC: Inputs!$B$32
Name BlumeW: Inputs!$B$31
Name BorrowAmt: Inputs!$C$125:$C$125
Name BorrowRate: Inputs!$B$125:$B$125
Name BridgeAdj: Bridge!$C$22
Name BsAmt: FS_Hist!$D$33:$D$37
Name BsClass: FS_Hist!$C$33:$C$37
Name BsName: FS_Hist!$A$33:$A$37
Name CAGR: Forecast!$C$24
Name CapexRatio: Forecast!$F$15
Name CfStart: Inputs!$B$14
Name CheckTable: Checks!$B$6:$F$74
Name ClipHi: Inputs!$B$64
Name ClipLo: Inputs!$B$63
Name Close: Inputs!$B$44
Name COGSR: Forecast!$F$16
Name CommonIssued: Inputs!$B$40
Name CommonTreasury: Inputs!$B$41
Name ConvEngine: Convergence!$A$7:$F$8
Name ConvLive: Convergence!$A$13:$F$14
Name ConvShare: Inputs!$B$61
Name DaysYr: Inputs!$B$15
Name DE_Target: Inputs!$B$33
Name DiagCandTable: Diagnostics!$A$58:$D$60
Name DiagCompTable: Diagnostics!$A$37:$C$44
Name DiagDcf: Diagnostics!$B$5
Name DiagDcfEngine: Diagnostics!$B$6
Name DiagDnaTable: Diagnostics!$A$133:$D$139
Name DiagFlagTable: Diagnostics!$A$48:$C$54
Name DiagGuardTable: Diagnostics!$A$120:$B$120
Name DiagHeadline: Diagnostics!$B$120
Name DiagLight: Diagnostics!$B$23
Name DiagLightCheck: Diagnostics!$B$25
Name DiagLightEngine: Diagnostics!$B$24
Name DiagLightMkt: Diagnostics!$B$22
Name DiagLightPeer: Diagnostics!$B$21
Name DiagMistagTable: Diagnostics!$A$161:$D$161
Name DiagMktRatio: Diagnostics!$B$14
Name DiagOtherTable: Diagnostics!$B$93:$D$117
Name DiagPeerBasis: Diagnostics!$B$7
Name DiagPeerMed: Diagnostics!$B$9
Name DiagPeerN: Diagnostics!$B$11

Sheet Cover
B2: 솔본 (035610) 주식가치 산정 모델 (자동 생성 초안)
B3: 자동 생성 초안. 기계적 가치산정 결과이며 전문가 판단을 거친 가치평가(평가보고서)가 아님. 투자 권유 아님
B4: 예시 입력 시세(실제 종가 아님) — 결과는 가정 하의 추정 내재가치 예시
B5: 평가대상 | C5: 솔본 (KOSDAQ 035610, 법인 00249982)
B6: 평가기준일 | C6: 2026-09-30
B7: 재무 기준일 | C7: 2026-06-30 (반기보고서)
B8: 기준가치 | C8: 주당 내재가치 추정(가치산정, 가정 하의 예시). '공정가치'(K-IFRS 1113·자본시장법 공정가액)가 아님
B9: 평가 전제 | C9: 계속기업
B10: 목적 | C10: 방법론 예시·교육(실제 거래·공시용 아님)
B11: 평가 구조 | C11: 연결 DCF − 비지배지분
B12: 단위 | C12: 백만원(주당 값은 원). 비율은 %
B13: 출처 표시 | C13: 재무: DART 접수번호 / 금리: ECOS 817Y002 / 시세·시가총액·VWAP·베타: 한국거래소 통계정보(기준일 단일 값·집계만)
B14: 생성 | C14: src/excel/build.py ← 공개 배포 작업 공간/sessions/035610_20260930_001/v1_public/valuation_035610_035610_20260930_001v1p.yaml (P4, 엔진 형태 mechanical). 결과 확인: Checks 시트의 master check
B17: 현재 선택 | C17: ="시나리오: "&ScenSel&" / SRP: "&TEXT(SRP_Sel,"0.0%")&" / 주당 가치(Gordon): "&TEXT(PerShare,"#,##0")&"원" -> 시나리오: 기본 / SRP: 0.0% / 주당 가치(Gordon): 8,734원
B18: master check | C18: =MasterCheck -> OK
B20: 사람이 작성할 칸
B21: 평가방법 선택 근거
B22: 주요 가정의 합리성
B23: 평가상 한계
B24: 검토자·검토일

Sheet Guide
B2: 모델 안내
B4: 시트 지도
B5: Inputs | C5: 모든 입력값(파란 글씨·노란 바탕). 출처·기준일·상태(✅/🔸/⚠️) 열. 시나리오·SRP·RONIC 규칙 선택 칸이 맨 위
B6: FS_Hist | C6: 엔진이 쓴 과거 재무(모회사 별도, 연결 2026-06-30)와 부문 주석, 열마다 DART 접수번호
B7: Forecast | C7: 선택한 시나리오의 2H26~2040 예측: 매출·EBIT·D&A·CAPEX·ΔNWC·누진 세금·NOPAT·FCFF. 2032까지 명시, 2033~2040 체감
B8: WACC | C8: 피어 베타(원 β → Blume → Hamada 언레버 → 중앙값) → 리레버 → Ke, Kd 규칙(등급·Rf 하한), WACC, R² 경고
B9: DCF | C9: 할인계수(mid-year, 6/30 할인 → 9/30 이월), RONIC, 가치동인 영구가치, EV, 영구가치 비중, 함의 배수, Exit 병행
B10: Bridge | C10: 연결 EV − 순차입금(리스 포함) + 비영업 − 비지배 → 주당 가치. 계열사 대여금 표시·토글, 구조 판단
B11: Peers | C11: 피어 배수 4종(LTM), N/M 처리, 사분위(QUARTILE.INC) → 주당 가치
B12: Premium | C12: 시총 백분위와 D6 적용 규칙(method·이유) → 20일 VWAP × (1+프리미엄) 블록 1주당 범위, 상증법 할증 비교
B13: Scenarios | C13: 시나리오 3 × SRP 3 표(살아 있는 수식, Scen_Calc), 데이터 표 2개(WACC×g, 성장×이익률, 엑셀 What-If), 역DCF(엔진 값)
B14: Scen_Calc | C14: Scenarios 표를 계산하는 시나리오별 블록(Forecast와 같은 수식, 시나리오 고정)
B15: Football | C15: 방법별 주당 범위 그림(수식 셀 참조) + 기준일 종가 선
B16: Convergence | C16: 수렴 시험(사전 고정 기준): 엔진 기록 판정(C2 1차, C3)과 살아 있는 모델 재계산
... B28: P5-B 참고값(P6-A) | C28: Forecast 사업계획 검증 옆 달성률 표, Inputs SRP 옆 한공회 인용 표는 스팩 합병 외부평가 의견서 집계(회색, 표시만). 자동 감액·경고 판정 없음

Sheet Inputs
A1: Inputs — 입력값 (파란 글씨·노란 바탕 칸만 바꾼다)
A2: 단위: 백만원(주당 값은 원). 출처 열: DART 접수번호·ECOS 코드·config 경로. 상태: ✅ 1차 출처·독립 확인 / 🔸 단일 출처·직접 계산 / ⚠️ 미확인·프로젝트 가정
A4: 항목 | B4: 값 | C4: 단위 | D4: 출처 | E4: 기준일 | F4: 상태 | G4: 근거·비고
A5: 1. 선택 (모델 실행)
A6: 시나리오 선택 | B6: 기본 | D6: 공개 배포 작업 공간/sessions/035610_20260930_001/v1_public/valuation_035610_035610_20260930_001v1p.yaml excel.default_scenario | F6: 🔸 | G6: 목록: 비관/기본/낙관
A7: SRP 선택(규모위험프리미엄) | B7: 0 | C7: % | D7: config/valuation_rf.yaml decisions.srp_columns (D4) | F7: ⚠️ | G7: 목록: SRP 열 세 값. 한공회 구간 표 미확보 → 세 열 병기
A8: Rf 만기 선택(5 = 국고채 5년, 10 = 국고채 10년) | B8: 5 | C8: 년 | D8: config/valuation_rf.yaml risk_free.tenor | F8: 🔸 | G8: 기본 5년(P3 공통 장부, 사전 고정 결과 그대로). 10년 = 선택: P5-B 의견서 Rf 만기 표시 57건 중 10년 56건(reports/p5b_final.md 7절) → 10년을 선택 칸으로 추가. 기본 5년 불변
A9: RONIC 출발점 규칙 | B9: normal | D9: config/valuation_rules.yaml common_rules.ronic | F9: 🔸 | G9: normal = P3-C3 공통 규칙(FY2026 매출 × 정상 이익률) / mixed = P3-B2·C2 방식(1H 실적 + 2H 정상)
A11: 2. 기준일·기간 구조
A12: 평가기준일 | B12: 46295 | C12: 날짜 | D12: 공개 배포 작업 공간/sessions/035610_20260930_001/v1_public/valuation_035610_035610_20260930_001v1p.yaml meta.as_of | E12: 2026-09-30 | F12: 🔸 | G12: KRX 시세 마지막 적재 거래일
A13: 할인 기준일(재무상태표일) | B13: 46203 | C13: 날짜 | D13: 공개 배포 작업 공간/sessions/035610_20260930_001/v1_public/valuation_035610_035610_20260930_001v1p.yaml meta.bs_date | F13: 🔸 | G13: 순현금(6/30 재무상태표)과 시작점을 맞춘다. EV는 평가기준일로 이월
A14: 현금흐름 시작일 | B14: 46204 | C14: 날짜 | D14: 공개 배포 작업 공간/sessions/035610_20260930_001/v1_public/valuation_035610_035610_20260930_001v1p.yaml meta.bs_date + 1일 | F14: 🔸
A15: 연 일수 | B15: 365 | C15: 일 | D15: src/valuation/dcf.py DAYS | F15: 🔸 | G15: 할인 기간·회전일수 계산(윤일 포함 실제 일수 ÷ 365)
A16: 단위 환산 | B16: 1000000 | C16: 원/백만원 | D16: 단위 | F16: 🔸 | G16: 주당 가치 = 주식가치(백만원) × 1,000,000 ÷ 주식수
A17: mid-year 할인(1=예, 0=기말) | B17: 1 | D17: 공개 배포 작업 공간/sessions/035610_20260930_001/v1_public/valuation_035610_035610_20260930_001v1p.yaml forecast.mid_year | F17: 🔸
A18: 명시 기간 마지막 연도(생성 시 고정) | B18: 2032 | C18: 연도 | D18: company_dcf.EXPLICIT_END (P3-B2 구조) | F18: 🔸 | G18: 열 수가 생성 시 정해진다. 바꾸려면 config 수정 후 재생성(Checks에서 확인)
A19: 체감 구간 연수(생성 시 고정) | B19: 8 | C19: 년 | D19: p3b2.stages.fade_years | F19: ⚠️ | G19: g_t = g_2032 − k × (g_2032 − g) / 8
A20: 평가 구조(사용자 결정·규칙 판정) | B20: consolidated | D20: 공개 배포 작업 공간/sessions/035610_20260930_001/v1_public/valuation_035610_035610_20260930_001v1p.yaml structure (규칙 판정) | F20: 🔸 | G20: Bridge 시트의 구조 판단 규칙(valuation_rules.yaml) 결과와 같아야 한다
A22: 3. 할인율 (공통 장부)
A23: 무위험이자율 국고채 5년(기본) | B23: 0.04203 | C23: % | D23: ECOS 817Y002 010200001 (KTB5Y) | E23: 2026-09-30 | F23: ✅ | G23: 평가 표본 5년 48%·10년 39%(P3) → 5년 기본. 모델이 쓰는 Rf = WACC 시트 'Rf'(Rf 만기 선택)
A24: 무위험이자율 국고채 10년(선택) | B24: 0.04407 | C24: % | D24: ECOS 817Y002 010210000 (KTB10Y) | E24: 2026-09-30 | F24: ✅ | G24: P5-B 외부평가 의견서 Rf 만기 표시 57건 중 10년 56건(reports/p5b_final.md 7절) | I24: 참고: 한공회 규모위험 프리미엄 인용값(P5-B 외부평가 의견서 재인용 🔸, 집계)
A25: 시장위험프리미엄 MRP | B25: 0.08 | C25: % | D25: 한공회 MRP 가이던스 7~9%(2022 발표·2023 유지), 2026-05 설문 8.167%(CPA뉴스 2026-05-29, 한국세정신문 2026-05-29) | E25: 2026-05 | F25: ✅ | G25: 가이던스 7~9% 중앙값 | I25: 인용 기준 연도 | J25: 구간 이름 | K25: 값 | L25: 건수 | M25: 신고서 연도
A26: SRP 열 1 | B26: 0 | C26: % | D26: config/valuation_rf.yaml decisions.srp_columns | F26: ⚠️ | G26: 한공회 2026년 1월 기준 규모위험프리미엄 연구(기사 인용). 구간 경계·전체 표 원문 미확보 | I26: 2022 | J26: 3분위 | K26: 0.0335 | L26: 1 | M26: 2024
A27: SRP 열 2 | B27: 0.01 | C27: % | D27: config/valuation_rf.yaml decisions.srp_columns | F27: ⚠️ | I27: 2022 | J27: 5분위 | K27: 0.0416 | L27: 1 | M27: 2024
A28: SRP 열 3 | B28: 0.02 | C28: % | D28: config/valuation_rf.yaml decisions.srp_columns | F28: ⚠️ | I28: 2022 | J28: Micro | K28: 0.0335 | L28: 4 | M28: 2023~2024
A29: SRP 인용 참고값(한공회 Micro, 민감도 전용) | B29: 0.0402 | C29: % | D29: DB p5b_srp_cites: 가장 최근 신고서의 같은 구간 인용값(reports/p5b_final.md 8절) | E29: 20260821 | F29: 🔸 | G29: 의견서 2차 인용 3건(2025~2026 신고서). SRP 기본 열(결정 D4)은 그대로. Scenarios G 표에서만 쓴다 | I29: 2023 | J29: 5분위 | K29: 0.0473 | L29: 1 | M29: 2024
A30: Hamada 세율(언레버·리레버) | B30: 0.22 | C30: % | D30: 공개 배포 작업 공간/sessions/035610_20260930_001/v1_public/valuation_035610_035610_20260930_001v1p.yaml beta.tax | F30: 🔸 | G30: 피어 대부분의 과세표준 구간 한계세율 | I30: 2023 | J30: Micro | K30: 0.0335 | L30: 1 | M30: 2024
A31: Blume 가중치(원 β) | B31: 0.67 | D31: config/valuation_rules.yaml common_rules.beta.blume | F31: 🔸 | G31: Blume = 0.67 × 원 β + 0.33 | I31: 2024 | J31: (미추출) | K31: 0.0375 | L31: 1 | M31: 2025
A32: Blume 상수 | B32: 0.33 | D32: config/valuation_rules.yaml common_rules.beta.blume | F32: 🔸 | I32: 2024 | J32: 3분위 | K32: 0.0375 | L32: 1 | M32: 2025
A33: 목표 D/E (WACC) | B33: 0.0042596555 | C33: 배 | D33: 공개 배포 작업 공간/sessions/035610_20260930_001/v1_public/valuation_035610_035610_20260930_001v1p.yaml (공개 모드 집계 입력) | F33: 🔸 | G33: 자체 D/E 시점 평균(5개 시점, PC에서 계산한 집계값. 시점별 시가총액은 공개 모드에 표시하지 않음) | I33: 2024 | J33: 5분위 | K33: 0.0473 | L33: 1 | M33: 2024
A34: 신용등급(빈칸 = 무등급) | D34: 자동 탐색 안 함(OpenDART 등급 API 없음) — 사람 확인 | F34: 🔸 | G34: Kd 규칙: 무등급·BBB 이하 → BBB- 3년, AA- 이상 → AA-, A+~BBB+ → max(실제 가중, AA-), 하한 Rf | I34: 미추출 | J34: (미추출) | K34: 0.0335 | L34: 1 | M34: 2025
A35: 회사채 3년 BBB- | B35: 0.10506 | C35: % | D35: ECOS 817Y002 010320000 (CB3Y_BBBm) | E35: 2026-09-30 | F35: ✅ | I35: 미추출 | J35: 3분위 | K35: 0.0375 | L35: 1 | M35: 2025
A36: 회사채 3년 AA- | B36: 0.04703 | C36: % | D36: ECOS 817Y002 010300000 (CB3Y_AAm) | E36: 2026-09-30 | F36: ✅ | I36: 미추출 | J36: 3분위 | K36: 0.0402 | L36: 1 | M36: 2026
A37: 베타 신뢰성 경고 기준(피어 R² 중앙값 미만) | B37: 0.1 | D37: common_rules.beta.warn_r2_median_below | F37: 🔸 | G37: 표시만(경로 불변) | I37: 미추출 | J37: 5분위 | K37: 0.0416 | L37: 1 | M37: 2023
I38: 미추출 | J38: 5분위 | K38: 0.0466 | L38: 1 | M38: 2026
A39: 4. 주식·시장 (기준일 단일 값) | I39: 미추출 | J39: Micro | K39: 0.0402 | L39: 3 | M39: 2025~2026
A40: 보통주 발행주식수(기준일) | B40: 27345997 | C40: 주 | D40: 반기보고서 주식의 총수 20260814003092(stockTotqySttus), KRX 기준일 상장 우선주 | E40: 2026-09-30 | F40: ✅ | G40: 주당가치 = 주식가치 ÷ 보통주 유통주식수(우선주 없음) | I40: 구간 경계(시가총액)와 대상 회사가 속한 구간은 미확인. 같은 이름도 연구 기준 연도마다 값이 다름. 출처: reports/p5b_final.md (커밋 0a8d7c6), DB p5b_error·p5b_forecast·p5b_srp_cites
A41: 보통주 자기주식수(기준일) | B41: 0 | C41: 주 | D41: 반기보고서 주식의 총수 20260814003092(stockTotqySttus), KRX 기준일 상장 우선주 | E41: 2026-09-30 | F41: ✅
A42: 우선주 발행주식수(기준일) | B42: 0 | C42: 주 | D42: 반기보고서 주식의 총수 20260814003092(stockTotqySttus), KRX 기준일 상장 우선주 | E42: 2026-09-30 | F42: ✅ | G42: 우선주 없음
A43: 우선주 자기주식수(기준일) | B43: 0 | C43: 주 | D43: 반기보고서 주식의 총수 20260814003092(stockTotqySttus), KRX 기준일 상장 우선주 | E43: 2026-09-30 | F43: ✅
A44: 기준일 종가(보통주) | B44: 20000 | C44: 원 | D44: 한국거래소 통계정보 | E44: 2026-09-30 | F44: ✅
A45: 기준일 시가총액(대상 보통주) | B45: 546919.94 | C45: 백만원 | D45: 한국거래소 통계정보 (mktcap_fix 보정 적용) | E45: 2026-09-30 | F45: ✅ | G45: 시총 백분위에 사용
A46: 상장 종속회사 시가총액(없음) | B46: 0 | C46: 백만원 | D46: 상장 종속회사 없음 | E46: 2026-09-30 | F46: ✅ | G46: 구조 판단 수식용 0
A47: 상장 종속회사 지분율(없음) | B47: 0 | C47: % | D47: 상장 종속회사 없음 | F47: ✅
A48: 중요 종속회사 상장 여부(1=예) | B48: 0 | D48: 공개 배포 작업 공간/sessions/035610_20260930_001/v1_public/valuation_035610_035610_20260930_001v1p.yaml structure.listed_subsidiary (otrCprInvstmntSttus) | F48: ✅
A50: 5. 기계적 예측 규칙 (P7-B 자동 초안 규칙)
A51: 영구성장률 g(사람 값) | B51: 0.02 | C51: % | D51: 공개 배포 작업 공간/sessions/035610_20260930_001/v1_public/valuation_035610_035610_20260930_001v1p.yaml forecast.human.g_terminal | F51: ⚠️ | G51: 세 시나리오 같음. 2030년까지 출발 성장률에서 같은 폭으로 체감
A52: 출발 성장률 → g 도달 연도 | B52: 2030 | C52: 연도 | D52: 공개 배포 작업 공간/sessions/035610_20260930_001/v1_public/valuation_035610_035610_20260930_001v1p.yaml params.fade_to_terminal_by | F52: 🔸 | G52: 2031~2032 = g
A53: D&A 반기 ÷ 연간 하한 | B53: 0.35 | D53: 공개 배포 작업 공간/sessions/035610_20260930_001/v1_public/valuation_035610_035610_20260930_001v1p.yaml params.ebitda_rule | F53: 🔸 | G53: 반기 D&A가 3개월 값으로 보이면 LTM = FY D&A
A54: D&A 반기 ÷ 연간 상한 | B54: 0.75 | D54: 공개 배포 작업 공간/sessions/035610_20260930_001/v1_public/valuation_035610_035610_20260930_001v1p.yaml params.ebitda_rule | F54: 🔸
A55: D&A ÷ 매출 하한(N/M) | B55: 0.001 | D55: 공개 배포 작업 공간/sessions/035610_20260930_001/v1_public/valuation_035610_035610_20260930_001v1p.yaml params.ebitda_rule | F55: 🔸
A56: D&A ÷ 매출 상한(N/M) | B56: 0.2 | D56: 공개 배포 작업 공간/sessions/035610_20260930_001/v1_public/valuation_035610_035610_20260930_001v1p.yaml params.ebitda_rule | F56: 🔸
A57: 부문 이익률 차이(단일 보고부문) | B57: 0 | C57: %p | D57: 공개 배포 작업 공간/sessions/035610_20260930_001/v1_public/valuation_035610_035610_20260930_001v1p.yaml structure.segments | F57: ✅ | G57: 단일 부문(자동 초안: 부문 미수집)
A58: 부문 성장률 차이(단일 보고부문) | B58: 0 | C58: %p | D58: 공개 배포 작업 공간/sessions/035610_20260930_001/v1_public/valuation_035610_035610_20260930_001v1p.yaml structure.segments | F58: ✅
A59: v2 피어 LTM 영업이익률 중앙값(n=5) | B59: 0.12355134 | C59: % | D59: 피어 fs_std LTM(company_dcf.peer_metrics) | F59: 🔸 | G59: 피어 3곳 미만이면 빈칸(수렴 없음)
A60: v2 피어 매출 성장률 중앙값(n=5) | B60: 0.020720899 | C60: % | D60: 피어 fs_std FY2023→2025 CAGR | F60: 🔸 | G60: 피어 3곳 미만이면 빈칸(대상 CAGR만)
A61: v2 수렴 비율(2032년까지 피어 쪽으로 좁히는 몫) | B61: 0.5 | D61: config/p7b2b.yaml mechanical_v2 | F61: ⚠️ | G61: 사이클 평균 + 경쟁에 따른 평균 회귀(근거 reports/p7b2b_default.md)
A62: v2 대상 CAGR 가중치(나머지 = 피어 성장률) | B62: 0.5 | D62: config/p7b2b.yaml mechanical_v2 | F62: ⚠️ | G62: 기저율 혼합
A63: v2 출발 성장률 하한 | B63: -0.1 | D63: config/p7b2b.yaml mechanical_v2 | F63: ⚠️
A64: v2 출발 성장률 상한 | B64: 0.25 | D64: config/p7b2b.yaml mechanical_v2 | F64: ⚠️
A66: 8. 구조 판단 규칙 (config/valuation_rules.yaml structure)
A67: 비지배지분 ÷ 주식가치 ≥ (SOTP) | B67: 0.1 | C67: % | D67: valuation_rules.yaml structure.nci_share_min | F67: ⚠️ | G67: 비지배지분 시가(상장 종속회사) 우선, 없으면 장부
A68: 상장 종속회사 + 부문 이익률 차이 ≥ | B68: 0.05 | C68: %p | D68: valuation_rules.yaml listed_sub_margin_gap_pp | F68: ⚠️
A69: 상장 종속회사 + 부문 성장률 차이 ≥ | B69: 0.1 | C69: %p | D69: valuation_rules.yaml listed_sub_growth_gap_pp | F69: ⚠️
A71: 9. 블록 프리미엄 (프리미엄 DB 집계값만, 거래 목록 없음)
A72: 기준일 시총 백분위(고정, KOSDAQ 보통주 1,740종목 중) | B72: 66.4 | C72: 백분위 | D72: 한국거래소 통계정보 → predict.mktcap_percentile, 기준일 값 고정(공개 모드: 입력한 주가로 바뀌지 않음) | E72: 2026-09-30 | F72: 🔸 | G72: 중간 순위 백분위(0~100). 공개 배포 스냅샷은 소수 첫째 자리
A73: 시총 백분위 고정 여부(공개 모드) | B73: 1 | D73: config/p7c3b.yaml percentile | F73: 🔸 | G73: 1 = 기준일 값 고정
A74: 시장 | B74: KOSDAQ | D74: 공개 배포 작업 공간/sessions/035610_20260930_001/v1_public/valuation_035610_035610_20260930_001v1p.yaml meta.target.market | F74: ✅
A75: C3 판정: CV q50 손실 개선 | B75: 0.051476309 | C75: % | D75: predict.adoption (사전 등록 5-fold CV) | F75: 🔸 | G75: 5.15% ≥ 5% → 회귀 채택(D1, 판정 불안정 공개)
A76: 회귀 채택 기준 | B76: 0.05 | C76: % | D76: config/premium_p2c3.yaml | F76: 🔸
A77: D6: KOSDAQ 상위 구간 기준(백분위 이상) | B77: 80 | C77: 백분위 | D77: config/premium_p2c3.yaml application_rule | F77: 🔸 | G77: D6(사용자 2026-10-03)
A78: 경고: 회귀 vs 이웃 중앙값 차이 > | B78: 0.1 | C78: %p | D78: predict.GAP_WARN (사전 등록) | F78: 🔸
A79: 이웃 50건 q25 | B79: -0.082132402 | C79: % | D79: predict.premium_range (주 표본 n=510, bu20_doc), 결정 D1·D6 | F79: 🔸
A80: 이웃 50건 q50 | B80: 0.084419618 | C80: % | D80: predict.premium_range (주 표본 n=510, bu20_doc), 결정 D1·D6 | F80: 🔸
A81: 이웃 50건 q75 | B81: 0.30876385 | C81: % | D81: predict.premium_range (주 표본 n=510, bu20_doc), 결정 D1·D6 | F81: 🔸
A82: 분위 회귀(참고) q25 | B82: -0.080474082 | C82: % | D82: predict.premium_range (주 표본 n=510, bu20_doc), 결정 D1·D6 | F82: 🔸
A83: 분위 회귀(참고) q50 | B83: 0.080149048 | C83: % | D83: predict.premium_range (주 표본 n=510, bu20_doc), 결정 D1·D6 | F83: 🔸
A84: 분위 회귀(참고) q75 | B84: 0.36540326 | C84: % | D84: predict.premium_range (주 표본 n=510, bu20_doc), 결정 D1·D6 | F84: 🔸
A85: 이웃 표본 수 | B85: 50 | C85: 건 | D85: predict.premium_range (주 표본 n=510, bu20_doc), 결정 D1·D6 | F85: 🔸 | G85: 같은 시장 우선
A86: 구간 표 P60-80 q25 | B86: -0.092879496 | C86: % | D86: predict.premium_range (주 표본 n=510, bu20_doc), 결정 D1·D6 | F86: 🔸
A87: 구간 표 P60-80 q50 | B87: 0.083969898 | C87: % | D87: predict.premium_range (주 표본 n=510, bu20_doc), 결정 D1·D6 | F87: 🔸
A88: 구간 표 P60-80 q75 | B88: 0.40342333 | C88: % | D88: predict.premium_range (주 표본 n=510, bu20_doc), 결정 D1·D6 | F88: 🔸
A89: 구간 표 P60-80 표본 수 | B89: 77 | C89: 건 | D89: predict.premium_range (주 표본 n=510, bu20_doc), 결정 D1·D6 | F89: 🔸
A90: 20거래일 VWAP(사용자 입력) | B90: 19800 | C90: 원 | D90: 사용자 입력 시세 | E90: 2026-09-30 | F90: 🔸 | G90: 공개 모드: 사용자가 넣은 값
A91: 상증법 최대주주 할증률(비교용) | B91: 0.2 | C91: % | D91: 상증법 제63조 제3항(원문 미확인) | F91: ⚠️ | G91: 중소기업·일정 중견기업은 제외 → 해당 여부 미확인
A92: 피어 배수 표본 수 경고 기준(미만) | B92: 5 | C92: 곳 | D92: 공개 배포 작업 공간/sessions/035610_20260930_001/v1_public/valuation_035610_035610_20260930_001v1p.yaml relative.n_warn | F92: 🔸 | G92: N/M(분모 ≤ 0) 제외 후 표본 수
A93: 프리미엄 표본 수 경고 기준(미만) | B93: 10 | C93: 건 | D93: CLAUDE.md 통계 원칙(n<10 경고) | F93: 🔸
A96: 표 1. 법인세 + 지방소득세 누진 구간 (2026~ 사업연도)
A97: 구간 | B97: 하한(백만원) | C97: 상한(백만원) | D97: 세율 | E97: 출처
A98: 구간 1 | B98: 0 | C98: 200 | D98: 0.11 | E98: 법인세법(법률 제21217호, 2025-12-23 공포, 2026-01-01 시행), 지방세법 제103조의20(법률 제21308호)
A99: 구간 2 | B99: 200 | C99: 20000 | D99: 0.22
A100: 구간 3 | B100: 20000 | C100: 300000 | D100: 0.242
A101: 구간 4 | B101: 300000 | D101: 0.275
A102: 마지막 구간 상한은 빈칸(상한 없음). 상태 ✅(law.go.kr 개정이유·국회예산정책처)
A104: 표 2. 신용등급 척도 (Kd 규칙)
A105: 순서 | B105: 등급
A106: 1 | B106: AAA
A107: 2 | B107: AA+
A108: 3 | B108: AA
A109: 4 | B109: AA-
...

Sheet FS_Hist
A1: FS_Hist — 엔진이 쓴 과거 재무 (백만원, DART 정기보고서 API·원문 주석)
A2: 열마다 주 접수번호(가장 많은 줄의 출처), 기타 접수번호는 비교 칸 출처. 값이 없는 줄은 0(엔진과 같음). 입력 셀
A4: 재무제표 | C4: 별도(OFS) | D4: 별도(OFS) | E4: 별도(OFS) | F4: 별도(OFS) | G4: 별도(OFS) | H4: 별도(OFS) | I4: 별도(OFS) | J4: 별도(OFS)
A5: 기간 | C5: 2020 FY | D5: 2021 FY | E5: 2022 FY | F5: 2023 FY | G5: 2024 FY | H5: 2025 FY | I5: 2025 H1 | J5: 2026 H1
A6: 주 접수번호 | C6: 20220323000559 | D6: 20230721000054 | E6: 20240321001602 | F6: 20260320001033 | G6: 20260323000001 | H6: 20260323000001 | I6: 20260814003092 | J6: 20260814003092
A7: 기타 접수번호 | C7: - | D7: 20220323000559 | E7: 20230721000054 | F7: 20240321001602 | G7: 20260320001033 | H7: - | I7: 20250813001150 | J7: -
A8: 매출액 | B8: revenue | C8: 3540.8746 | D8: 3324.1199 | E8: 3307.0693 | F8: 4545.6638 | G8: 5169.9308 | H8: 3686.9784 | I8: 2598.7278 | J8: 1699.4526
A9: 매출원가 | B9: cogs | C9: 113.40545 | D9: 112.79845 | E9: 98.116134 | F9: 93.330299 | G9: 90.569449 | H9: 99.836631 | I9: 48.778481 | J9: 51.642809
A10: 영업이익 | B10: operating_income | C10: 1182.3769 | D10: 1374.8942 | E10: -324.43883 | F10: 1453.6667 | G10: 75.220169 | H10: -1794.8232 | I10: 772.55253 | J10: -259.27283
A11: pretax_income | B11: pretax_income | C11: 913.03956 | D11: 18012.262 | E11: -11344.259 | F11: 4885.3981 | G11: -5289.807 | H11: -4873.4799 | I11: 744.40479 | J11: 914.02463
A12: 당기순이익 | B12: net_income | C12: 913.03956 | D12: 18012.262 | E12: -11344.259 | F12: 4885.3981 | G12: -5289.807 | H12: -4873.4799 | I12: 562.22505 | J12: -21.678901
A13: net_income_parent | B13: net_income_parent | C13: 0 | D13: 0 | E13: 0 | F13: 0 | G13: 0 | H13: 0 | I13: 0 | J13: 0
A14: 유형자산 취득(CAPEX) | B14: capex_ppe | C14: 1.2 | D14: 3.9 | E14: 4.773637 | F14: 1.875 | G14: 69.992727 | H14: 93.67 | I14: 75.075 | J14: 8.4846
A15: 무형자산 취득 | B15: capex_intangibles | C15: 0 | D15: 0 | E15: 0 | F15: 0 | G15: 0 | H15: 0 | I15: 0 | J15: 0
A16: 감가상각비·무형자산상각비(주석) | B16: dna | D16: 129.868 | E16: 114.227 | F16: 103.232 | G16: 93.911 | H16: 116.591 | I16: 50.33 | J16: 70.66
A17: dna_dep | B17: dna_dep | C17: 0 | D17: 129.828 | E17: 114.187 | F17: 103.232 | G17: 93.911 | H17: 110.095 | I17: 50.33 | J17: 62.205
A18: 매출채권 | B18: receivables | C18: 13131.713 | D18: 9346.1395 | E18: 7010.9404 | F18: 2660.6366 | G18: 1286.9762 | H18: 570.96784 | I18: 1331.8225 | J18: 846.27433
A19: 재고자산 | B19: inventories | C19: 35.144 | D19: 2.47 | E19: 1.685 | F19: 0.935 | G19: 0.935 | H19: 0 | I19: 0.935 | J19: 0
A20: 매입채무 | B20: trade_payables | C20: 592.5531 | D20: 468.07143 | E20: 3486.4705 | F20: 2546.2337 | G20: 774.35165 | H20: 434.98341 | I20: 514.11926 | J20: 542.24401
A21: 유형자산 | B21: ppe | C21: 290.92026 | D21: 242.177 | E21: 209.94787 | F21: 185.77524 | G21: 292.72182 | H21: 306.97369 | I21: 314.42879 | J21: 300.29703
A22: 무형자산 | B22: intangibles | C22: 7.680093 | D22: 7.64 | E22: 7.64 | F22: 7.64 | G22: 7.64 | H22: 7.64 | I22: 7.64 | J22: 7.64
A23: 사용권자산 | B23: rou_assets | C23: 0 | D23: 0 | E23: 0 | F23: 0 | G23: 0 | H23: 23.584536 | I23: 0 | J23: 56.911371
A24: 총차입금(API 표준 계정) | B24: total_debt | C24: 0 | D24: 0 | E24: 0 | F24: 0 | G24: 1500 | H24: 0 | I24: 725.85642 | J24: 0
A25: 리스부채 | B25: lease_liabilities | C25: 0 | D25: 0 | E25: 0 | F25: 0 | G25: 0 | H25: 23.879169 | I25: 0 | J25: 55.459414
A26: 비지배지분 | B26: nci | C26: 0 | D26: 0 | E26: 0 | F26: 0 | G26: 0 | H26: 0 | I26: 0 | J26: 0
A27: 지배주주지분 | B27: equity_parent | C27: 0 | D27: 0 | E27: 0 | F27: 0 | G27: 0 | H27: 0 | I27: 0 | J27: 0
A28: 자본총계 | B28: total_equity | C28: 144863.02 | D28: 167740.11 | E28: 117746.92 | F28: 122562.28 | G28: 117240.74 | H28: 119185.57 | I28: 117802.97 | J28: 119163.89
A31: 연결 재무상태표 금융자산 줄 분류 (2026-06-30, 백만원) — 20260814003092 연결 재무상태표 줄(peer_p3.classify 규칙)
A32: 계정 | B32: 구간 | C32: 분류 | D32: 금액
A33: 현금및현금성자산 | B33: 유동 | C33: cash_like | D33: 1111.4503
A34: 투자부동산 | B34: 비유동 | C34: non_operating | D34: 26435.924
A35: 관계기업투자주식 | B35: 비유동 | C35: nonop_assoc | D35: 13228.925
A36: 종속기업투자주식 | B36: 비유동 | C36: sub_inv | D36: 70894.006
A37: 당기손익-공정가치측정금융자산 | B37: 비유동 | C37: non_operating | D37: 6060.6815
A38: 분류 cash_like = 현금성(유동: 현금·단기금융·공정가치·기타 유동 금융자산), non_operating = 비영업(비유동: 공정가치·장기금융·기타 금융자산·관계기업·투자부동산). 대상과 피어에 같은 규칙(peer_p3.classify) ⚠️ '기타 금융자산'에는 대여금이 섞일 수 있음

Sheet Forecast
A1: Forecast — 연결 예측(기계적 경로) (선택한 시나리오, 백만원)
A2: ="선택 시나리오: "&ScenSel&" (2H26~"&ExplicitEnd&" 명시, 이후 "&FadeYears&"년 체감 → 영구)" -> 선택 시나리오: 기본 (2H26~2032 명시, 이후 8년 체감 → 영구)
A4: 세율표(누진) — Inputs 표 1 연결, 한계세율 차이
C5: 하한 | D5: 상한 | E5: 세율 | F5: 세율 증분
A6: 구간 1 | C6: =Inputs!B98 -> 0 | D6: =IF(ISBLANK(Inputs!C98),"",Inputs!C98) -> 200 | E6: =Inputs!D98 -> 0.11 | F6: =E6 -> 0.11
A7: 구간 2 | C7: =Inputs!B99 -> 200 | D7: =IF(ISBLANK(Inputs!C99),"",Inputs!C99) -> 20000 | E7: =Inputs!D99 -> 0.22 | F7: =E7-N(E6) -> 0.11
A8: 구간 3 | C8: =Inputs!B100 -> 20000 | D8: =IF(ISBLANK(Inputs!C100),"",Inputs!C100) -> 300000 | E8: =Inputs!D100 -> 0.242 | F8: =E8-N(E7) -> 0.022
A9: 구간 4 | C9: =Inputs!B101 -> 300000 | D9: =IF(ISBLANK(Inputs!C101),"",Inputs!C101) | E9: =Inputs!D101 -> 0.275 | F9: =E9-N(E8) -> 0.033
A11: 기초 비율 — 연결 과거 값(FS_Hist), 과거 3년 평균
C12: FY2023 | D12: FY2024 | E12: FY2025 | F12: 평균
A13: 영업이익률 | C13: =(FS_Hist!$F$10)/(FS_Hist!$F$8) -> 0.31979196 | D13: =(FS_Hist!$G$10)/(FS_Hist!$G$8) -> 0.01454955 | E13: =(FS_Hist!$H$10)/(FS_Hist!$H$8) -> -0.48680058 | F13: =AVERAGE(C13:E13) -> -0.050819691
A14: D&A ÷ 매출 | C14: =IF(ISNUMBER(FS_Hist!$F$16),(FS_Hist!$F$16)/(FS_Hist!$F$8),"n/a") -> 0.022709995 | D14: =IF(ISNUMBER(FS_Hist!$G$16),(FS_Hist!$G$16)/(FS_Hist!$G$8),"n/a") -> 0.018164847 | E14: =IF(ISNUMBER(FS_Hist!$H$16),(FS_Hist!$H$16)/(FS_Hist!$H$8),"n/a") -> 0.031622372 | F14: =AVERAGE(C14:E14) -> 0.024165738
A15: CAPEX ÷ 매출(유형 + 무형) | C15: =(FS_Hist!$F$14+FS_Hist!$F$15)/(FS_Hist!$F$8) -> 0.00041248101 | D15: =(FS_Hist!$G$14+FS_Hist!$G$15)/(FS_Hist!$G$8) -> 0.013538426 | E15: =(FS_Hist!$H$14+FS_Hist!$H$15)/(FS_Hist!$H$8) -> 0.025405628 | F15: =AVERAGE(C15:E15) -> 0.013118845
A16: 매출원가율 | C16: =(FS_Hist!$F$9)/(FS_Hist!$F$8) -> 0.020531721 | D16: =(FS_Hist!$G$9)/(FS_Hist!$G$8) -> 0.017518503 | E16: =(FS_Hist!$H$9)/(FS_Hist!$H$8) -> 0.027078171 | F16: =AVERAGE(C16:E16) -> 0.021709465
A17: 매출채권 회전일수(매출 기준) | C17: =IF((FS_Hist!$F$8)=0,"n/a",(FS_Hist!$F$18)/(FS_Hist!$F$8)*DaysYr) -> 213.63928 | D17: =IF((FS_Hist!$G$8)=0,"n/a",(FS_Hist!$G$18)/(FS_Hist!$G$8)*DaysYr) -> 90.861235 | E17: =IF((FS_Hist!$H$8)=0,"n/a",(FS_Hist!$H$18)/(FS_Hist!$H$8)*DaysYr) -> 56.524134 | F17: =IF(COUNT(C17:E17)=0,0,AVERAGE(C17:E17)) -> 120.34155
A18: 재고 회전일수(매출원가 기준) | C18: =IF((FS_Hist!$F$9)=0,"n/a",(FS_Hist!$F$19)/(FS_Hist!$F$9)*DaysYr) -> 3.6566367 | D18: =IF((FS_Hist!$G$9)=0,"n/a",(FS_Hist!$G$19)/(FS_Hist!$G$9)*DaysYr) -> 3.7681029 | E18: =IF((FS_Hist!$H$9)=0,"n/a",(FS_Hist!$H$19)/(FS_Hist!$H$9)*DaysYr) -> 0 | F18: =IF(COUNT(C18:E18)=0,0,AVERAGE(C18:E18)) -> 2.4749132
A19: 매입채무 회전일수(매출원가 기준) | C19: =IF((FS_Hist!$F$9)=0,"n/a",(FS_Hist!$F$20)/(FS_Hist!$F$9)*DaysYr) -> 9957.9163 | D19: =IF((FS_Hist!$G$9)=0,"n/a",(FS_Hist!$G$20)/(FS_Hist!$G$9)*DaysYr) -> 3120.6809 | E19: =IF((FS_Hist!$H$9)=0,"n/a",(FS_Hist!$H$20)/(FS_Hist!$H$9)*DaysYr) -> 1590.2875 | F19: =IF(COUNT(C19:E19)=0,0,AVERAGE(C19:E19)) -> 4889.6282
A20: 기초 투하자본(전년 말) | C20: =FS_Hist!$E$18+FS_Hist!$E$19-FS_Hist!$E$20+FS_Hist!$E$21+FS_Hist!$E$22+FS_Hist!$E$23 -> 3743.7428 | D20: =FS_Hist!$F$18+FS_Hist!$F$19-FS_Hist!$F$20+FS_Hist!$F$21+FS_Hist!$F$22+FS_Hist!$F$23 -> 308.7531 | E20: =FS_Hist!$G$18+FS_Hist!$G$19-FS_Hist!$G$20+FS_Hist!$G$21+FS_Hist!$G$22+FS_Hist!$G$23 -> 813.92134
A21: NOPAT = 영업이익 − 누진 세금 | C21: =FS_Hist!$F$10-IF(FS_Hist!$F$10>0,SUMPRODUCT((FS_Hist!$F$10>TaxFrom)*(FS_Hist!$F$10-TaxFrom)*TaxDRate),0) -> 1155.86 | D21: =FS_Hist!$G$10-IF(FS_Hist!$G$10>0,SUMPRODUCT((FS_Hist!$G$10>TaxFrom)*(FS_Hist!$G$10-TaxFrom)*TaxDRate),0) -> 66.94595 | E21: =FS_Hist!$H$10-IF(FS_Hist!$H$10>0,SUMPRODUCT((FS_Hist!$H$10>TaxFrom)*(FS_Hist!$H$10-TaxFrom)*TaxDRate),0) -> -1794.8232
A22: ROIC(기초 투하자본 > 0일 때) | C22: =IF(C20>0,C21/C20,"") -> 0.30874451 | D22: =IF(D20>0,D21/D20,"") -> 0.21682681 | E22: =IF(E20>0,E21/E20,"") -> -2.2051556 | F22: =AVERAGE(C22:E22) -> -0.55986143 | G22: RONIC 상한(사전 고정)
A24: 매출 5년 CAGR(FY2020 → FY2025) | B24: % | C24: =(FS_Hist!$H$8/FS_Hist!$C$8)^(1/(2025-2020))-1 -> 0.0081194842
A25: 순운전자본(기초, 2026-06-30) | B25: 백만원 | C25: =FS_Hist!$J$18+FS_Hist!$J$19-FS_Hist!$J$20 -> 304.03032 | D25: 매출채권 + 재고 − 매입채무
A26: 2026 상반기 매출(연결) | B26: 백만원 | C26: =FS_Hist!$J$8 -> 1699.4526
A27: 2026 상반기 영업이익(연결) | B27: 백만원 | C27: =FS_Hist!$J$10 -> -259.27283
A28: FY2025 매출(연결) | B28: 백만원 | C28: =FS_Hist!$H$8 -> 3686.9784
A29: LTM 세전이익(세후 Kd 한계세율 기준) | B29: 백만원 | C29: =FS_Hist!$H$11+FS_Hist!$J$11-FS_Hist!$I$11 -> -4703.86
A31: 기본 경로 v2 — 5년 이익률 중앙값, 피어 쪽 수렴, 성장률 혼합(사전 고정 91a84dd)
A32: 영업이익률 FY2021~2025(매출 > 0인 해) | C32: =IF(FS_Hist!$D$8>0,FS_Hist!$D$10/FS_Hist!$D$8,"n/a") -> 0.4136115 | D32: =IF(FS_Hist!$E$8>0,FS_Hist!$E$10/FS_Hist!$E$8,"n/a") -> -0.098104633 | E32: =IF(FS_Hist!$F$8>0,FS_Hist!$F$10/FS_Hist!$F$8,"n/a") -> 0.31979196 | F32: =IF(FS_Hist!$G$8>0,FS_Hist!$G$10/FS_Hist!$G$8,"n/a") -> 0.01454955 | G32: =IF(FS_Hist!$H$8>0,FS_Hist!$H$10/FS_Hist!$H$8,"n/a") -> -0.48680058
A33: 출발 정상 이익률 v2 = 중앙값(3년 이상), 아니면 3년 평균 | B33: % | C33: =IF(COUNT(C32:G32)>=3,MEDIAN(C32:G32),HistMargin) -> 0.01454955
A34: 2032년까지 피어 쪽 이동 폭 = 수렴 비율 × (피어 중앙값 − 출발) | B34: % | C34: =IF(ISNUMBER(PeerMarginV2),ConvShare*(PeerMarginV2-M0V2),0) -> 0.054500896 | D34: 체감·영구 구간 = 출발 + 이동 폭
A35: 출발 성장률 v2 = clip(가중 × CAGR + (1 − 가중) × 피어 성장률) | B35: % | C35: =MAX(ClipLo,MIN(ClipHi,IF(ISNUMBER(PeerGrowthV2),WOwn*CAGR+(1-WOwn)*PeerGrowthV2,CAGR))) -> 0.014420192
A37: 시나리오 파라미터 — Inputs 표 3 연결, '선택' 열 = INDEX(…, 선택 순번)
A38: 선택 순번 | B38: =MATCH(ScenSel,ScenNames,0) -> 2 | C38: 비관 | D38: 기본 | E38: 낙관 | F38: 선택
A39: 출발 성장률 이동 | C39: =Inputs!B120 -> -0.02 | D39: =Inputs!C120 -> 0 | E39: =Inputs!D120 -> 0.02 | F39: =IF(ISNUMBER(GrowthShiftOvr),GrowthShiftOvr,INDEX(C39:E39,ScenIdx)) -> 0
A40: 정상 이익률 이동 | C40: =Inputs!B121 -> -0.02 | D40: =Inputs!C121 -> 0 | E40: =Inputs!D121 -> 0.02 | F40: =IF(ISNUMBER(MarginShiftOvr),MarginShiftOvr,INDEX(C40:E40,ScenIdx)) -> 0
A41: 출발 성장률 = v2 출발 성장률 + 이동 | C41: =G0Base+C39 -> -0.0055798084 | D41: =G0Base+D39 -> 0.014420192 | E41: =G0Base+E39 -> 0.034420192 | F41: =G0Base+F39 -> 0.014420192
A42: 출발 정상 영업이익률 = v2 중앙값 + 이동 | C42: =M0V2+C40 -> -0.0054504496 | D42: =M0V2+D40 -> 0.01454955 | E42: =M0V2+E40 -> 0.03454955 | F42: =M0V2+F40 -> 0.01454955
A43: 명시 마지막 연도 성장률 | C43: =C41+(GTermCfg-C41)*MIN(ExplicitEnd-YEAR(CfStart),FadeTo-YEAR(CfStart))/(FadeTo-YEAR(CfStart)) -> 0.02 | D43: =D41+(GTermCfg-D41)*MIN(ExplicitEnd-YEAR(CfStart),FadeTo-YEAR(CfStart))/(FadeTo-YEAR(CfStart)) -> 0.02 | E43: =E41+(GTermCfg-E41)*MIN(ExplicitEnd-YEAR(CfStart),FadeTo-YEAR(CfStart))/(FadeTo-YEAR(CfStart)) -> 0.02 | F43: =F41+(GTermCfg-F41)*MIN(ExplicitEnd-YEAR(CfStart),FadeTo-YEAR(CfStart))/(FadeTo-YEAR(CfStart)) -> 0.02
A44: 영구성장률(설정) | B44: % | C44: =GTermCfg -> 0.02
A45: 영구·체감 구간 g(데이터 표 입력 칸이 비면 시나리오 값) | B45: % | C45: =IF(ISNUMBER(GOvr),GOvr,GTerm_Sel) -> 0.02 | D45: Scenarios 시트의 데이터 표가 GOvr 칸에 값을 넣어 계산한다
A47: 예측 (기초 열 = 2026-06-30 재무상태표) | C47: 기초 | D47: =IF(D48=1,"2H"&RIGHT(D49,2),""&D49) -> 2H26 | E47: =IF(E48=1,"2H"&RIGHT(E49,2),""&E49) -> 2027 | F47: =IF(F48=1,"2H"&RIGHT(F49,2),""&F49) -> 2028 | G47: =IF(G48=1,"2H"&RIGHT(G49,2),""&G49) -> 2029 | H47: =IF(H48=1,"2H"&RIGHT(H49,2),""&H49) -> 2030 | I47: =IF(I48=1,"2H"&RIGHT(I49,2),""&I49) -> 2031 | J47: =IF(J48=1,"2H"&RIGHT(J49,2),""&J49) -> 2032 | K47: =IF(K48=1,"2H"&RIGHT(K49,2),""&K49) -> 2033 | ... R47: =IF(R48=1,"2H"&RIGHT(R49,2),""&R49) -> 2040
A48: 기간 순번 | C48: 0 | D48: =C48+1 -> 1 | E48: =D48+1 -> 2 | F48: =E48+1 -> 3 | G48: =F48+1 -> 4 | H48: =G48+1 -> 5 | I48: =H48+1 -> 6 | J48: =I48+1 -> 7 | K48: =J48+1 -> 8 | ... R48: =Q48+1 -> 15
A49: 연도 | D49: =YEAR(CfStart)+D48-1 -> 2026 | E49: =YEAR(CfStart)+E48-1 -> 2027 | F49: =YEAR(CfStart)+F48-1 -> 2028 | G49: =YEAR(CfStart)+G48-1 -> 2029 | H49: =YEAR(CfStart)+H48-1 -> 2030 | I49: =YEAR(CfStart)+I48-1 -> 2031 | J49: =YEAR(CfStart)+J48-1 -> 2032 | K49: =YEAR(CfStart)+K48-1 -> 2033 | ... R49: =YEAR(CfStart)+R48-1 -> 2040
A50: 구간 | D50: =IF(D54=1,"명시","체감") -> 명시 | E50: =IF(E54=1,"명시","체감") -> 명시 | F50: =IF(F54=1,"명시","체감") -> 명시 | G50: =IF(G54=1,"명시","체감") -> 명시 | H50: =IF(H54=1,"명시","체감") -> 명시 | I50: =IF(I54=1,"명시","체감") -> 명시 | J50: =IF(J54=1,"명시","체감") -> 명시 | K50: =IF(K54=1,"명시","체감") -> 체감 | ... R50: =IF(R54=1,"명시","체감") -> 체감
A51: 시작일 | D51: =MAX(DATE(D49,1,1),CfStart) -> 46204 | E51: =MAX(DATE(E49,1,1),CfStart) -> 46388 | F51: =MAX(DATE(F49,1,1),CfStart) -> 46753 | G51: =MAX(DATE(G49,1,1),CfStart) -> 47119 | H51: =MAX(DATE(H49,1,1),CfStart) -> 47484 | I51: =MAX(DATE(I49,1,1),CfStart) -> 47849 | J51: =MAX(DATE(J49,1,1),CfStart) -> 48214 | K51: =MAX(DATE(K49,1,1),CfStart) -> 48580 | ... R51: =MAX(DATE(R49,1,1),CfStart) -> 51136
A52: 종료일 | D52: =DATE(D49,12,31) -> 46387 | E52: =DATE(E49,12,31) -> 46752 | F52: =DATE(F49,12,31) -> 47118 | G52: =DATE(G49,12,31) -> 47483 | H52: =DATE(H49,12,31) -> 47848 | I52: =DATE(I49,12,31) -> 48213 | J52: =DATE(J49,12,31) -> 48579 | K52: =DATE(K49,12,31) -> 48944 | ... R52: =DATE(R49,12,31) -> 51501
A53: 기간 비율(일수 ÷ 365) | D53: =(D52-D51+1)/DaysYr -> 0.50410959 | E53: =(E52-E51+1)/DaysYr -> 1 | F53: =(F52-F51+1)/DaysYr -> 1.0027397 | G53: =(G52-G51+1)/DaysYr -> 1 | H53: =(H52-H51+1)/DaysYr -> 1 | I53: =(I52-I51+1)/DaysYr -> 1 | J53: =(J52-J51+1)/DaysYr -> 1.0027397 | K53: =(K52-K51+1)/DaysYr -> 1 | ... R53: =(R52-R51+1)/DaysYr -> 1.0027397
A54: 명시 구간(1/0) | D54: =IF(D49<=ExplicitEnd,1,0) -> 1 | E54: =IF(E49<=ExplicitEnd,1,0) -> 1 | F54: =IF(F49<=ExplicitEnd,1,0) -> 1 | G54: =IF(G49<=ExplicitEnd,1,0) -> 1 | H54: =IF(H49<=ExplicitEnd,1,0) -> 1 | I54: =IF(I49<=ExplicitEnd,1,0) -> 1 | J54: =IF(J49<=ExplicitEnd,1,0) -> 1 | K54: =IF(K49<=ExplicitEnd,1,0) -> 0 | ... R54: =IF(R49<=ExplicitEnd,1,0) -> 0
A55: 매출 성장률 | B55: % | D55: =IF(D54=1,G0_Sel+(GTermCfg-G0_Sel)*MIN(D49-YEAR(CfStart),FadeTo-YEAR(CfStart))/(FadeTo-YEAR(CfStart)),GLast_Sel-(D49-ExplicitEnd)*(GLast_Sel-GEff)/FadeYears) -> 0.014420192 | E55: =IF(E54=1,G0_Sel+(GTermCfg-G0_Sel)*MIN(E49-YEAR(CfStart),FadeTo-YEAR(CfStart))/(FadeTo-YEAR(CfStart)),GLast_Sel-(E49-ExplicitEnd)*(GLast_Sel-GEff)/FadeYears) -> 0.015815144 | F55: =IF(F54=1,G0_Sel+(GTermCfg-G0_Sel)*MIN(F49-YEAR(CfStart),FadeTo-YEAR(CfStart))/(FadeTo-YEAR(CfStart)),GLast_Sel-(F49-ExplicitEnd)*(GLast_Sel-GEff)/FadeYears) -> 0.017210096 | G55: =IF(G54=1,G0_Sel+(GTermCfg-G0_Sel)*MIN(G49-YEAR(CfStart),FadeTo-YEAR(CfStart))/(FadeTo-YEAR(CfStart)),GLast_Sel-(G49-ExplicitEnd)*(GLast_Sel-GEff)/FadeYears) -> 0.018605048 | H55: =IF(H54=1,G0_Sel+(GTermCfg-G0_Sel)*MIN(H49-YEAR(CfStart),FadeTo-YEAR(CfStart))/(FadeTo-YEAR(CfStart)),GLast_Sel-(H49-ExplicitEnd)*(GLast_Sel-GEff)/FadeYears) -> 0.02 | I55: =IF(I54=1,G0_Sel+(GTermCfg-G0_Sel)*MIN(I49-YEAR(CfStart),FadeTo-YEAR(CfStart))/(FadeTo-YEAR(CfStart)),GLast_Sel-(I49-ExplicitEnd)*(GLast_Sel-GEff)/FadeYears) -> 0.02 | J55: =IF(J54=1,G0_Sel+(GTermCfg-G0_Sel)*MIN(J49-YEAR(CfStart),FadeTo-YEAR(CfStart))/(FadeTo-YEAR(CfStart)),GLast_Sel-(J49-ExplicitEnd)*(GLast_Sel-GEff)/FadeYears) -> 0.02 | K55: =IF(K54=1,G0_Sel+(GTermCfg-G0_Sel)*MIN(K49-YEAR(CfStart),FadeTo-YEAR(CfStart))/(FadeTo-YEAR(CfStart)),GLast_Sel-(K49-ExplicitEnd)*(GLast_Sel-GEff)/FadeYears) -> 0.02 | ... R55: =IF(R54=1,G0_Sel+(GTermCfg-G0_Sel)*MIN(R49-YEAR(CfStart),FadeTo-YEAR(CfStart))/(FadeTo-YEAR(CfStart)),GLast_Sel-(R49-ExplicitEnd)*(GLast_Sel-GEff)/FadeYears) -> 0.02
A56: 회계연도 매출 | B56: 백만원 | D56: =IF(D48=1,RevFY_Last*(1+D55),C56*(1+D55)) -> 3740.1453 | E56: =IF(E48=1,RevFY_Last*(1+E55),D56*(1+E55)) -> 3799.2962 | F56: =IF(F48=1,RevFY_Last*(1+F55),E56*(1+F55)) -> 3864.6825 | G56: =IF(G48=1,RevFY_Last*(1+G55),F56*(1+G55)) -> 3936.5851 | H56: =IF(H48=1,RevFY_Last*(1+H55),G56*(1+H55)) -> 4015.3168 | I56: =IF(I48=1,RevFY_Last*(1+I55),H56*(1+I55)) -> 4095.6231 | J56: =IF(J48=1,RevFY_Last*(1+J55),I56*(1+J55)) -> 4177.5356 | K56: =IF(K48=1,RevFY_Last*(1+K55),J56*(1+K55)) -> 4261.0863 | ... R56: =IF(R48=1,RevFY_Last*(1+R55),Q56*(1+R55)) -> 4894.6488
A57: 기간 매출 | B57: 백만원 | D57: =IF(D48=1,D56-H1Rev,D56) -> 2040.6927 | E57: =IF(E48=1,E56-H1Rev,E56) -> 3799.2962 | F57: =IF(F48=1,F56-H1Rev,F56) -> 3864.6825 | G57: =IF(G48=1,G56-H1Rev,G56) -> 3936.5851 | H57: =IF(H48=1,H56-H1Rev,H56) -> 4015.3168 | I57: =IF(I48=1,I56-H1Rev,I56) -> 4095.6231 | J57: =IF(J48=1,J56-H1Rev,J56) -> 4177.5356 | K57: =IF(K48=1,K56-H1Rev,K56) -> 4261.0863 | ... R57: =IF(R48=1,R56-H1Rev,R56) -> 4894.6488
A58: 영업이익(EBIT) | B58: 백만원 | D58: =D57*(Margin_Sel+MarginConvAmt*MIN((D49-YEAR(CfStart))/(ExplicitEnd-YEAR(CfStart)),1)) -> 29.691162 | E58: =E57*(Margin_Sel+MarginConvAmt*MIN((E49-YEAR(CfStart))/(ExplicitEnd-YEAR(CfStart)),1)) -> 89.788893 | F58: =F57*(Margin_Sel+MarginConvAmt*MIN((F49-YEAR(CfStart))/(ExplicitEnd-YEAR(CfStart)),1)) -> 126.43894 | G58: =G57*(Margin_Sel+MarginConvAmt*MIN((G49-YEAR(CfStart))/(ExplicitEnd-YEAR(CfStart)),1)) -> 164.54925 | H58: =H57*(Margin_Sel+MarginConvAmt*MIN((H49-YEAR(CfStart))/(ExplicitEnd-YEAR(CfStart)),1)) -> 204.3133 | I58: =I57*(Margin_Sel+MarginConvAmt*MIN((I49-YEAR(CfStart))/(ExplicitEnd-YEAR(CfStart)),1)) -> 245.60208 | J58: =J57*(Margin_Sel+MarginConvAmt*MIN((J49-YEAR(CfStart))/(ExplicitEnd-YEAR(CfStart)),1)) -> 288.4607 | K58: =K57*(Margin_Sel+MarginConvAmt*MIN((K49-YEAR(CfStart))/(ExplicitEnd-YEAR(CfStart)),1)) -> 294.22991 | ... R58: =R57*(Margin_Sel+MarginConvAmt*MIN((R49-YEAR(CfStart))/(ExplicitEnd-YEAR(CfStart)),1)) -> 337.97768
A59: 회계연도 영업이익(과세표준) | B59: 백만원 | D59: =IF(D48=1,H1Op+D58,D58) -> -229.58167 | E59: =IF(E48=1,H1Op+E58,E58) -> 89.788893 | F59: =IF(F48=1,H1Op+F58,F58) -> 126.43894 | G59: =IF(G48=1,H1Op+G58,G58) -> 164.54925 | H59: =IF(H48=1,H1Op+H58,H58) -> 204.3133 | I59: =IF(I48=1,H1Op+I58,I58) -> 245.60208 | J59: =IF(J48=1,H1Op+J58,J58) -> 288.4607 | K59: =IF(K48=1,H1Op+K58,K58) -> 294.22991 | ... R59: =IF(R48=1,H1Op+R58,R58) -> 337.97768
A60: D&A = 매출 × 과거 3년 D&A/매출 | B60: 백만원 | D60: =IF(D54=1,D57*DnaRatio,0) -> 49.314845 | E60: =IF(E54=1,E57*DnaRatio,0) -> 91.812796 | F60: =IF(F54=1,F57*DnaRatio,0) -> 93.392903 | G60: =IF(G54=1,G57*DnaRatio,0) -> 95.130482 | H60: =IF(H54=1,H57*DnaRatio,0) -> 97.033092 | I60: =IF(I54=1,I57*DnaRatio,0) -> 98.973754 | J60: =IF(J54=1,J57*DnaRatio,0) -> 100.95323 | K60: =IF(K54=1,K57*DnaRatio,0) -> 0 | ... R60: =IF(R54=1,R57*DnaRatio,0) -> 0
A61: CAPEX = 매출 × 과거 3년 CAPEX/매출 | B61: 백만원 | D61: =IF(D54=1,D57*CapexRatio,0) -> 26.771532 | E61: =IF(E54=1,E57*CapexRatio,0) -> 49.842378 | F61: =IF(F54=1,F57*CapexRatio,0) -> 50.700171 | G61: =IF(G54=1,G57*CapexRatio,0) -> 51.64345 | H61: =IF(H54=1,H57*CapexRatio,0) -> 52.676319 | I61: =IF(I54=1,I57*CapexRatio,0) -> 53.729845 | J61: =IF(J54=1,J57*CapexRatio,0) -> 54.804442 | K61: =IF(K54=1,K57*CapexRatio,0) -> 0 | ... R61: =IF(R54=1,R57*CapexRatio,0) -> 0
A62: 순운전자본(기말) | B62: 백만원 | C62: =NWC_Open -> 304.03032 | D62: =IF(D54=1,D56*DSO/DaysYr+D56*COGSR*DIO/DaysYr-D56*COGSR*DPO/DaysYr,C62) -> 145.95858 | E62: =IF(E54=1,E56*DSO/DaysYr+E56*COGSR*DIO/DaysYr-E56*COGSR*DPO/DaysYr,D62) -> 148.26693 | F62: =IF(F54=1,F56*DSO/DaysYr+F56*COGSR*DIO/DaysYr-F56*COGSR*DPO/DaysYr,E62) -> 150.81862 | G62: =IF(G54=1,G56*DSO/DaysYr+G56*COGSR*DIO/DaysYr-G56*COGSR*DPO/DaysYr,F62) -> 153.62461 | H62: =IF(H54=1,H56*DSO/DaysYr+H56*COGSR*DIO/DaysYr-H56*COGSR*DPO/DaysYr,G62) -> 156.6971 | I62: =IF(I54=1,I56*DSO/DaysYr+I56*COGSR*DIO/DaysYr-I56*COGSR*DPO/DaysYr,H62) -> 159.83104 | J62: =IF(J54=1,J56*DSO/DaysYr+J56*COGSR*DIO/DaysYr-J56*COGSR*DPO/DaysYr,I62) -> 163.02767 | K62: =IF(K54=1,K56*DSO/DaysYr+K56*COGSR*DIO/DaysYr-K56*COGSR*DPO/DaysYr,J62) -> 163.02767 | ... R62: =IF(R54=1,R56*DSO/DaysYr+R56*COGSR*DIO/DaysYr-R56*COGSR*DPO/DaysYr,Q62) -> 163.02767
A63: ΔNWC(증가 = 유출) | B63: 백만원 | D63: =IF(D54=1,D62-C62,0) -> -158.07174 | E63: =IF(E54=1,E62-D62,0) -> 2.3083559 | F63: =IF(F54=1,F62-E62,0) -> 2.5516881 | G63: =IF(G54=1,G62-F62,0) -> 2.8059877 | H63: =IF(H54=1,H62-G62,0) -> 3.0724922 | I63: =IF(I54=1,I62-H62,0) -> 3.1339421 | J63: =IF(J54=1,J62-I62,0) -> 3.1966209 | K63: =IF(K54=1,K62-J62,0) -> 0 | ... R63: =IF(R54=1,R62-Q62,0) -> 0
A64: 실효세율(누진, 회계연도 과세표준) | B64: % | D64: =IF(D59>0,IF(D59>0,SUMPRODUCT((D59>TaxFrom)*(D59-TaxFrom)*TaxDRate),0)/D59,0) -> 0 | E64: =IF(E59>0,IF(E59>0,SUMPRODUCT((E59>TaxFrom)*(E59-TaxFrom)*TaxDRate),0)/E59,0) -> 0.11 | F64: =IF(F59>0,IF(F59>0,SUMPRODUCT((F59>TaxFrom)*(F59-TaxFrom)*TaxDRate),0)/F59,0) -> 0.11 | G64: =IF(G59>0,IF(G59>0,SUMPRODUCT((G59>TaxFrom)*(G59-TaxFrom)*TaxDRate),0)/G59,0) -> 0.11 | H64: =IF(H59>0,IF(H59>0,SUMPRODUCT((H59>TaxFrom)*(H59-TaxFrom)*TaxDRate),0)/H59,0) -> 0.11232223 | I64: =IF(I59>0,IF(I59>0,SUMPRODUCT((I59>TaxFrom)*(I59-TaxFrom)*TaxDRate),0)/I59,0) -> 0.13042421 | J64: =IF(J59>0,IF(J59>0,SUMPRODUCT((J59>TaxFrom)*(J59-TaxFrom)*TaxDRate),0)/J59,0) -> 0.14373311 | K64: =IF(K59>0,IF(K59>0,SUMPRODUCT((K59>TaxFrom)*(K59-TaxFrom)*TaxDRate),0)/K59,0) -> 0.14522854 | ... R64: =IF(R59>0,IF(R59>0,SUMPRODUCT((R59>TaxFrom)*(R59-TaxFrom)*TaxDRate),0)/R59,0) -> 0.15490694
A65: 법인세 | B65: 백만원 | D65: =MAX(D58,0)*D64 -> 0 | E65: =MAX(E58,0)*E64 -> 9.8767783 | F65: =MAX(F58,0)*F64 -> 13.908284 | G65: =MAX(G58,0)*G64 -> 18.100417 | H65: =MAX(H58,0)*H64 -> 22.948925 | I65: =MAX(I58,0)*I64 -> 32.032458 | J65: =MAX(J58,0)*J64 -> 41.461353 | K65: =MAX(K58,0)*K64 -> 42.73058 | ... R65: =MAX(R58,0)*R64 -> 52.35509
A66: NOPAT | B66: 백만원 | D66: =D58-D65 -> 29.691162 | E66: =E58-E65 -> 79.912115 | F66: =F58-F65 -> 112.53066 | G66: =G58-G65 -> 146.44883 | H66: =H58-H65 -> 181.36437 | I66: =I58-I65 -> 213.56962 | J66: =J58-J65 -> 246.99934 | K66: =K58-K65 -> 251.49933 | ... R66: =R58-R65 -> 285.62259
A67: 체감 구간 재투자율 g ÷ RONIC | B67: % | D67: =IF(D54=1,0,D55/RONIC) -> 0 | E67: =IF(E54=1,0,E55/RONIC) -> 0 | F67: =IF(F54=1,0,F55/RONIC) -> 0 | G67: =IF(G54=1,0,G55/RONIC) -> 0 | H67: =IF(H54=1,0,H55/RONIC) -> 0 | I67: =IF(I54=1,0,I55/RONIC) -> 0 | J67: =IF(J54=1,0,J55/RONIC) -> 0 | K67: =IF(K54=1,0,K55/RONIC) -> 0.21710519 | ... R67: =IF(R54=1,0,R55/RONIC) -> 0.21710519
A68: 체감 구간 재투자 | B68: 백만원 | D68: =D66*D67 -> 0 | E68: =E66*E67 -> 0 | F68: =F66*F67 -> 0 | G68: =G66*G67 -> 0 | H68: =H66*H67 -> 0 | I68: =I66*I67 -> 0 | J68: =J66*J67 -> 0 | K68: =K66*K67 -> 54.60181 | ... R68: =R66*R67 -> 62.010147
A69: FCFF | B69: 백만원 | D69: =D66+D60-D61-D63-D68 -> 210.30621 | E69: =E66+E60-E61-E63-E68 -> 119.57418 | F69: =F66+F60-F61-F63-F68 -> 152.67171 | G69: =G66+G60-G61-G63-G68 -> 187.12988 | H69: =H66+H60-H61-H63-H68 -> 222.64865 | I69: =I66+I60-I61-I63-I68 -> 255.67959 | J69: =J66+J60-J61-J63-J68 -> 289.95151 | K69: =K66+K60-K61-K63-K68 -> 196.89752 | ... R69: =R66+R60-R61-R63-R68 -> 223.61244
A70: EBITDA | B70: 백만원 | D70: =D58+D60 -> 79.006007 | E70: =E58+E60 -> 181.60169 | F70: =F58+F60 -> 219.83185 | G70: =G58+G60 -> 259.67973 | H70: =H58+H60 -> 301.34639 | I70: =I58+I60 -> 344.57584 | J70: =J58+J60 -> 389.41392 | K70: =K58+K60 -> 294.22991 | ... R70: =R58+R60 -> 337.97768
A73: 사업계획 검증 — 예측(선택 시나리오) vs 과거 (표시만, 괴리 경고 기준은 사람 판단) | F73: 참고: P5-B 스팩 합병 외부평가 추정의 실제 달성률(실적 ÷ 예측, 표시만) 🔸
A74: 과거 매출 CAGR(연결 FY2020 → FY2025) | B74: % | C74: =CAGR -> 0.0081194842 | F74: 계정 | G74: 차연도 h | H74: n | I74: 달성률 중앙값 | J74: Q1 | K74: Q3
A75: 예측 FY2026 매출 성장률(직전 회계연도 대비) | B75: % | C75: =Forecast!D56/RevFY_Last-1 -> 0.014420192 | F75: 매출 | G75: 1 | H75: 86 | I75: 0.8421506 | J75: 0.7074825 | K75: 0.95438191
A76: 예측 매출 CAGR(FY2026 → 명시 마지막 연도) | B76: % | C76: =(INDEX(Forecast!$D$56:$R$56,MATCH(ExplicitEnd,Forecast!$D$49:$R$49,0))/Forecast!D56)^(1/(ExplicitEnd-YEAR(CfStart)))-1 -> 0.018603773 | F76: 매출 | G76: 2 | H76: 72 | I76: 0.76062242 | J76: 0.59764563 | K76: 0.88605666
A77: 차이(예측 CAGR − 과거 CAGR) | B77: % | C77: =PlanFcCAGR-PlanHistCAGR -> 0.010484289 | F77: 매출 | G77: 3 | H77: 62 | I77: 0.72454703 | J77: 0.48126332 | K77: 0.91472553
A78: 과거 영업이익률 평균(연결 FY2023~FY2025) | B78: % | C78: =HistMargin -> -0.050819691 | F78: 영업이익 | G78: 1 | H78: 89 | I78: 0.39829567 | J78: 0.098738311 | K78: 0.66555286
A79: 예측 정상 영업이익률 | B79: % | C79: =Margin_Sel -> 0.01454955 | F79: 영업이익 | G79: 2 | H79: 75 | I79: 0.31400106 | J79: -0.021301029 | K79: 0.57888972
A80: 차이(예측 − 과거) | B80: % | C80: =PlanMargin-PlanHistMargin -> 0.065369241 | F80: 영업이익 | G80: 3 | H80: 65 | I80: 0.1765892 | J80: -0.048739342 | K80: 0.42909249
F81: 스팩 합병 외부평가 추정 기준 참고값. 대상 회사와 상황이 다름. 달성률은 예측이 분모라 높은 예측일수록 낮게 나오는 기계적 성분이 있음
F82: 출처: reports/p5b_final.md (커밋 0a8d7c6), DB p5b_error·p5b_forecast·p5b_srp_cites. 거래 목록은 넣지 않음(집계값만)
F84: 예측 매출 CAGR 구간별 매출 달성률 중앙값(스팩, 사분위 4구간, 기준 86건)
F85: 구간 | G85: CAGR 하한 | H85: CAGR 상한 | I85: 거래 수 | J85: 1차 중앙값 | K85: 1차 n | L85: 2차 중앙값 | M85: 2차 n | N85: 3차 중앙값 | O85: 3차 n
F86: 1구간(하위 25%) | G86: 0.011473173 | H86: 0.095236454 | I86: 22 | J86: 0.89888091 | K86: 22 | L86: 0.85667237 | M86: 17 | N86: 0.82364668 | O86: 16
F87: 2구간 | G87: 0.095236454 | H87: 0.14085439 | I87: 21 | J87: 0.83530124 | K87: 21 | L87: 0.81079711 | M87: 16 | N87: 0.65009863 | O87: 15
F88: 3구간 | G88: 0.14085439 | H88: 0.24175148 | I88: 21 | J88: 0.87316236 | K88: 21 | L88: 0.77370633 | M88: 20 | N88: 0.74939621 | O88: 16
F89: 4구간(상위 25%) | G89: 0.24175148 | H89: 1.3322277 | I89: 22 | J89: 0.73875495 | K89: 22 | L89: 0.54700169 | M89: 19 | N89: 0.59931419 | O89: 15
F91: 비교 기준 추정 연수(의견서 추정 기간 중앙값) | J91: 5
F92: 대상 회사 예측 매출 CAGR(첫 추정 회계연도부터 N개 연도, 선택 시나리오) | J92: =(INDEX(Forecast!$D$56:$R$56,MATCH(YEAR(CfStart)+$J$91-1,Forecast!$D$49:$R$49,0))/Forecast!$D$56)^(1/($J$91-1))-1 -> 0.017906377
F93: 해당 구간(1~4) | J93: =IF(PlanFcCAGR5>=$G$89,4,IF(PlanFcCAGR5>=$G$88,3,IF(PlanFcCAGR5>=$G$87,2,1))) -> 1 | K93: =IF(OR(PlanFcCAGR5<$G$86,PlanFcCAGR5>$H$89),"표본 범위 밖(참고만)","표본 범위 안") -> 표본 범위 안
F94: 그 구간 매출 달성률 중앙값 1차 / 2차 / 3차 | J94: =INDEX($J$86:$J$89,PlanBand) -> 0.89888091 | K94: =INDEX($L$86:$L$89,PlanBand) -> 0.85667237 | L94: =INDEX($N$86:$N$89,PlanBand) -> 0.82364668
F95: 표시만: 예측을 자동으로 깎거나 경고 판정하지 않는다. 비교 기준이 다름(스팩 합병 의견서 5년 추정 vs 이 모델)

Sheet WACC
A1: WACC — 피어 베타 → 할인율
A2: 원 β → Blume(0.67 β + 0.33) → Hamada 언레버(회사별 기간평균 D/E, t 22%) → 포함 피어 중앙값. 회귀 결과는 한국거래소 통계정보 기반
A5: 포함 피어 수 | B5: 곳 | C5: =BetaPubN -> 6
A6: βu(공개 모드 집계 입력) | C6: =BetaPubU -> 0.62399371 | D6: 엔진 βu 중앙값 | E6: 0.62399371
A7: R² 중앙값(포함 피어, 집계 입력) | C7: =BetaPubR2 -> 0.15
A8: 베타 신뢰성 경고 | C8: =IF(ISNUMBER(BetaR2Median),IF(BetaR2Median<BetaR2Warn,"경고: 회귀 베타 신뢰 낮음(R² 중앙값 "&TEXT(BetaR2Median,"0.00")&" < "&TEXT(BetaR2Warn,"0.00")&")","경고 없음"),"공개 모드: 피어 부족 — R² 중앙값 표시 안 함") -> 경고 없음 | D8: 표시만(경로 불변, common_rules)
A10: 할인율 (선택한 SRP)
A11: Rf(Inputs 'Rf 만기 선택', 데이터 표 입력 칸이 비면) | C11: =IF(ISNUMBER(RfOvr),RfOvr,IF(RfTenor=10,Rf_10Y,Rf_5Y)) -> 0.04203
A12: MRP(데이터 표 입력 칸이 비면 Inputs 값) | C12: =IF(ISNUMBER(MrpOvr),MrpOvr,MRP) -> 0.08
A13: SRP(데이터 표 입력 칸이 비면 선택 값) | C13: =IF(ISNUMBER(SrpOvr),SrpOvr,SRP_Sel) -> 0
A14: βu | C14: =BetaU -> 0.62399371
A15: 목표 D/E | B15: 배 | C15: =DE_Target -> 0.0042596555
A16: βL = βu × (1 + (1 − t) × D/E) | C16: =BetaU*(1+(1-T_Hamada)*DE_Target) -> 0.62606695
A17: Ke = Rf + βL × MRP + SRP | C17: =Rf+BetaL*MRP_Eff+SRP_Eff -> 0.092115356
A18: 한계세율 기준: 연결 LTM 세전이익 | B18: 백만원 | C18: =PretaxLTM -> -4703.86 | D18: company_dcf.discount_rate
A19: 한계세율(세후 Kd) | B19: % | C19: =INDEX(TaxRate,COUNTIF(TaxTo,"<"&EbitEnd)+1) -> 0.11
A20: 실제 가중 약정이자율(Inputs 표 5) | B20: % | C20: =IF(SUM(BorrowAmt)>0,SUMPRODUCT(BorrowRate,BorrowAmt)/SUM(BorrowAmt),0) -> 0 | D20: 등급 A+~BBB+일 때만 규칙에 쓰인다 | E20: =IF(OR(RatingIdx=0,RatingIdx<=MATCH("AA-",RatingScale,0),RatingIdx>MATCH("BBB+",RatingScale,0)),"미사용(규칙상: "&IF(RatingIdx=0,"무등급 → BBB- 3년","등급 구간 밖")&")","사용") -> 미사용(규칙상: 무등급 → BBB- 3년)
A21: 등급 순번(빈칸 = 무등급 0) | C21: =IF(Rating="",0,MATCH(Rating,RatingScale,0)) -> 0
A22: 규칙 Kd(하한 전) | B22: % | C22: =IF(RatingIdx=0,Kd_BBB,IF(RatingIdx<=MATCH("AA-",RatingScale,0),Kd_AA,IF(RatingIdx<=MATCH("BBB+",RatingScale,0),MAX(N(Kd_Actual),Kd_AA),Kd_BBB))) -> 0.10506
A23: 세전 Kd = max(규칙 Kd, Rf) | B23: % | C23: =MAX(C22,Rf) -> 0.10506
A24: 세후 Kd | B24: % | C24: =Kd_Pre*(1-T_Kd) -> 0.0935034 | E24: =IF(DE_Target=0,"미사용(D/E 0 → WACC에 Kd 반영 안 됨)","사용(D/V "&TEXT(DE_Target/(1+DE_Target),"0.0%")&")") -> 사용(D/V 0.4%)
A25: D/V = D/E ÷ (1 + D/E) | B25: % | C25: =DE_Target/(1+DE_Target) -> 0.0042415878
A26: WACC(계산) = E/V × Ke + D/V × Kd × (1 − t) | B26: % | C26: =(1-WD)*Ke+WD*Kd_AT -> 0.092121243
A27: WACC(모델 사용, 데이터 표 입력 칸이 비면 계산값) | B27: % | C27: =IF(ISNUMBER(WaccOvr),WaccOvr,WaccCalc) -> 0.092121243 | D27: Scenarios 시트 WACC × g 데이터 표가 WaccOvr 칸에 값을 넣어 계산
A28: Kd 규칙(공통 규칙, 위 순서): 무등급 → BBB- 3년 / AA- 이상 → AA- 3년 / A+~BBB+ → max(실제 가중, AA- 3년) / BBB 이하 → BBB- 3년, 하한 Rf
A30: SRP 열별 WACC(같은 βu·D/E)
A31: SRP 열 1 | B31: % | C31: =(1-WD)*(Rf+BetaL*MRP+SRP_1)+WD*Kd_AT -> 0.092121243
A32: SRP 열 2 | B32: % | C32: =(1-WD)*(Rf+BetaL*MRP+SRP_2)+WD*Kd_AT -> 0.10207883
A33: SRP 열 3 | B33: % | C33: =(1-WD)*(Rf+BetaL*MRP+SRP_3)+WD*Kd_AT -> 0.11203641

Sheet DCF
A1: DCF — 할인·영구가치·EV (선택한 시나리오·SRP)
A2: 할인 기준일 6/30(재무상태표) → mid-year 할인 → EV를 평가기준일 9/30로 이월. 순현금은 6/30 장부(이월 안 함)
A4: 기간 | D4: =Forecast!D47 -> 2H26 | E4: =Forecast!E47 -> 2027 | F4: =Forecast!F47 -> 2028 | G4: =Forecast!G47 -> 2029 | H4: =Forecast!H47 -> 2030 | I4: =Forecast!I47 -> 2031 | J4: =Forecast!J47 -> 2032 | K4: =Forecast!K47 -> 2033 | ... R4: =Forecast!R47 -> 2040
A5: 연도 | D5: =Forecast!D49 -> 2026 | E5: =Forecast!E49 -> 2027 | F5: =Forecast!F49 -> 2028 | G5: =Forecast!G49 -> 2029 | H5: =Forecast!H49 -> 2030 | I5: =Forecast!I49 -> 2031 | J5: =Forecast!J49 -> 2032 | K5: =Forecast!K49 -> 2033 | ... R5: =Forecast!R49 -> 2040
A6: 기간 비율 | D6: =Forecast!D53 -> 0.50410959 | E6: =Forecast!E53 -> 1 | F6: =Forecast!F53 -> 1.0027397 | G6: =Forecast!G53 -> 1 | H6: =Forecast!H53 -> 1 | I6: =Forecast!I53 -> 1 | J6: =Forecast!J53 -> 1.0027397 | K6: =Forecast!K53 -> 1 | ... R6: =Forecast!R53 -> 1.0027397
A7: 종료일 | D7: =Forecast!D52 -> 46387 | E7: =Forecast!E52 -> 46752 | F7: =Forecast!F52 -> 47118 | G7: =Forecast!G52 -> 47483 | H7: =Forecast!H52 -> 47848 | I7: =Forecast!I52 -> 48213 | J7: =Forecast!J52 -> 48579 | K7: =Forecast!K52 -> 48944 | ... R7: =Forecast!R52 -> 51501
A8: FCFF | B8: 백만원 | D8: =Forecast!D69 -> 210.30621 | E8: =Forecast!E69 -> 119.57418 | F8: =Forecast!F69 -> 152.67171 | G8: =Forecast!G69 -> 187.12988 | H8: =Forecast!H69 -> 222.64865 | I8: =Forecast!I69 -> 255.67959 | J8: =Forecast!J69 -> 289.95151 | K8: =Forecast!K69 -> 196.89752 | ... R8: =Forecast!R69 -> 223.61244
A9: 기간 말까지 연수(할인 기준일부터) | B9: 년 | D9: =(D7-DiscDate)/DaysYr -> 0.50410959 | E9: =(E7-DiscDate)/DaysYr -> 1.5041096 | F9: =(F7-DiscDate)/DaysYr -> 2.5068493 | G9: =(G7-DiscDate)/DaysYr -> 3.5068493 | H9: =(H7-DiscDate)/DaysYr -> 4.5068493 | I9: =(I7-DiscDate)/DaysYr -> 5.5068493 | J9: =(J7-DiscDate)/DaysYr -> 6.509589 | K9: =(K7-DiscDate)/DaysYr -> 7.509589 | ... R9: =(R7-DiscDate)/DaysYr -> 14.515068
A10: 할인 연수(mid-year면 기간 중앙) | B10: 년 | D10: =D9-IF(MidYear=1,D6/2,0) -> 0.25205479 | E10: =E9-IF(MidYear=1,E6/2,0) -> 1.0041096 | F10: =F9-IF(MidYear=1,F6/2,0) -> 2.0054795 | G10: =G9-IF(MidYear=1,G6/2,0) -> 3.0068493 | H10: =H9-IF(MidYear=1,H6/2,0) -> 4.0068493 | I10: =I9-IF(MidYear=1,I6/2,0) -> 5.0068493 | J10: =J9-IF(MidYear=1,J6/2,0) -> 6.0082192 | K10: =K9-IF(MidYear=1,K6/2,0) -> 7.009589 | ... R10: =R9-IF(MidYear=1,R6/2,0) -> 14.013699
A11: 할인계수 (1 + WACC)^−t | D11: =(1+WACC)^(-D10) -> 0.97803331 | E11: =(1+WACC)^(-E10) -> 0.91531771 | F11: =(1+WACC)^(-F10) -> 0.83800882 | G11: =(1+WACC)^(-G10) -> 0.76722952 | H11: =(1+WACC)^(-H10) -> 0.70251314 | I11: =(1+WACC)^(-I10) -> 0.64325563 | J11: =(1+WACC)^(-J10) -> 0.58892544 | K11: =(1+WACC)^(-K10) -> 0.53918405 | ... R11: =(1+WACC)^(-R10) -> 0.29085985
A12: 현재가치(6/30) | B12: 백만원 | D12: =D8*D11 -> 205.68648 | E12: =E8*E11 -> 109.44836 | F12: =F8*F11 -> 127.94023 | G12: =G8*G11 -> 143.57157 | H12: =H8*H11 -> 156.4136 | I12: =I8*I11 -> 164.46734 | J12: =J8*J11 -> 170.75982 | K12: =K8*K11 -> 106.164 | ... R12: =R8*R11 -> 65.039882
A14: RONIC — 2027~명시 마지막 연도 증분 ROIC (P3-B2 규칙, P3-C3 출발점)
A15: FY2026 EBIT(정상 = FY2026 매출 × 정상 이익률) | B15: 백만원 | C15: =Forecast!D56*Margin_Sel -> 54.417432
A16: NOPAT FY2026 (normal 규칙) | B16: 백만원 | C16: =C15-IF(C15>0,SUMPRODUCT((C15>TaxFrom)*(C15-TaxFrom)*TaxDRate),0) -> 48.431515
A17: FY2026 EBIT(혼합 = 1H 실적 + 2H 정상) | B17: 백만원 | C17: =Forecast!D59 -> -229.58167
A18: NOPAT FY2026 (mixed 규칙) | B18: 백만원 | C18: =C17-IF(C17>0,SUMPRODUCT((C17>TaxFrom)*(C17-TaxFrom)*TaxDRate),0) -> -229.58167
A19: 출발 NOPAT(선택 규칙) | B19: 백만원 | C19: =IF(RonicStart="normal",C16,C18) -> 48.431515 | D19: Inputs의 RONIC 출발점 규칙
A20: 명시 마지막 연도 EBIT | B20: 백만원 | C20: =INDEX(Forecast!$D$58:$R$58,MATCH(ExplicitEnd,Forecast!$D$49:$R$49,0)) -> 288.4607
A21: NOPAT | B21: 백만원 | C21: =C20-IF(C20>0,SUMPRODUCT((C20>TaxFrom)*(C20-TaxFrom)*TaxDRate),0) -> 246.99934
A22: 누적 재투자 Σ(CAPEX − D&A + ΔNWC), 2027~명시 끝 | B22: 백만원 | C22: =SUMPRODUCT((Forecast!$D$48:$R$48>1)*Forecast!$D$54:$R$54*(Forecast!$D$61:$R$61-Forecast!$D$60:$R$60+Forecast!$D$63:$R$63)) -> -246.83057
A23: 증분 ROIC(계산값) | C23: =IF(C22>0,(C21-C19)/C22,0) -> 0
A24: RONIC(적용) | C24: =IF(C22<=0,WACC,IF(C23<WACC,WACC,IF(C23>RonicCap,MAX(RonicCap,WACC),C23))) -> 0.092121243 | D24: 재투자 ≤ 0이면 WACC, 그 밖은 [WACC, 과거 3년 ROIC]로 자름(사전 고정); 과거 ROIC < WACC면 WACC(하한 우선, P7-X2b)
A25: 대체 여부 | C25: =IF(C22<=0,"재투자 ≤ 0 → WACC",IF(C23<WACC,"계산값 < WACC → 하한",IF(C23>RonicCap,IF(RonicCap<WACC,"과거 ROIC < WACC → WACC(하한 우선)","계산값 > 상한(과거 ROIC)"),"계산값 사용"))) -> 재투자 ≤ 0 → WACC
A27: 영구가치 (가치동인: FCF = NOPAT × (1 − g ÷ RONIC))
A28: 마지막 체감 연도 매출 | B28: 백만원 | C28: =Forecast!$R$57 -> 4894.6488
A29: 마지막 체감 연도 EBIT | B29: 백만원 | C29: =Forecast!$R$58 -> 337.97768
A30: 다음 해 매출 = 매출 × (1 + g) | B30: 백만원 | C30: =C28*(1+GEff) -> 4992.5417
A31: 다음 해 EBIT | B31: 백만원 | C31: =C30*(Margin_Sel+MarginConvAmt) -> 344.73723
A32: 다음 해 NOPAT | B32: 백만원 | C32: =C31-IF(C31>0,SUMPRODUCT((C31>TaxFrom)*(C31-TaxFrom)*TaxDRate),0) -> 290.89504
A33: 다음 해 FCF = NOPAT × (1 − g ÷ RONIC) | B33: 백만원 | C33: =C32*(1-GEff/RONIC) -> 227.74022
A34: 영구가치 TV(Gordon, mid-year면 × (1+WACC)^0.5) | B34: 백만원 | C34: =C33/(WACC-GEff)*IF(MidYear=1,(1+WACC)^0.5,1) -> 3299.9849
A35: 마지막 기간 말까지 연수 | C35: =R9 -> 14.515068
A36: 영구가치 현재가치 | B36: 백만원 | C36: =C34*(1+WACC)^(-C35) -> 918.34926
A37: 명시·체감 FCFF 현재가치 합 | B37: 백만원 | C37: =SUM(D12:R12) -> 1751.5871
A38: EV(할인 기준일 6/30) | B38: 백만원 | C38: =C37+C36 -> 2669.9363
A39: 이월 일수(평가기준일 − 할인 기준일) | C39: =ValDate-DiscDate -> 92
A40: EV(평가기준일, × (1+WACC)^(일수 ÷ 365)) | B40: 백만원 | C40: =C38*(1+WACC)^(C39/DaysYr) -> 2729.9032
A41: 영구가치 비중(PV TV ÷ EV) | C41: =C36/C38 -> 0.34395924
A42: 명시 마지막 연도 D&A | B42: 백만원 | C42: =INDEX(Forecast!$D$60:$R$60,MATCH(ExplicitEnd,Forecast!$D$49:$R$49,0)) -> 100.95323
A43: 명시 마지막 연도 매출 | B43: 백만원 | C43: =INDEX(Forecast!$D$57:$R$57,MATCH(ExplicitEnd,Forecast!$D$49:$R$49,0)) -> 4177.5356
A44: 마지막 연도 D&A(매출 × D&A/매출) | B44: 백만원 | C44: =C28*DnaRatio -> 118.2828
A45: 마지막 연도 EBITDA | B45: 백만원 | C45: =C29+C44 -> 456.26048
A46: Gordon 함의 EV/EBITDA(TV ÷ EBITDA) | C46: =IF(C45>0,C34/C45,"N/M") -> 7.2326776
A47: Exit 배수(EV/EBITDA) | C47: =PeerEvEbitdaMed -> N/M | D47: 피어 EV/EBITDA 중앙값(병행 표시용, 엔진은 Exit 미계산 ⚠️)
A48: Exit 영구가치(배수 × EBITDA) | B48: 백만원 | C48: =IF(ISNUMBER(C47),C47*C45,"N/M") -> N/M | D48: 시장 배수 → mid-year 조정 없음
A49: Exit 영구가치 현재가치 | B49: 백만원 | C49: =IF(ISNUMBER(C47),C48*(1+WACC)^(-C35),"N/M") -> N/M
A50: EV(Exit, 6/30) | B50: 백만원 | C50: =IF(ISNUMBER(C47),C37+C49,"N/M") -> N/M
A51: EV(Exit, 평가기준일) | B51: 백만원 | C51: =IF(ISNUMBER(C47),C50*(1+WACC)^(C39/DaysYr),"N/M") -> N/M
A52: 영구가치 비중(Exit) | C52: =IF(ISNUMBER(C47),C49/C50,"N/M") -> N/M
A53: Exit 함의 영구성장률 | C53: =IF(ISNUMBER(C47),(C48/IF(MidYear=1,(1+WACC)^0.5,1)*WACC-C33/(1+GEff))/(C48/IF(MidYear=1,(1+WACC)^0.5,1)+C33/(1+GEff)),"N/M") -> N/M
A55: 영구가치 교차 확인 (Gordon vs Exit, 같은 명시·체감 현금흐름)
A56: 방식 | C56: 주당(원) | D56: EV/EBITDA(배) | E56: 영구성장률 | F56: 영구가치 비중
A57: Gordon(가치동인) | C57: =PerShare -> 8733.8645 | D57: =ImpliedMultiple -> 7.2326776 | E57: =GEff -> 0.02 | F57: =TVShare -> 0.34395924
A58: Exit(배수) | C58: =PerShareExit -> N/M | D58: =ExitMult -> N/M | E58: =ImpliedG_Exit -> N/M | F58: =TVShare_Exit -> N/M
A59: Gordon 행의 배수 = 함의 배수, Exit 행의 g = 함의 영구성장률. 차이는 사실로만 표시

Sheet Bridge
A1: Bridge — EV → 주식가치 → 주당 (연결 DCF − 비지배지분)
A2: 주식가치 = EV − 순차입금(차입금 + 리스부채 − 현금성) + 비영업자산 − 비지배지분(장부). 현금성·비영업은 FS_Hist 줄 분류(peer_p3 규칙)
A4: EV(평가기준일) | B4: 백만원 | C4: =EV_930 -> 2729.9032 | D4: DCF 시트
A5: 총차입금(차입금·사채) | B5: 백만원 | C5: =FS_Hist!$J$24 -> 0 | D5: 2026-06-30 연결
A6: 리스부채(IFRS 16) | B6: 백만원 | C6: =FS_Hist!$J$25 -> 55.459414 | D6: WACC D/E와 같은 정의
A7: 현금성(유동 금융자산 줄 합계) | B7: 백만원 | C7: =SUMIFS(BsAmt,BsClass,"cash_like") -> 1111.4503 | D7: FS_Hist 분류 cash_like
A8: 순차입금 = 차입금 + 리스 − 현금성 | B8: 백만원 | C8: =C5+C6-C7 -> -1055.9909
A9: 비영업자산(비유동 금융자산·관계기업 줄 합계) + SOTP 종속회사 가치 | B9: 백만원 | C9: =SUMIFS(BsAmt,BsClass,"non_operating")+SotpRemainder+SotpListed*(1-SubDiscount)+SotpUnlisted+AssocLines+AssocValue-AssocReplaced -> 235050.34 | D9: FS_Hist 분류 non_operating + 아래 SOTP 행(종속 줄은 빼고 바꿔 넣음)
A10: 참고: '기타금융자산' 줄 합계(유동 + 비유동) | B10: 백만원 | C10: =SUMPRODUCT(ISNUMBER(SEARCH("기타금융자산",BsName))*BsAmt) -> 0 | D10: 현금성·비영업 안에 포함된 금액
A11: SOTP: 별도 재무상태표 '종속' 투자 줄(비영업에서 제외) | B11: 백만원 | C11: =SUMIFS(BsAmt,BsClass,"sub_inv") -> 70894.006 | D11: FS_Hist 분류 sub_inv
A12: SOTP: 그중 연결 범위 피투자회사 장부가(출자현황) | B12: 백만원 | C12: =SUM(SubBook) -> 51166 | D12: Inputs 표 10
A13: SOTP: 합친 줄의 관계기업 몫 = max(줄 − 장부, 0) | B13: 백만원 | C13: =MAX(C11-C12,0) -> 19728.006 | D13: 장부가 유지
A14: SOTP: 상장 종속회사 지분 시가 = 보유 주식수 × 종가 | B14: 백만원 | C14: =SUMPRODUCT(SubShares,SubClose,SubListedDirect)/MnToWon -> 142764 | D14: 직접 보유분만, 한국거래소 통계정보 종가
A15: SOTP: 상장 지분 할인율 | C15: =SubDiscount -> 0.3 | D15: 기본 0%, 민감도 30%·50%
A16: SOTP: 비상장 종속회사 장부가 | B16: 백만원 | C16: =SUMPRODUCT(SubBook,SubUnlisted) -> 29988 | D16: Inputs 표 10
A17: 상장 관계기업: 관계기업·공동기업·지분법 줄(비영업, 장부) | B17: 백만원 | C17: =SUMIFS(BsAmt,BsClass,"nonop_assoc") -> 13228.925 | D17: FS_Hist 분류 nonop_assoc
A18: 상장 관계기업 지분 시가 × (1 − 할인) | B18: 백만원 | C18: =SUMPRODUCT(AssocShares,AssocClose)/MnToWon*(1-AssocDiscount) -> 51936 | D18: Inputs 표 11, 한국거래소 통계정보 종가
A19: 빼는 장부 = MIN(관계기업 줄, Σ 관계기업 장부) (줄이 없으면 SOTP 나머지에서) | B19: 백만원 | C19: =IF(AssocLines>0,MIN(AssocLines,SUM(AssocBook)),MIN(SotpRemainder,SUM(AssocBook))) -> 12262 | D19: 이중 계산 방지(관계기업 장부를 시가로 바꿈)
A20: 비지배지분(장부) | B20: 백만원 | C20: =FS_Hist!$J$26 -> 0 | D20: 상장 종속회사 없음 → 장부
A21: 주식가치 | B21: 백만원 | C21: =C4-C8+C9-C20 -> 238836.23
A22: EV 밖 항목 합계(시나리오·SRP와 무관) | B22: 백만원 | C22: =C21-C4 -> 236106.33 | D22: Scen_Calc·Peers가 같은 값을 쓴다
A23: 지분법 방식 배수(PER·PBR)에 더할 항목 | B23: 백만원 | C23: =0 -> 0 | D23: 연결 구조: 없음
A24: 유통주식수 = (보통주 + 우선주) − 자기주식 | B24: 주 | C24: =(CommonIssued-CommonTreasury)+(PrefIssued-PrefTreasury) -> 27345997 | D24: 우선주를 보통주와 같은 청구권으로 본다(⚠️)
A25: 주당 가치(원, Gordon) | B25: 원 | C25: =C21*MnToWon/Shares -> 8733.8645 | D25: 가정 하의 추정 내재가치(예시)
A26: 기준일 종가(보통주) 대비 | C26: =PerShare/Close-1 -> -0.56330678 | D26: 가정 차이 표시(판단 아님)
A27: 주식가치(Exit 영구가치) | B27: 백만원 | C27: =IF(ISNUMBER(EVExit_930),EVExit_930+BridgeAdj,"N/M") -> N/M
A28: 주당 가치(원, Exit) | B28: 원 | C28: =IF(ISNUMBER(C27),C27*MnToWon/Shares,"N/M") -> N/M
A29: 참고: 순자산가치(지배주주지분 장부, 없으면 자본총계 − 비지배, 주당 원) | B29: 원 | C29: =IF(FS_Hist!$J$27<>0,FS_Hist!$J$27,FS_Hist!$J$28-FS_Hist!$J$26)*MnToWon/Shares -> 4357.6355 | D29: 자산가치 접근(재평가 없음, 장부 그대로) — 03 문서 3-2
A31: 구조 판단 규칙 (config/valuation_rules.yaml structure)
A32: 시장 주식가치(보통주 + 우선주) | B32: 백만원 | C32: =Close*(CommonIssued-CommonTreasury+PrefIssued-PrefTreasury)/MnToWon -> 546919.94
A33: 비지배지분(상장 종속회사면 시가, 아니면 장부) | B33: 백만원 | C33: =IF(ListedSub=1,(1-Stake)*SubMC,C20) -> 0
A34: 비지배지분 ÷ 시장 주식가치 | C34: =C33/C32 -> 0
A35: 부문 이익률 차이 | C35: =SegMarginGap -> 0
A36: 부문 성장률 차이 | C36: =SegGrowthGap -> 0
A37: 규칙 판정 | C37: =IF(OR(C34>=NciShareMin,AND(ListedSub=1,OR(C35>=MarginGapMin,C36>=GrowthGapMin))),"sotp","consolidated") -> consolidated | D37: 비지배 ≥ 10% 또는 (상장 종속회사 + 이익률 차이 ≥ 5%p 또는 성장률 차이 ≥ 10%p) → SOTP

Sheet Peers
A1: Peers — 피어 배수 (LTM, 연결 브리지로 주당 환산)
A2: 배수 = EV(또는 시가총액) ÷ LTM 지표. 분모 ≤ 0이면 N/M, 배수 ≤ 0(음의 EV)은 통계에서 제외(엔진과 같음). 포함 = core+extended. 사분위 = QUARTILE.INC(pandas 선형 보간과 같음)
A3: 공개 모드: 피어별 시가총액·배수는 표시하지 않고 사분위 배수만 입력 칸(Inputs 표 P)으로 둔다
A5: 대상 LTM 지표 (연결, D&A는 점검 규칙 적용)
A6: 매출(연결 LTM) | B6: 백만원 | C6: =FS_Hist!$H$8+FS_Hist!$J$8-FS_Hist!$I$8 -> 2787.7031
A7: 영업이익(연결 LTM) | B7: 백만원 | C7: =FS_Hist!$H$10+FS_Hist!$J$10-FS_Hist!$I$10 -> -2826.6486
A8: D&A LTM(반기 값이 3개월로 보이면 FY 값, D&A/매출 1~20% 밖이면 N/M) | B8: 백만원 | C8: =IF(OR(FS_Hist!$H$17=0,FS_Hist!$H$16/FS_Hist!$H$8<DnaRatioLo,FS_Hist!$H$16/FS_Hist!$H$8>DnaRatioHi),"N/M",IF(AND(FS_Hist!$J$17<>0,FS_Hist!$I$17<>0,FS_Hist!$J$16/FS_Hist!$H$16>=DnaH1Lo,FS_Hist!$J$16/FS_Hist!$H$16<=DnaH1Hi,FS_Hist!$I$16/FS_Hist!$H$16>=DnaH1Lo,FS_Hist!$I$16/FS_Hist!$H$16<=DnaH1Hi),FS_Hist!$H$16+FS_Hist!$J$16-FS_Hist!$I$16,FS_Hist!$H$16)) -> 136.921
A9: EBITDA(LTM) | B9: 백만원 | C9: =IF(ISNUMBER(C8),C7+C8,"N/M") -> -2689.7276
A10: 지배주주순이익(LTM, 없으면 당기순이익) | B10: 백만원 | C10: =IF((FS_Hist!$H$13+FS_Hist!$J$13-FS_Hist!$I$13)<>0,FS_Hist!$H$13+FS_Hist!$J$13-FS_Hist!$I$13,FS_Hist!$H$12+FS_Hist!$J$12-FS_Hist!$I$12) -> -5457.3838
A11: 지배주주지분(6/30, 없으면 자본총계 − 비지배) | B11: 백만원 | C11: =IF(FS_Hist!$J$27<>0,FS_Hist!$J$27,FS_Hist!$J$28-FS_Hist!$J$26) -> 119163.89
A13: 배수 요약 → 주당 가치
A14: 배수 | C14: n | D14: q25 | E14: 중앙값 | F14: q75 | G14: 대상 지표 | H14: 주당 q25(원) | I14: 주당 중앙값(원) | J14: 주당 q75(원) | K14: 경고 | L14: 엔진 주당 q25 | M14: 엔진 주당 중앙값 | N14: 엔진 주당 q75
A15: EV/EBITDA | C15: =Inputs!B145 -> 3 | D15: =IF(OR(C15=0,NOT(ISNUMBER(Inputs!C145))),"N/M",Inputs!C145) -> N/M | E15: =IF(OR(C15=0,NOT(ISNUMBER(Inputs!D145))),"N/M",Inputs!D145) -> N/M | F15: =IF(OR(C15=0,NOT(ISNUMBER(Inputs!E145))),"N/M",Inputs!E145) -> N/M | G15: =C9 -> -2689.7276 | H15: =IF(OR(C15=0,NOT(ISNUMBER(D15)),NOT(ISNUMBER(G15)),N(G15)<=0),"N/M",(D15*G15+BridgeAdj)*MnToWon/Shares) -> N/M | I15: =IF(OR(C15=0,NOT(ISNUMBER(E15)),NOT(ISNUMBER(G15)),N(G15)<=0),"N/M",(E15*G15+BridgeAdj)*MnToWon/Shares) -> N/M | J15: =IF(OR(C15=0,NOT(ISNUMBER(F15)),NOT(ISNUMBER(G15)),N(G15)<=0),"N/M",(F15*G15+BridgeAdj)*MnToWon/Shares) -> N/M | K15: =IF(C15<PeerNWarn,"n<"&PeerNWarn,"") -> n<5 | L15: n/a | M15: n/a | N15: n/a
A16: EV/EBITDA(보완 전) | C16: =Inputs!B146 -> 3 | D16: =IF(OR(C16=0,NOT(ISNUMBER(Inputs!C146))),"N/M",Inputs!C146) -> N/M | E16: =IF(OR(C16=0,NOT(ISNUMBER(Inputs!D146))),"N/M",Inputs!D146) -> N/M | F16: =IF(OR(C16=0,NOT(ISNUMBER(Inputs!E146))),"N/M",Inputs!E146) -> N/M | G16: =C9 -> -2689.7276 | H16: =IF(OR(C16=0,NOT(ISNUMBER(D16)),NOT(ISNUMBER(G16)),N(G16)<=0),"N/M",(D16*G16+BridgeAdj)*MnToWon/Shares) -> N/M | I16: =IF(OR(C16=0,NOT(ISNUMBER(E16)),NOT(ISNUMBER(G16)),N(G16)<=0),"N/M",(E16*G16+BridgeAdj)*MnToWon/Shares) -> N/M | J16: =IF(OR(C16=0,NOT(ISNUMBER(F16)),NOT(ISNUMBER(G16)),N(G16)<=0),"N/M",(F16*G16+BridgeAdj)*MnToWon/Shares) -> N/M | K16: =IF(C16<PeerNWarn,"n<"&PeerNWarn,"") -> n<5
A17: EV/Sales | C17: =Inputs!B147 -> 3 | D17: =IF(OR(C17=0,NOT(ISNUMBER(Inputs!C147))),"N/M",Inputs!C147) -> N/M | E17: =IF(OR(C17=0,NOT(ISNUMBER(Inputs!D147))),"N/M",Inputs!D147) -> N/M | F17: =IF(OR(C17=0,NOT(ISNUMBER(Inputs!E147))),"N/M",Inputs!E147) -> N/M | G17: =C6 -> 2787.7031 | H17: =IF(OR(C17=0,NOT(ISNUMBER(D17)),NOT(ISNUMBER(G17)),N(G17)<=0),"N/M",(D17*G17+BridgeAdj)*MnToWon/Shares) -> N/M | I17: =IF(OR(C17=0,NOT(ISNUMBER(E17)),NOT(ISNUMBER(G17)),N(G17)<=0),"N/M",(E17*G17+BridgeAdj)*MnToWon/Shares) -> N/M | J17: =IF(OR(C17=0,NOT(ISNUMBER(F17)),NOT(ISNUMBER(G17)),N(G17)<=0),"N/M",(F17*G17+BridgeAdj)*MnToWon/Shares) -> N/M | K17: =IF(C17<PeerNWarn,"n<"&PeerNWarn,"") -> n<5 | L17: n/a | M17: n/a | N17: n/a
A18: PBR | C18: =Inputs!B148 -> 6 | D18: =IF(OR(C18=0,NOT(ISNUMBER(Inputs!C148))),"N/M",Inputs!C148) -> 0.46649647 | E18: =IF(OR(C18=0,NOT(ISNUMBER(Inputs!D148))),"N/M",Inputs!D148) -> 0.58888537 | F18: =IF(OR(C18=0,NOT(ISNUMBER(Inputs!E148))),"N/M",Inputs!E148) -> 0.96479007 | G18: =C11 -> 119163.89 | H18: =IF(OR(C18=0,NOT(ISNUMBER(D18)),NOT(ISNUMBER(G18)),N(G18)<=0),"N/M",(D18*G18+EqAddOn)*MnToWon/Shares) -> 2032.8216 | I18: =IF(OR(C18=0,NOT(ISNUMBER(E18)),NOT(ISNUMBER(G18)),N(G18)<=0),"N/M",(E18*G18+EqAddOn)*MnToWon/Shares) -> 2566.1478 | J18: =IF(OR(C18=0,NOT(ISNUMBER(F18)),NOT(ISNUMBER(G18)),N(G18)<=0),"N/M",(F18*G18+EqAddOn)*MnToWon/Shares) -> 4204.2034 | K18: =IF(C18<PeerNWarn,"n<"&PeerNWarn,"") | L18: 2032.8216 | M18: 2566.1478 | N18: 4204.2034
A19: PER | C19: =Inputs!B149 -> 5 | D19: =IF(OR(C19=0,NOT(ISNUMBER(Inputs!C149))),"N/M",Inputs!C149) -> 5.2590982 | E19: =IF(OR(C19=0,NOT(ISNUMBER(Inputs!D149))),"N/M",Inputs!D149) -> 7.6482179 | F19: =IF(OR(C19=0,NOT(ISNUMBER(Inputs!E149))),"N/M",Inputs!E149) -> 10.006508 | G19: =C10 -> -5457.3838 | H19: =IF(OR(C19=0,NOT(ISNUMBER(D19)),NOT(ISNUMBER(G19)),N(G19)<=0),"N/M",(D19*G19+EqAddOn)*MnToWon/Shares) -> N/M | I19: =IF(OR(C19=0,NOT(ISNUMBER(E19)),NOT(ISNUMBER(G19)),N(G19)<=0),"N/M",(E19*G19+EqAddOn)*MnToWon/Shares) -> N/M | J19: =IF(OR(C19=0,NOT(ISNUMBER(F19)),NOT(ISNUMBER(G19)),N(G19)<=0),"N/M",(F19*G19+EqAddOn)*MnToWon/Shares) -> N/M | K19: =IF(C19<PeerNWarn,"n<"&PeerNWarn,"") | L19: n/a | M19: n/a | N19: n/a
A20: EV 배수: 배수 × 대상 LTM 지표 + EV 밖 항목(− 순차입금 + 비영업 − 비지배, Bridge). PER × 지배순이익, PBR × 지배지분

Sheet Premium
A1: Premium — 지배 블록 1주당 가격 범위 (경영권 프리미엄 DB 집계값)
A2: 블록 1주당 = 20거래일 VWAP × (1 + 프리미엄). 지분 전체·DCF 가치에 (1+프리미엄)을 곱하지 않는다. 프리미엄 DB는 분위수·표본 수만
A4: D6 적용 규칙 (config/premium_p2c3.yaml application_rule, 사용자 결정 2026-10-03)
A5: 시총 백분위 | C5: =Prem_Pct -> 66.4
A6: 시장 | C6: =Prem_Market -> KOSDAQ
A7: 회귀 채택(CV 개선 ≥ 기준, 1=예) | C7: =IF(Prem_CV>=Prem_Thr,1,0) -> 1
A8: 회귀 q50 − 이웃 중앙값(절댓값) | C8: =ABS(Prem_REG_q50-Prem_NEI_q50) -> 0.0042705702
A9: 차이 경고(> 10%p, 1=예) | C9: =IF(ABS(Prem_REG_q50-Prem_NEI_q50)>Prem_GapWarn,1,0) -> 0
A10: method | C10: =IF(Prem_Market="KOSPI","neighbours",IF(Prem_Pct>=Prem_TopBand,"neighbours",IF(C7=1,IF(C9=1,"neighbours","regression"),"band_table"))) -> regression | D10: 엔진(predict.premium_range) | E10: regression
A11: 이유 | C11: =IF(Prem_Market="KOSPI","rule_market",IF(Prem_Pct>=Prem_TopBand,"rule_top_band",IF(C7=1,IF(C9=1,"warning","cv_adopted"),"cv_not_adopted"))) -> cv_adopted | E11: cv_adopted
A12: 순서: KOSPI → 이웃(rule_market) / KOSDAQ 백분위 ≥ 80 → 이웃(rule_top_band) / 회귀 채택 + 차이 경고 → 이웃(warning) / 회귀 채택 → 회귀(cv_adopted) / 미채택 → 구간 표(cv_not_adopted)
A14: 프리미엄 분위 | C14: q25 | D14: q50 | E14: q75 | F14: 표본 수
A15: 이웃 50건 | C15: =Prem_NEI_q25 -> -0.082132402 | D15: =Prem_NEI_q50 -> 0.084419618 | E15: =Prem_NEI_q75 -> 0.30876385 | F15: =Prem_NB_n -> 50
A16: 분위 회귀(참고, 항상 표시) | C16: =Prem_REG_q25 -> -0.080474082 | D16: =Prem_REG_q50 -> 0.080149048 | E16: =Prem_REG_q75 -> 0.36540326 | F16: ="회귀" -> 회귀
A17: 구간 표 P60-80 | C17: =Prem_BAN_q25 -> -0.092879496 | D17: =Prem_BAN_q50 -> 0.083969898 | E17: =Prem_BAN_q75 -> 0.40342333 | F17: =Prem_BAN_n -> 77
A18: 적용(D6 method) | C18: =IF(PremMethod="neighbours",C15,IF(PremMethod="regression",C16,C17)) -> -0.080474082 | D18: =IF(PremMethod="neighbours",D15,IF(PremMethod="regression",D16,D17)) -> 0.080149048 | E18: =IF(PremMethod="neighbours",E15,IF(PremMethod="regression",E16,E17)) -> 0.36540326 | F18: =IF(PremMethod="neighbours",F15,IF(PremMethod="band_table",F17,"회귀")) -> 회귀
A20: 블록 1주당 가격 (원)
A21: 20거래일 VWAP(평가기준일까지, 한국거래소 통계정보) | B21: 원 | C21: =VWAP20 -> 19800
A22: 기준일 종가 | B22: 원 | C22: =Close -> 20000
A23: 블록 1주당 q25 = VWAP × (1 + 프리미엄) | B23: 원 | C23: =IF(ISNUMBER(PremQ1),VWAP20*(1+PremQ1),"N/M") -> 18206.613 | D23: 엔진 | E23: 18206.613
A24: 블록 1주당 q50 = VWAP × (1 + 프리미엄) | B24: 원 | C24: =IF(ISNUMBER(PremQ2),VWAP20*(1+PremQ2),"N/M") -> 21386.951 | D24: 엔진 | E24: 21386.951
A25: 블록 1주당 q75 = VWAP × (1 + 프리미엄) | B25: 원 | C25: =IF(ISNUMBER(PremQ3),VWAP20*(1+PremQ3),"N/M") -> 27034.985 | D25: 엔진 | E25: 27034.985
A27: 상증법 최대주주 할증 비교 (⚠️ 원문 미확인, 중소·일정 중견기업 제외 가능)
A28: 할증 적용: VWAP × (1 + 할증률) | B28: 원 | C28: =VWAP20*(1+TaxPrem) -> 23760
A29: 할증 적용: 종가 × (1 + 할증률) | B29: 원 | C29: =Close*(1+TaxPrem) -> 24000
A30: 할증 제외(VWAP) | B30: 원 | C30: =VWAP20 -> 19800
A31: 세법 평가액은 평가기준일 전후 2개월 평균 종가가 원칙 — 여기서는 비교용 단순화
A33: 엔진 경고(predict.premium_range): 없음

Sheet Scenarios
A1: Scenarios — 시나리오 × SRP (가정 하의 추정 내재가치, 예시)
A2: A 표·C·D 데이터 표는 살아 있는 수식(Scen_Calc, 엑셀 What-If). 회색 표는 엔진 계산값(수식 아님) — 대조용
A4: A-1. 주당 가치(원, Gordon) — 살아 있는 수식
A5: 시나리오 \ SRP | B5: =SRP_1 -> 0 | C5: =SRP_2 -> 0.01 | D5: =SRP_3 -> 0.02 | F5: 기준일 종가 대비
A6: 비관 | B6: =Scen_Calc!$C$47 -> 8702.4406 | C6: =Scen_Calc!$C$60 -> 8695.7866 | D6: =Scen_Calc!$C$73 -> 8690.3282 | F6: =B6/Close-1 -> -0.56487797 | G6: =C6/Close-1 -> -0.56521067 | H6: =D6/Close-1 -> -0.56548359
A7: 기본 | B7: =Scen_Calc!$C$120 -> 8733.8645 | C7: =Scen_Calc!$C$133 -> 8724.325 | D7: =Scen_Calc!$C$146 -> 8716.4931 | F7: =B7/Close-1 -> -0.56330678 | G7: =C7/Close-1 -> -0.56378375 | H7: =D7/Close-1 -> -0.56417534
A8: 낙관 | B8: =Scen_Calc!$C$193 -> 8767.5065 | C8: =Scen_Calc!$C$206 -> 8754.833 | D8: =Scen_Calc!$C$219 -> 8744.4261 | F8: =B8/Close-1 -> -0.56162467 | G8: =C8/Close-1 -> -0.56225835 | H8: =D8/Close-1 -> -0.5627787
A10: A-2. WACC
A11: 시나리오 \ SRP | B11: =SRP_1 -> 0 | C11: =SRP_2 -> 0.01 | D11: =SRP_3 -> 0.02
A12: 비관 | B12: =Scen_Calc!$C$38 -> 0.092121243 | C12: =Scen_Calc!$C$51 -> 0.10207883 | D12: =Scen_Calc!$C$64 -> 0.11203641
A13: 기본 | B13: =Scen_Calc!$C$111 -> 0.092121243 | C13: =Scen_Calc!$C$124 -> 0.10207883 | D13: =Scen_Calc!$C$137 -> 0.11203641
A14: 낙관 | B14: =Scen_Calc!$C$184 -> 0.092121243 | C14: =Scen_Calc!$C$197 -> 0.10207883 | D14: =Scen_Calc!$C$210 -> 0.11203641
A16: A-3. RONIC(적용)
A17: 시나리오 \ SRP | B17: =SRP_1 -> 0 | C17: =SRP_2 -> 0.01 | D17: =SRP_3 -> 0.02
A18: 비관 | B18: =Scen_Calc!$C$39 -> 0.092121243 | C18: =Scen_Calc!$C$52 -> 0.10207883 | D18: =Scen_Calc!$C$65 -> 0.11203641
A19: 기본 | B19: =Scen_Calc!$C$112 -> 0.092121243 | C19: =Scen_Calc!$C$125 -> 0.10207883 | D19: =Scen_Calc!$C$138 -> 0.11203641
A20: 낙관 | B20: =Scen_Calc!$C$185 -> 0.092121243 | C20: =Scen_Calc!$C$198 -> 0.10207883 | D20: =Scen_Calc!$C$211 -> 0.11203641
A22: A-4. 영구가치 비중
A23: 시나리오 \ SRP | B23: =SRP_1 -> 0 | C23: =SRP_2 -> 0.01 | D23: =SRP_3 -> 0.02
A24: 비관 | B24: =Scen_Calc!$C$48 -> 0.35162596 | C24: =Scen_Calc!$C$61 -> 0.31024024 | D24: =Scen_Calc!$C$74 -> 0.27397114
A25: 기본 | B25: =Scen_Calc!$C$121 -> 0.34395924 | C25: =Scen_Calc!$C$134 -> 0.30290028 | D25: =Scen_Calc!$C$147 -> 0.26700511
A26: 낙관 | B26: =Scen_Calc!$C$194 -> 0.34149813 | C26: =Scen_Calc!$C$207 -> 0.30053198 | D26: =Scen_Calc!$C$220 -> 0.2647465
A28: 선택 칸(시나리오·SRP)의 표 값 | C28: =INDEX(ScenGridPS,ScenIdx,MATCH(SRP_Sel,SRP_List,0)) -> 8733.8645 | D28: = Bridge 주당 가치와 같아야 한다(Checks)
A30: B. 엔진 값(수식 아님) — rf_dcf2.value, P3-C3 규칙. Checks의 INFO 대조에 쓴다
A31: 엔진: 주당 가치(원, Gordon) | B31: 0 | C31: 0.01 | D31: 0.02
A32: 비관 | B32: 8702.4406 | C32: 8695.7866 | D32: 8690.3282
A33: 기본 | B33: 8733.8645 | C33: 8724.325 | D33: 8716.4931
A34: 낙관 | B34: 8767.5065 | C34: 8754.833 | D34: 8744.4261
A36: 엔진: WACC | B36: 0 | C36: 0.01 | D36: 0.02
A37: 비관 | B37: 0.092121243 | C37: 0.10207883 | D37: 0.11203641
A38: 기본 | B38: 0.092121243 | C38: 0.10207883 | D38: 0.11203641
A39: 낙관 | B39: 0.092121243 | C39: 0.10207883 | D39: 0.11203641
A41: 엔진: RONIC | B41: 0 | C41: 0.01 | D41: 0.02
A42: 비관 | B42: 0.092121243 | C42: 0.10207883 | D42: 0.11203641
A43: 기본 | B43: 0.092121243 | C43: 0.10207883 | D43: 0.11203641
A44: 낙관 | B44: 0.092121243 | C44: 0.10207883 | D44: 0.11203641
... A56: 엔진: 주당 가치(원, Exit) | B56: 0 | C56: 0.01 | D56: 0.02
A57: 비관 | B57: n/a | C57: n/a | D57: n/a
A58: 기본 | B58: n/a | C58: n/a | D58: n/a
A59: 낙관 | B59: n/a | C59: n/a | D59: n/a
A61: 엔진: EV(평가기준일, 백만원) | B61: 0 | C61: 0.01 | D61: 0.02
A62: 비관 | B62: 1870.5865 | C62: 1688.6265 | D62: 1539.3603
A63: 기본 | B63: 2729.9032 | C63: 2469.0368 | D63: 2254.8675
A64: 낙관 | B64: 3649.8798 | C64: 3303.3091 | D64: 3018.7213
A66: 엔진: Exit 함의 영구성장률 | B66: 0 | C66: 0.01 | D66: 0.02
A67: 비관 | B67: n/a | C67: n/a | D67: n/a
A68: 기본 | B68: n/a | C68: n/a | D68: n/a
A69: 낙관 | B69: n/a | C69: n/a | D69: n/a
A71: 엔진: 영구가치 비중(Exit) | B71: 0 | C71: 0.01 | D71: 0.02
A72: 비관 | B72: n/a | C72: n/a | D72: n/a
A73: 기본 | B73: n/a | C73: n/a | D73: n/a
A74: 낙관 | B74: n/a | C74: n/a | D74: n/a
A76: 살아 있는 표 − 엔진 표 (주당, 원)
A77: 비관 | B77: =B6-B32 -> 0 | C77: =C6-C32 -> 0 | D77: =D6-D32 -> 0
A78: 기본 | B78: =B7-B33 -> -3.6379788e-12 | C78: =C7-C33 -> -1.8189894e-12 | D78: =D7-D33 -> 0
A79: 낙관 | B79: =B8-B34 -> -1.8189894e-12 | C79: =C8-C34 -> 0 | D79: =D8-D34 -> 0
A81: 데이터 표 입력 칸 — 비워 둔다(데이터 표가 계산할 때만 값이 들어간다). 값을 넣으면 모델 전체가 그 값으로 바뀐다
A82: WACC 입력 칸(C 표 행 입력) | D82: 영구성장률 입력 칸(C 표 열 입력)
A83: 이익률 이동 입력 칸(D 표 행 입력) | D83: 출발 성장률 이동 입력 칸(D 표 열 입력)
A84: SRP 입력 칸(M 표 행 입력) | D84: MRP 입력 칸(M 표 열 입력)
A86: C. WACC × 영구성장률 g — 살아 있는 데이터 표(주당 원, 현재 선택 시나리오·SRP 기준). 오른쪽은 엔진 격자(기본·SRP 0%)
A87: WACC 이동폭(입력) | B87: -0.02 | C87: -0.01 | D87: 0 | E87: 0.01 | F87: 0.02
A88: =PerShare -> 8733.8645 | B88: =WaccCalc+B87 -> 0.072121243 | C88: =WaccCalc+C87 -> 0.082121243 | D88: =WaccCalc+D87 -> 0.092121243 | E88: =WaccCalc+E87 -> 0.10212124 | F88: =WaccCalc+F87 -> 0.11212124 | H88: 엔진(기본·SRP 0%) | I88: 0.072121243 | J88: 0.082121243 | K88: 0.092121243 | L88: 0.10212124 | M88: 0.11212124 | O88: 표 − 엔진(원)
A89: 0.01 | B89: 8760.6301 | C89: 8745.4549 | D89: 8733.587 | E89: 8724.0551 | F89: 8716.2343 | H89: 0.01 | I89: 8760.6301 | J89: 8745.4549 | K89: 8733.587 | L89: 8724.0551 | M89: 8716.2343 | P89: =IF(ISNUMBER(I89),B89-I89,"") -> 0 | Q89: =IF(ISNUMBER(J89),C89-J89,"") -> 0 | R89: =IF(ISNUMBER(K89),D89-K89,"") -> 0 | S89: =IF(ISNUMBER(L89),E89-L89,"") -> 0 | T89: =IF(ISNUMBER(M89),F89-M89,"") -> 0
A90: 0.015 | B90: 8760.8328 | C90: 8745.6205 | D90: 8733.7246 | E90: 8724.1708 | F90: 8716.3326 | H90: 0.015 | I90: 8760.8328 | J90: 8745.6205 | K90: 8733.7246 | L90: 8724.1708 | M90: 8716.3326 | P90: =IF(ISNUMBER(I90),B90-I90,"") -> 0 | Q90: =IF(ISNUMBER(J90),C90-J90,"") -> 0 | R90: =IF(ISNUMBER(K90),D90-K90,"") -> 0 | S90: =IF(ISNUMBER(L90),E90-L90,"") -> 0 | T90: =IF(ISNUMBER(M90),F90-M90,"") -> 0
A91: 0.02 | B91: 8761.0391 | C91: 8745.7891 | D91: 8733.8645 | E91: 8724.2883 | F91: 8716.4324 | H91: 0.02 | I91: 8761.0391 | J91: 8745.7891 | K91: 8733.8645 | L91: 8724.2883 | M91: 8716.4324 | P91: =IF(ISNUMBER(I91),B91-I91,"") -> 0 | Q91: =IF(ISNUMBER(J91),C91-J91,"") -> 0 | R91: =IF(ISNUMBER(K91),D91-K91,"") -> 0 | S91: =IF(ISNUMBER(L91),E91-L91,"") -> 0 | T91: =IF(ISNUMBER(M91),F91-M91,"") -> 0
A92: 0.025 | B92: 8761.2492 | C92: 8745.9607 | D92: 8734.0067 | E92: 8724.4079 | F92: 8716.5339 | H92: 0.025 | I92: 8761.2492 | J92: 8745.9607 | K92: 8734.0067 | L92: 8724.4079 | M92: 8716.5339 | P92: =IF(ISNUMBER(I92),B92-I92,"") -> 0 | Q92: =IF(ISNUMBER(J92),C92-J92,"") -> 0 | R92: =IF(ISNUMBER(K92),D92-K92,"") -> 0 | S92: =IF(ISNUMBER(L92),E92-L92,"") -> 0 | T92: =IF(ISNUMBER(M92),F92-M92,"") -> 0
A93: 0.03 | B93: 8761.4631 | C93: 8746.1352 | D93: 8734.1514 | E93: 8724.5294 | F93: 8716.637 | H93: 0.03 | I93: 8761.4631 | J93: 8746.1352 | K93: 8734.1514 | L93: 8724.5294 | M93: 8716.637 | P93: =IF(ISNUMBER(I93),B93-I93,"") -> 0 | Q93: =IF(ISNUMBER(J93),C93-J93,"") -> 0 | R93: =IF(ISNUMBER(K93),D93-K93,"") -> 0 | S93: =IF(ISNUMBER(L93),E93-L93,"") -> 0 | T93: =IF(ISNUMBER(M93),F93-M93,"") -> 0
A95: D. 출발 성장률 이동 × 정상 이익률 이동 — 살아 있는 데이터 표(주당 원, 현재 선택 시나리오·SRP 기준). 오른쪽은 엔진 격자(기본·SRP 0%)
A97: =PerShare -> 8733.8645 | B97: -0.04 | C97: -0.02 | D97: 0 | E97: 0.02 | F97: 0.04 | H97: 엔진(기본·SRP 0%) | I97: -0.04 | J97: -0.02 | K97: 0 | L97: 0.02 | M97: 0.04 | O97: 표 − 엔진(원)
A98: -0.04 | B98: 8671.3732 | C98: 8699.8499 | D98: 8726.1475 | E98: 8752.0079 | F98: 8777.372 | H98: -0.04 | I98: 8671.3732 | J98: 8699.8499 | K98: 8726.1475 | L98: 8752.0079 | M98: 8777.372 | P98: =IF(ISNUMBER(I98),B98-I98,"") -> 0 | Q98: =IF(ISNUMBER(J98),C98-J98,"") -> 0 | R98: =IF(ISNUMBER(K98),D98-K98,"") -> 0 | S98: =IF(ISNUMBER(L98),E98-L98,"") -> 0 | T98: =IF(ISNUMBER(M98),F98-M98,"") -> 0
A99: -0.02 | B99: 8672.7658 | C99: 8702.4406 | D99: 8729.9476 | E99: 8757.0193 | F99: 8783.575 | H99: -0.02 | I99: 8672.7658 | J99: 8702.4406 | K99: 8729.9476 | L99: 8757.0193 | M99: 8783.575 | P99: =IF(ISNUMBER(I99),B99-I99,"") -> 0 | Q99: =IF(ISNUMBER(J99),C99-J99,"") -> 0 | R99: =IF(ISNUMBER(K99),D99-K99,"") -> 0 | S99: =IF(ISNUMBER(L99),E99-L99,"") -> 0 | T99: =IF(ISNUMBER(M99),F99-M99,"") -> 0
A100: 0 | B100: 8674.2101 | C100: 8705.0775 | D100: 8733.8645 | E100: 8762.1863 | F100: 8789.9856 | H100: 0 | I100: 8674.2101 | J100: 8705.0775 | K100: 8733.8645 | L100: 8762.1863 | M100: 8789.9856 | P100: =IF(ISNUMBER(I100),B100-I100,"") -> 0 | Q100: =IF(ISNUMBER(J100),C100-J100,"") -> 0 | R100: =IF(ISNUMBER(K100),D100-K100,"") -> 0 | S100: =IF(ISNUMBER(L100),E100-L100,"") -> 0 | T100: =IF(ISNUMBER(M100),F100-M100,"") -> 0
A101: 0.02 | B101: 8675.7073 | C101: 8707.7905 | D101: 8737.8962 | E101: 8767.5065 | F101: 8796.6082 | H101: 0.02 | I101: 8675.7073 | J101: 8707.7905 | K101: 8737.8962 | L101: 8767.5065 | M101: 8796.6082 | P101: =IF(ISNUMBER(I101),B101-I101,"") -> 0 | Q101: =IF(ISNUMBER(J101),C101-J101,"") -> 0 | R101: =IF(ISNUMBER(K101),D101-K101,"") -> 0 | S101: =IF(ISNUMBER(L101),E101-L101,"") -> 0 | T101: =IF(ISNUMBER(M101),F101-M101,"") -> 0
A102: 0.04 | B102: 8677.2585 | C102: 8710.5955 | D102: 8742.0617 | E102: 8773.0013 | F102: 8803.447 | H102: 0.04 | I102: 8677.2585 | J102: 8710.5955 | K102: 8742.0617 | L102: 8773.0013 | M102: 8803.447 | P102: =IF(ISNUMBER(I102),B102-I102,"") -> 0 | Q102: =IF(ISNUMBER(J102),C102-J102,"") -> 0 | R102: =IF(ISNUMBER(K102),D102-K102,"") -> 0 | S102: =IF(ISNUMBER(L102),E102-L102,"") -> 0 | T102: =IF(ISNUMBER(M102),F102-M102,"") -> 0
A104: M. MRP × SRP (기본 시나리오) — 살아 있는 데이터 표(주당 원, 현재 선택 시나리오 기준). 오른쪽은 엔진 격자(기본)
A106: =PerShare -> 8733.8645 | B106: 0 | C106: 0.01 | D106: 0.02 | F106: 엔진(기본·SRP 0%) | G106: 0 | H106: 0.01 | I106: 0.02 | K106: 표 − 엔진(원)
A107: 0.07 | B107: 8740.9706 | C107: 8730.0637 | D107: 8721.2224 | F107: 0.07 | G107: 8740.9706 | H107: 8730.0637 | I107: 8721.2224 | L107: =IF(ISNUMBER(G107),B107-G107,"") -> 0 | M107: =IF(ISNUMBER(H107),C107-H107,"") -> 0 | N107: =IF(ISNUMBER(I107),D107-I107,"") -> 0
A108: 0.08 | B108: 8733.8645 | C108: 8724.325 | D108: 8716.4931 | F108: 0.08 | G108: 8733.8645 | H108: 8724.325 | I108: 8716.4931 | L108: =IF(ISNUMBER(G108),B108-G108,"") -> 0 | M108: =IF(ISNUMBER(H108),C108-H108,"") -> 0 | N108: =IF(ISNUMBER(I108),D108-I108,"") -> 0
A109: 0.09 | B109: 8727.6644 | C109: 8719.2517 | D109: 8712.2669 | F109: 0.09 | G109: 8727.6644 | H109: 8719.2517 | I109: 8712.2669 | L109: =IF(ISNUMBER(G109),B109-G109,"") -> 0 | M109: =IF(ISNUMBER(H109),C109-H109,"") -> 0 | N109: =IF(ISNUMBER(I109),D109-I109,"") -> 0
A110: 데이터 표는 현재 선택(기본·SRP 0%이 기본)으로 계산된다. 엔진 격자는 기본·SRP 0% 값이라 선택이 같을 때만 비교한다. 엑셀 계산 옵션이 '데이터 표 제외 자동'이면 F9로 다시 계산
A112: E. 역DCF — 기준일 종가(20,000원)를 맞추는 값 (기본 경로, SRP 0%, 하나씩만 바꿈) — 엔진 값
A113: 출발 성장률 g_2026(2030년까지 g로 체감, 탐색 −30%~+60%) | B113: n/a
A114: 보조: 같은 경로·이익률에서의 WACC | B114: n/a
A115: 보조: 기본 성장·WACC에서 필요한 정상 이익률 | B115: n/a
A117: G. Rf 만기 × SRP (P6-A) — 기본 결과(A 표)는 그대로. 10년·인용 SRP는 민감도
A118: Rf 입력 칸(G 표 열 입력) — 비워 둔다
A119: G-1. 살아 있는 데이터 표(주당 원, 현재 선택 시나리오). 행 = Rf 국고채 5년 / 10년, 열 = SRP 열 1~3 / 한공회 인용 참고값
A120: =PerShare -> 8733.8645 | B120: =SRP_1 -> 0 | C120: =SRP_2 -> 0.01 | D120: =SRP_3 -> 0.02 | E120: =SRP_Cite -> 0.0402 | G120: 엔진(기본 시나리오) | H120: 0 | I120: 0.01 | J120: 0.02 | K120: 0.0402 | M120: 표 − 엔진(원)
A121: =Rf_5Y -> 0.04203 | B121: 8733.8645 | C121: 8724.325 | D121: 8716.4931 | E121: 8704.3036 | G121: 0.04203 | H121: 8733.8645 | I121: 8724.325 | J121: 8716.4931 | K121: 8704.3036 | N121: =IF(ISNUMBER(H121),B121-H121,"") -> 0 | O121: =IF(ISNUMBER(I121),C121-I121,"") -> 0 | P121: =IF(ISNUMBER(J121),D121-J121,"") -> 0 | Q121: =IF(ISNUMBER(K121),E121-K121,"") -> 0
A122: =Rf_10Y -> 0.04407 | B122: 8731.7534 | C122: 8722.6046 | D122: 8715.0648 | E122: 8703.278 | G122: 0.04407 | H122: 8731.7534 | I122: 8722.6046 | J122: 8715.0648 | K122: 8703.278 | N122: =IF(ISNUMBER(H122),B122-H122,"") -> 0 | O122: =IF(ISNUMBER(I122),C122-I122,"") -> 0 | P122: =IF(ISNUMBER(J122),D122-J122,"") -> 0 | Q122: =IF(ISNUMBER(K122),E122-K122,"") -> 0
A123: SRP 인용 참고값 주당(Rf 5년, 현재 시나리오) — 위 표 마지막 열. SRP 기본 열(0·1·2%, 결정 D4)은 바꾸지 않는다
A125: G-2. 엔진: Rf 국고채 10년 — 주당 가치(원, Gordon) | B125: 0 | C125: 0.01 | D125: 0.02
A126: 비관 | B126: 8700.9677 | C126: 8694.5872 | D126: 8689.3332
A127: 기본 | B127: 8731.7534 | C127: 8722.6046 | D127: 8715.0648
A128: 낙관 | B128: 8764.7021 | C128: 8752.5472 | D128: 8742.5279
A130: G-2. 엔진: Rf 국고채 10년 — WACC | B130: 0 | C130: 0.01 | D130: 0.02
A131: 비관 | B131: 0.09415259 | C131: 0.10411017 | D131: 0.11406776
A132: 기본 | B132: 0.09415259 | C132: 0.10411017 | D132: 0.11406776
A133: 낙관 | B133: 0.09415259 | C133: 0.10411017 | D133: 0.11406776
...

Sheet Scen_Calc
A1: Scen_Calc — 시나리오 4 × SRP 3 (Forecast·DCF와 같은 수식, 시나리오 고정)
A2: Scenarios 시트 표의 계산. 할인 연수는 DCF 시트와 같은 행을 쓴다. 주식가치 = EV + Bridge의 EV 밖 항목
A4: 시나리오: 비관
A5: 기간 순번 | C5: 0 | D5: =C5+1 -> 1 | E5: =D5+1 -> 2 | F5: =E5+1 -> 3 | G5: =F5+1 -> 4 | H5: =G5+1 -> 5 | I5: =H5+1 -> 6 | J5: =I5+1 -> 7 | K5: =J5+1 -> 8 | ... R5: =Q5+1 -> 15
A6: 연도 | D6: =YEAR(CfStart)+D5-1 -> 2026 | E6: =YEAR(CfStart)+E5-1 -> 2027 | F6: =YEAR(CfStart)+F5-1 -> 2028 | G6: =YEAR(CfStart)+G5-1 -> 2029 | H6: =YEAR(CfStart)+H5-1 -> 2030 | I6: =YEAR(CfStart)+I5-1 -> 2031 | J6: =YEAR(CfStart)+J5-1 -> 2032 | K6: =YEAR(CfStart)+K5-1 -> 2033 | ... R6: =YEAR(CfStart)+R5-1 -> 2040
A7: 구간 | D7: =IF(D11=1,"명시","체감") -> 명시 | E7: =IF(E11=1,"명시","체감") -> 명시 | F7: =IF(F11=1,"명시","체감") -> 명시 | G7: =IF(G11=1,"명시","체감") -> 명시 | H7: =IF(H11=1,"명시","체감") -> 명시 | I7: =IF(I11=1,"명시","체감") -> 명시 | J7: =IF(J11=1,"명시","체감") -> 명시 | K7: =IF(K11=1,"명시","체감") -> 체감 | ... R7: =IF(R11=1,"명시","체감") -> 체감
A8: 시작일 | D8: =MAX(DATE(D6,1,1),CfStart) -> 46204 | E8: =MAX(DATE(E6,1,1),CfStart) -> 46388 | F8: =MAX(DATE(F6,1,1),CfStart) -> 46753 | G8: =MAX(DATE(G6,1,1),CfStart) -> 47119 | H8: =MAX(DATE(H6,1,1),CfStart) -> 47484 | I8: =MAX(DATE(I6,1,1),CfStart) -> 47849 | J8: =MAX(DATE(J6,1,1),CfStart) -> 48214 | K8: =MAX(DATE(K6,1,1),CfStart) -> 48580 | ... R8: =MAX(DATE(R6,1,1),CfStart) -> 51136
A9: 종료일 | D9: =DATE(D6,12,31) -> 46387 | E9: =DATE(E6,12,31) -> 46752 | F9: =DATE(F6,12,31) -> 47118 | G9: =DATE(G6,12,31) -> 47483 | H9: =DATE(H6,12,31) -> 47848 | I9: =DATE(I6,12,31) -> 48213 | J9: =DATE(J6,12,31) -> 48579 | K9: =DATE(K6,12,31) -> 48944 | ... R9: =DATE(R6,12,31) -> 51501
A10: 기간 비율(일수 ÷ 365) | D10: =(D9-D8+1)/DaysYr -> 0.50410959 | E10: =(E9-E8+1)/DaysYr -> 1 | F10: =(F9-F8+1)/DaysYr -> 1.0027397 | G10: =(G9-G8+1)/DaysYr -> 1 | H10: =(H9-H8+1)/DaysYr -> 1 | I10: =(I9-I8+1)/DaysYr -> 1 | J10: =(J9-J8+1)/DaysYr -> 1.0027397 | K10: =(K9-K8+1)/DaysYr -> 1 | ... R10: =(R9-R8+1)/DaysYr -> 1.0027397
A11: 명시 구간(1/0) | D11: =IF(D6<=ExplicitEnd,1,0) -> 1 | E11: =IF(E6<=ExplicitEnd,1,0) -> 1 | F11: =IF(F6<=ExplicitEnd,1,0) -> 1 | G11: =IF(G6<=ExplicitEnd,1,0) -> 1 | H11: =IF(H6<=ExplicitEnd,1,0) -> 1 | I11: =IF(I6<=ExplicitEnd,1,0) -> 1 | J11: =IF(J6<=ExplicitEnd,1,0) -> 1 | K11: =IF(K6<=ExplicitEnd,1,0) -> 0 | ... R11: =IF(R6<=ExplicitEnd,1,0) -> 0
A12: 매출 성장률 | B12: % | D12: =IF(D11=1,Forecast!$C$41+(GTermCfg-Forecast!$C$41)*MIN(D6-YEAR(CfStart),FadeTo-YEAR(CfStart))/(FadeTo-YEAR(CfStart)),Forecast!$C$43-(D6-ExplicitEnd)*(Forecast!$C$43-GTermCfg)/FadeYears) -> -0.0055798084 | E12: =IF(E11=1,Forecast!$C$41+(GTermCfg-Forecast!$C$41)*MIN(E6-YEAR(CfStart),FadeTo-YEAR(CfStart))/(FadeTo-YEAR(CfStart)),Forecast!$C$43-(E6-ExplicitEnd)*(Forecast!$C$43-GTermCfg)/FadeYears) -> 0.0008151437 | F12: =IF(F11=1,Forecast!$C$41+(GTermCfg-Forecast!$C$41)*MIN(F6-YEAR(CfStart),FadeTo-YEAR(CfStart))/(FadeTo-YEAR(CfStart)),Forecast!$C$43-(F6-ExplicitEnd)*(Forecast!$C$43-GTermCfg)/FadeYears) -> 0.0072100958 | G12: =IF(G11=1,Forecast!$C$41+(GTermCfg-Forecast!$C$41)*MIN(G6-YEAR(CfStart),FadeTo-YEAR(CfStart))/(FadeTo-YEAR(CfStart)),Forecast!$C$43-(G6-ExplicitEnd)*(Forecast!$C$43-GTermCfg)/FadeYears) -> 0.013605048 | H12: =IF(H11=1,Forecast!$C$41+(GTermCfg-Forecast!$C$41)*MIN(H6-YEAR(CfStart),FadeTo-YEAR(CfStart))/(FadeTo-YEAR(CfStart)),Forecast!$C$43-(H6-ExplicitEnd)*(Forecast!$C$43-GTermCfg)/FadeYears) -> 0.02 | I12: =IF(I11=1,Forecast!$C$41+(GTermCfg-Forecast!$C$41)*MIN(I6-YEAR(CfStart),FadeTo-YEAR(CfStart))/(FadeTo-YEAR(CfStart)),Forecast!$C$43-(I6-ExplicitEnd)*(Forecast!$C$43-GTermCfg)/FadeYears) -> 0.02 | J12: =IF(J11=1,Forecast!$C$41+(GTermCfg-Forecast!$C$41)*MIN(J6-YEAR(CfStart),FadeTo-YEAR(CfStart))/(FadeTo-YEAR(CfStart)),Forecast!$C$43-(J6-ExplicitEnd)*(Forecast!$C$43-GTermCfg)/FadeYears) -> 0.02 | K12: =IF(K11=1,Forecast!$C$41+(GTermCfg-Forecast!$C$41)*MIN(K6-YEAR(CfStart),FadeTo-YEAR(CfStart))/(FadeTo-YEAR(CfStart)),Forecast!$C$43-(K6-ExplicitEnd)*(Forecast!$C$43-GTermCfg)/FadeYears) -> 0.02 | ... R12: =IF(R11=1,Forecast!$C$41+(GTermCfg-Forecast!$C$41)*MIN(R6-YEAR(CfStart),FadeTo-YEAR(CfStart))/(FadeTo-YEAR(CfStart)),Forecast!$C$43-(R6-ExplicitEnd)*(Forecast!$C$43-GTermCfg)/FadeYears) -> 0.02
A13: 회계연도 매출 | B13: 백만원 | D13: =IF(D5=1,RevFY_Last*(1+D12),C13*(1+D12)) -> 3666.4057 | E13: =IF(E5=1,RevFY_Last*(1+E12),D13*(1+E12)) -> 3669.3944 | F13: =IF(F5=1,RevFY_Last*(1+F12),E13*(1+F12)) -> 3695.8511 | G13: =IF(G5=1,RevFY_Last*(1+G12),F13*(1+G12)) -> 3746.1333 | H13: =IF(H5=1,RevFY_Last*(1+H12),G13*(1+H12)) -> 3821.056 | I13: =IF(I5=1,RevFY_Last*(1+I12),H13*(1+I12)) -> 3897.4771 | J13: =IF(J5=1,RevFY_Last*(1+J12),I13*(1+J12)) -> 3975.4266 | K13: =IF(K5=1,RevFY_Last*(1+K12),J13*(1+K12)) -> 4054.9352 | ... R13: =IF(R5=1,RevFY_Last*(1+R12),Q13*(1+R12)) -> 4657.8459
A14: 기간 매출 | B14: 백만원 | D14: =IF(D5=1,D13-H1Rev,D13) -> 1966.9532 | E14: =IF(E5=1,E13-H1Rev,E13) -> 3669.3944 | F14: =IF(F5=1,F13-H1Rev,F13) -> 3695.8511 | G14: =IF(G5=1,G13-H1Rev,G13) -> 3746.1333 | H14: =IF(H5=1,H13-H1Rev,H13) -> 3821.056 | I14: =IF(I5=1,I13-H1Rev,I13) -> 3897.4771 | J14: =IF(J5=1,J13-H1Rev,J13) -> 3975.4266 | K14: =IF(K5=1,K13-H1Rev,K13) -> 4054.9352 | ... R14: =IF(R5=1,R13-H1Rev,R13) -> 4657.8459
A15: 영업이익(EBIT) | B15: 백만원 | D15: =D14*(Forecast!$C$42+MarginConvAmt*MIN((D6-YEAR(CfStart))/(ExplicitEnd-YEAR(CfStart)),1)) -> -10.720779 | E15: =E14*(Forecast!$C$42+MarginConvAmt*MIN((E6-YEAR(CfStart))/(ExplicitEnd-YEAR(CfStart)),1)) -> 13.331031 | F15: =F14*(Forecast!$C$42+MarginConvAmt*MIN((F6-YEAR(CfStart))/(ExplicitEnd-YEAR(CfStart)),1)) -> 46.998348 | G15: =G14*(Forecast!$C$42+MarginConvAmt*MIN((G6-YEAR(CfStart))/(ExplicitEnd-YEAR(CfStart)),1)) -> 81.665699 | H15: =H14*(Forecast!$C$42+MarginConvAmt*MIN((H6-YEAR(CfStart))/(ExplicitEnd-YEAR(CfStart)),1)) -> 118.00751 | I15: =I14*(Forecast!$C$42+MarginConvAmt*MIN((I6-YEAR(CfStart))/(ExplicitEnd-YEAR(CfStart)),1)) -> 155.77032 | J15: =J14*(Forecast!$C$42+MarginConvAmt*MIN((J6-YEAR(CfStart))/(ExplicitEnd-YEAR(CfStart)),1)) -> 194.99645 | K15: =K14*(Forecast!$C$42+MarginConvAmt*MIN((K6-YEAR(CfStart))/(ExplicitEnd-YEAR(CfStart)),1)) -> 198.89638 | ... R15: =R14*(Forecast!$C$42+MarginConvAmt*MIN((R6-YEAR(CfStart))/(ExplicitEnd-YEAR(CfStart)),1)) -> 228.46942
A16: 회계연도 영업이익(과세표준) | B16: 백만원 | D16: =IF(D5=1,H1Op+D15,D15) -> -269.99361 | E16: =IF(E5=1,H1Op+E15,E15) -> 13.331031 | F16: =IF(F5=1,H1Op+F15,F15) -> 46.998348 | G16: =IF(G5=1,H1Op+G15,G15) -> 81.665699 | H16: =IF(H5=1,H1Op+H15,H15) -> 118.00751 | I16: =IF(I5=1,H1Op+I15,I15) -> 155.77032 | J16: =IF(J5=1,H1Op+J15,J15) -> 194.99645 | K16: =IF(K5=1,H1Op+K15,K15) -> 198.89638 | ... R16: =IF(R5=1,H1Op+R15,R15) -> 228.46942
A17: D&A = 매출 × 과거 3년 D&A/매출 | B17: 백만원 | D17: =IF(D11=1,D14*DnaRatio,0) -> 47.532874 | E17: =IF(E11=1,E14*DnaRatio,0) -> 88.673622 | F17: =IF(F11=1,F14*DnaRatio,0) -> 89.312967 | G17: =IF(G11=1,G14*DnaRatio,0) -> 90.528074 | H17: =IF(H11=1,H14*DnaRatio,0) -> 92.338636 | I17: =IF(I11=1,I14*DnaRatio,0) -> 94.185409 | J17: =IF(J11=1,J14*DnaRatio,0) -> 96.069117 | K17: =IF(K11=1,K14*DnaRatio,0) -> 0 | ... R17: =IF(R11=1,R14*DnaRatio,0) -> 0
A18: CAPEX = 매출 × 과거 3년 CAPEX/매출 | B18: 백만원 | D18: =IF(D11=1,D14*CapexRatio,0) -> 25.804154 | E18: =IF(E11=1,E14*CapexRatio,0) -> 48.138216 | F18: =IF(F11=1,F14*CapexRatio,0) -> 48.485297 | G18: =IF(G11=1,G14*CapexRatio,0) -> 49.144942 | H18: =IF(H11=1,H14*CapexRatio,0) -> 50.127841 | I18: =IF(I11=1,I14*CapexRatio,0) -> 51.130398 | J18: =IF(J11=1,J14*CapexRatio,0) -> 52.153006 | K18: =IF(K11=1,K14*CapexRatio,0) -> 0 | ... R18: =IF(R11=1,R14*CapexRatio,0) -> 0
A19: 순운전자본(기말) | B19: 백만원 | C19: =NWC_Open -> 304.03032 | D19: =IF(D11=1,D13*DSO/DaysYr+D13*COGSR*DIO/DaysYr-D13*COGSR*DPO/DaysYr,C19) -> 143.0809 | E19: =IF(E11=1,E13*DSO/DaysYr+E13*COGSR*DIO/DaysYr-E13*COGSR*DPO/DaysYr,D19) -> 143.19754 | F19: =IF(F11=1,F13*DSO/DaysYr+F13*COGSR*DIO/DaysYr-F13*COGSR*DPO/DaysYr,E19) -> 144.23 | G19: =IF(G11=1,G13*DSO/DaysYr+G13*COGSR*DIO/DaysYr-G13*COGSR*DPO/DaysYr,F19) -> 146.19226 | H19: =IF(H11=1,H13*DSO/DaysYr+H13*COGSR*DIO/DaysYr-H13*COGSR*DPO/DaysYr,G19) -> 149.1161 | I19: =IF(I11=1,I13*DSO/DaysYr+I13*COGSR*DIO/DaysYr-I13*COGSR*DPO/DaysYr,H19) -> 152.09843 | J19: =IF(J11=1,J13*DSO/DaysYr+J13*COGSR*DIO/DaysYr-J13*COGSR*DPO/DaysYr,I19) -> 155.14039 | K19: =IF(K11=1,K13*DSO/DaysYr+K13*COGSR*DIO/DaysYr-K13*COGSR*DPO/DaysYr,J19) -> 155.14039 | ... R19: =IF(R11=1,R13*DSO/DaysYr+R13*COGSR*DIO/DaysYr-R13*COGSR*DPO/DaysYr,Q19) -> 155.14039
A20: ΔNWC(증가 = 유출) | B20: 백만원 | D20: =IF(D11=1,D19-C19,0) -> -160.94941 | E20: =IF(E11=1,E19-D19,0) -> 0.1166315 | F20: =IF(F11=1,F19-E19,0) -> 1.0324679 | G20: =IF(G11=1,G19-F19,0) -> 1.9622561 | H20: =IF(H11=1,H19-G19,0) -> 2.9238452 | I20: =IF(I11=1,I19-H19,0) -> 2.9823221 | J20: =IF(J11=1,J19-I19,0) -> 3.0419685 | K20: =IF(K11=1,K19-J19,0) -> 0 | ... R20: =IF(R11=1,R19-Q19,0) -> 0
A21: 실효세율(누진, 회계연도 과세표준) | B21: % | D21: =IF(D16>0,IF(D16>0,SUMPRODUCT((D16>TaxFrom)*(D16-TaxFrom)*TaxDRate),0)/D16,0) -> 0 | E21: =IF(E16>0,IF(E16>0,SUMPRODUCT((E16>TaxFrom)*(E16-TaxFrom)*TaxDRate),0)/E16,0) -> 0.11 | F21: =IF(F16>0,IF(F16>0,SUMPRODUCT((F16>TaxFrom)*(F16-TaxFrom)*TaxDRate),0)/F16,0) -> 0.11 | G21: =IF(G16>0,IF(G16>0,SUMPRODUCT((G16>TaxFrom)*(G16-TaxFrom)*TaxDRate),0)/G16,0) -> 0.11 | H21: =IF(H16>0,IF(H16>0,SUMPRODUCT((H16>TaxFrom)*(H16-TaxFrom)*TaxDRate),0)/H16,0) -> 0.11 | I21: =IF(I16>0,IF(I16>0,SUMPRODUCT((I16>TaxFrom)*(I16-TaxFrom)*TaxDRate),0)/I16,0) -> 0.11 | J21: =IF(J16>0,IF(J16>0,SUMPRODUCT((J16>TaxFrom)*(J16-TaxFrom)*TaxDRate),0)/J16,0) -> 0.11 | K21: =IF(K16>0,IF(K16>0,SUMPRODUCT((K16>TaxFrom)*(K16-TaxFrom)*TaxDRate),0)/K16,0) -> 0.11 | ... R21: =IF(R16>0,IF(R16>0,SUMPRODUCT((R16>TaxFrom)*(R16-TaxFrom)*TaxDRate),0)/R16,0) -> 0.12370703
A22: 법인세 | B22: 백만원 | D22: =MAX(D15,0)*D21 -> 0 | E22: =MAX(E15,0)*E21 -> 1.4664134 | F22: =MAX(F15,0)*F21 -> 5.1698182 | G22: =MAX(G15,0)*G21 -> 8.9832269 | H22: =MAX(H15,0)*H21 -> 12.980826 | I22: =MAX(I15,0)*I21 -> 17.134736 | J22: =MAX(J15,0)*J21 -> 21.449609 | K22: =MAX(K15,0)*K21 -> 21.878602 | ... R22: =MAX(R15,0)*R21 -> 28.263272
A23: NOPAT | B23: 백만원 | D23: =D15-D22 -> -10.720779 | E23: =E15-E22 -> 11.864617 | F23: =F15-F22 -> 41.828529 | G23: =G15-G22 -> 72.682472 | H23: =H15-H22 -> 105.02668 | I23: =I15-I22 -> 138.63559 | J23: =J15-J22 -> 173.54684 | K23: =K15-K22 -> 177.01778 | ... R23: =R15-R22 -> 200.20615
A24: FCFF(체감 재투자 전) | B24: 백만원 | D24: =D23+D17-D18-D20 -> 171.95735 | E24: =E23+E17-E18-E20 -> 52.283392 | F24: =F23+F17-F18-F20 -> 81.623731 | G24: =G23+G17-G18-G20 -> 112.10335 | H24: =H23+H17-H18-H20 -> 144.31363 | I24: =I23+I17-I18-I20 -> 178.70828 | J24: =J23+J17-J18-J20 -> 214.42098 | K24: =K23+K17-K18-K20 -> 177.01778 | ... R24: =R23+R17-R18-R20 -> 200.20615
A26: FY2026 EBIT(정상) | B26: 백만원 | C26: =D13*Forecast!$C$42 -> -19.98356
A27: FY2026 EBIT(혼합) | B27: 백만원 | C27: =D16 -> -269.99361
A28: 출발 NOPAT(선택 규칙) | B28: 백만원 | C28: =IF(RonicStart="normal",C26-IF(C26>0,SUMPRODUCT((C26>TaxFrom)*(C26-TaxFrom)*TaxDRate),0),C27-IF(C27>0,SUMPRODUCT((C27>TaxFrom)*(C27-TaxFrom)*TaxDRate),0)) -> -19.98356
A29: 명시 마지막 연도 EBIT | B29: 백만원 | C29: =INDEX($D$15:$R$15,MATCH(ExplicitEnd,$D$6:$R$6,0)) -> 194.99645
A30: NOPAT | B30: 백만원 | C30: =C29-IF(C29>0,SUMPRODUCT((C29>TaxFrom)*(C29-TaxFrom)*TaxDRate),0) -> 173.54684
A31: 누적 재투자 | B31: 백만원 | C31: =SUMPRODUCT(($D$5:$R$5>1)*$D$11:$R$11*($D$18:$R$18-$D$17:$R$17+$D$20:$R$20)) -> -239.86863
A32: 증분 ROIC(계산값) | C32: =IF(C31>0,(C30-C28)/C31,0) -> 0
A33: 한계세율(세후 Kd) | C33: =T_Kd -> 0.11
A34: 마지막 연도 매출 | B34: 백만원 | C34: =$R$14 -> 4657.8459
A35: 다음 해 NOPAT | B35: 백만원 | C35: =(C34*(1+GTermCfg)*(Forecast!$C$42+MarginConvAmt))-IF((C34*(1+GTermCfg)*(Forecast!$C$42+MarginConvAmt))>0,SUMPRODUCT(((C34*(1+GTermCfg)*(Forecast!$C$42+MarginConvAmt))>TaxFrom)*((C34*(1+GTermCfg)*(Forecast!$C$42+MarginConvAmt))-TaxFrom)*TaxDRate),0) -> 203.77027
A37: SRP 열 1 | C37: =SRP_1 -> 0
A38: WACC | C38: =(1-WD)*(Rf+BetaL*MRP+SRP_1)+WD*Kd_Pre*(1-C33) -> 0.092121243
A39: RONIC(적용) | C39: =IF(C31<=0,C38,IF(C32<C38,C38,IF(C32>RonicCap,MAX(RonicCap,C38),C32))) -> 0.092121243
A40: FCFF | D40: =D24-IF(D11=1,0,D23*D12/C39) -> 171.95735 | E40: =E24-IF(E11=1,0,E23*E12/C39) -> 52.283392 | F40: =F24-IF(F11=1,0,F23*F12/C39) -> 81.623731 | G40: =G24-IF(G11=1,0,G23*G12/C39) -> 112.10335 | H40: =H24-IF(H11=1,0,H23*H12/C39) -> 144.31363 | I40: =I24-IF(I11=1,0,I23*I12/C39) -> 178.70828 | J40: =J24-IF(J11=1,0,J23*J12/C39) -> 214.42098 | K40: =K24-IF(K11=1,0,K23*K12/C39) -> 138.5863 | L40: =L24-IF(L11=1,0,L23*L12/C39) -> 141.11049 | M40: =M24-IF(M11=1,0,M23*M12/C39) -> 143.58823 | N40: =N24-IF(N11=1,0,N23*N12/C39) -> 146.11552 | O40: =O24-IF(O11=1,0,O23*O12/C39) -> 148.69336 | P40: =P24-IF(P11=1,0,P23*P12/C39) -> 151.32275 | Q40: =Q24-IF(Q11=1,0,Q23*Q12/C39) -> 154.00473 | R40: =R24-IF(R11=1,0,R23*R12/C39) -> 156.74035
A41: 현재가치 | D41: =D40*(1+C38)^(-DCF!D10) -> 168.18002 | E41: =E40*(1+C38)^(-DCF!E10) -> 47.855915 | F41: =F40*(1+C38)^(-DCF!F10) -> 68.401406 | G41: =G40*(1+C38)^(-DCF!G10) -> 86.008999 | H41: =H40*(1+C38)^(-DCF!H10) -> 101.38222 | I41: =I40*(1+C38)^(-DCF!I10) -> 114.95511 | J41: =J40*(1+C38)^(-DCF!J10) -> 126.27797 | K41: =K40*(1+C38)^(-DCF!K10) -> 74.723522 | L41: =L40*(1+C38)^(-DCF!L10) -> 69.666741 | M41: =M40*(1+C38)^(-DCF!M10) -> 64.910382 | N41: =N40*(1+C38)^(-DCF!N10) -> 60.473958 | O41: =O40*(1+C38)^(-DCF!O10) -> 56.343047 | P41: =P40*(1+C38)^(-DCF!P10) -> 52.50276 | Q41: =Q40*(1+C38)^(-DCF!Q10) -> 48.926159 | R41: =R40*(1+C38)^(-DCF!R10) -> 45.589475
A42: 영구가치(가치동인) | B42: 백만원 | C42: =C35*(1-GTermCfg/C39)/(C38-GTermCfg)*IF(MidYear=1,(1+C38)^0.5,1) -> 2311.6201
A43: 영구가치 현재가치 | B43: 백만원 | C43: =C42*(1+C38)^(-DCF!R9) -> 643.29826
A44: EV(6/30) | B44: 백만원 | C44: =SUM(D41:R41)+C43 -> 1829.4959
A45: EV(평가기준일) | B45: 백만원 | C45: =C44*(1+C38)^((ValDate-DiscDate)/DaysYr) -> 1870.5865
A46: 주식가치 = EV + EV 밖 항목(Bridge) | B46: 백만원 | C46: =C45+BridgeAdj -> 237976.91
A47: 주당 가치(원) | B47: 원 | C47: =C46*MnToWon/Shares -> 8702.4406
A48: 영구가치 비중 | C48: =C43/C44 -> 0.35162596
A50: SRP 열 2 | C50: =SRP_2 -> 0.01
A51: WACC | C51: =(1-WD)*(Rf+BetaL*MRP+SRP_2)+WD*Kd_Pre*(1-C33) -> 0.10207883
A52: RONIC(적용) | C52: =IF(C31<=0,C51,IF(C32<C51,C51,IF(C32>RonicCap,MAX(RonicCap,C51),C32))) -> 0.10207883
A53: FCFF | D53: =D24-IF(D11=1,0,D23*D12/C52) -> 171.95735 | E53: =E24-IF(E11=1,0,E23*E12/C52) -> 52.283392 | F53: =F24-IF(F11=1,0,F23*F12/C52) -> 81.623731 | G53: =G24-IF(G11=1,0,G23*G12/C52) -> 112.10335 | H53: =H24-IF(H11=1,0,H23*H12/C52) -> 144.31363 | I53: =I24-IF(I11=1,0,I23*I12/C52) -> 178.70828 | J53: =J24-IF(J11=1,0,J23*J12/C52) -> 214.42098 | K53: =K24-IF(K11=1,0,K23*K12/C52) -> 142.33521 | L53: =L24-IF(L11=1,0,L23*L12/C52) -> 144.92769 | M53: =M24-IF(M11=1,0,M23*M12/C52) -> 147.47245 | N53: =N24-IF(N11=1,0,N23*N12/C52) -> 150.06811 | O53: =O24-IF(O11=1,0,O23*O12/C52) -> 152.71568 | P53: =P24-IF(P11=1,0,P23*P12/C52) -> 155.4162 | Q53: =Q24-IF(Q11=1,0,Q23*Q12/C52) -> 158.17073 | R53: =R24-IF(R11=1,0,R23*R12/C52) -> 160.98035
A54: 현재가치 | D54: =D53*(1+C51)^(-DCF!D10) -> 167.79571 | E54: =E53*(1+C51)^(-DCF!E10) -> 47.421754 | F54: =F53*(1+C51)^(-DCF!F10) -> 67.167599 | G54: =G53*(1+C51)^(-DCF!G10) -> 83.693452 | H54: =H53*(1+C51)^(-DCF!H10) -> 97.761441 | I54: =I53*(1+C51)^(-DCF!I10) -> 109.84802 | J54: =J53*(1+C51)^(-DCF!J10) -> 119.5761 | K54: =K53*(1+C51)^(-DCF!K10) -> 72.014336 | L54: =L53*(1+C51)^(-DCF!L10) -> 66.534258 | M54: =M53*(1+C51)^(-DCF!M10) -> 61.431651 | N54: =N53*(1+C51)^(-DCF!N10) -> 56.715167 | O54: =O53*(1+C51)^(-DCF!O10) -> 52.362931 | P54: =P53*(1+C51)^(-DCF!P10) -> 48.353058 | Q54: =Q53*(1+C51)^(-DCF!Q10) -> 44.652022 | R54: =R53*(1+C51)^(-DCF!R10) -> 41.230386
A55: 영구가치(가치동인) | B55: 백만원 | C55: =C35*(1-GTermCfg/C52)/(C51-GTermCfg)*IF(MidYear=1,(1+C51)^0.5,1) -> 2095.6149
A56: 영구가치 현재가치 | B56: 백만원 | C56: =C55*(1+C51)^(-DCF!R9) -> 511.20117
A57: EV(6/30) | B57: 백만원 | C57: =SUM(D54:R54)+C56 -> 1647.7591
A58: EV(평가기준일) | B58: 백만원 | C58: =C57*(1+C51)^((ValDate-DiscDate)/DaysYr) -> 1688.6265
A59: 주식가치 = EV + EV 밖 항목(Bridge) | B59: 백만원 | C59: =C58+BridgeAdj -> 237794.95
A60: 주당 가치(원) | B60: 원 | C60: =C59*MnToWon/Shares -> 8695.7866
A61: 영구가치 비중 | C61: =C56/C57 -> 0.31024024
A63: SRP 열 3 | C63: =SRP_3 -> 0.02
A64: WACC | C64: =(1-WD)*(Rf+BetaL*MRP+SRP_3)+WD*Kd_Pre*(1-C33) -> 0.11203641
A65: RONIC(적용) | C65: =IF(C31<=0,C64,IF(C32<C64,C64,IF(C32>RonicCap,MAX(RonicCap,C64),C32))) -> 0.11203641
A66: FCFF | D66: =D24-IF(D11=1,0,D23*D12/C65) -> 171.95735 | E66: =E24-IF(E11=1,0,E23*E12/C65) -> 52.283392 | F66: =F24-IF(F11=1,0,F23*F12/C65) -> 81.623731 | G66: =G24-IF(G11=1,0,G23*G12/C65) -> 112.10335 | H66: =H24-IF(H11=1,0,H23*H12/C65) -> 144.31363 | I66: =I24-IF(I11=1,0,I23*I12/C65) -> 178.70828 | J66: =J24-IF(J11=1,0,J23*J12/C65) -> 214.42098 | K66: =K24-IF(K11=1,0,K23*K12/C65) -> 145.41773 | L66: =L24-IF(L11=1,0,L23*L12/C65) -> 148.06635 | M66: =M24-IF(M11=1,0,M23*M12/C65) -> 150.66623 | N66: =N24-IF(N11=1,0,N23*N12/C65) -> 153.3181 | O66: =O24-IF(O11=1,0,O23*O12/C65) -> 156.02301 | P66: =P24-IF(P11=1,0,P23*P12/C65) -> 158.78201 | Q66: =Q24-IF(Q11=1,0,Q23*Q12/C65) -> 161.5962 | R66: =R24-IF(R11=1,0,R23*R12/C65) -> 164.46667
A67: 현재가치 | D67: =D66*(1+C64)^(-DCF!D10) -> 167.41572 | E67: =E66*(1+C64)^(-DCF!E10) -> 46.995385 | F67: =F66*(1+C64)^(-DCF!F10) -> 65.966846 | G67: =G66*(1+C64)^(-DCF!G10) -> 81.460239 | H67: =H66*(1+C64)^(-DCF!H10) -> 94.300814 | I67: =I66*(1+C64)^(-DCF!I10) -> 105.01075 | J67: =J66*(1+C64)^(-DCF!J10) -> 113.28546 | K67: =K66*(1+C64)^(-DCF!K10) -> 69.07837 | L67: =L66*(1+C64)^(-DCF!L10) -> 63.250227 | M67: =M66*(1+C64)^(-DCF!M10) -> 57.876547 | N67: =N66*(1+C64)^(-DCF!N10) -> 52.953898 | O67: =O66*(1+C64)^(-DCF!O10) -> 48.451917 | P67: =P66*(1+C64)^(-DCF!P10) -> 44.340912 | Q67: =Q66*(1+C64)^(-DCF!Q10) -> 40.580318 | R67: =R66*(1+C64)^(-DCF!R10) -> 37.134709
A68: 영구가치(가치동인) | B68: 백만원 | C68: =C35*(1-GTermCfg/C65)/(C64-GTermCfg)*IF(MidYear=1,(1+C64)^0.5,1) -> 1917.967
A69: 영구가치 현재가치 | B69: 백만원 | C69: =C68*(1+C64)^(-DCF!R9) -> 410.60155
A70: EV(6/30) | B70: 백만원 | C70: =SUM(D67:R67)+C69 -> 1498.7037
A71: EV(평가기준일) | B71: 백만원 | C71: =C70*(1+C64)^((ValDate-DiscDate)/DaysYr) -> 1539.3603
A72: 주식가치 = EV + EV 밖 항목(Bridge) | B72: 백만원 | C72: =C71+BridgeAdj -> 237645.69
A73: 주당 가치(원) | B73: 원 | C73: =C72*MnToWon/Shares -> 8690.3282
A74: 영구가치 비중 | C74: =C69/C70 -> 0.27397114
A77: 시나리오: 기본
A78: 기간 순번 | C78: 0 | D78: =C78+1 -> 1 | E78: =D78+1 -> 2 | F78: =E78+1 -> 3 | G78: =F78+1 -> 4 | H78: =G78+1 -> 5 | I78: =H78+1 -> 6 | J78: =I78+1 -> 7 | K78: =J78+1 -> 8 | ... R78: =Q78+1 -> 15
A79: 연도 | D79: =YEAR(CfStart)+D78-1 -> 2026 | E79: =YEAR(CfStart)+E78-1 -> 2027 | F79: =YEAR(CfStart)+F78-1 -> 2028 | G79: =YEAR(CfStart)+G78-1 -> 2029 | H79: =YEAR(CfStart)+H78-1 -> 2030 | I79: =YEAR(CfStart)+I78-1 -> 2031 | J79: =YEAR(CfStart)+J78-1 -> 2032 | K79: =YEAR(CfStart)+K78-1 -> 2033 | ... R79: =YEAR(CfStart)+R78-1 -> 2040
A80: 구간 | D80: =IF(D84=1,"명시","체감") -> 명시 | E80: =IF(E84=1,"명시","체감") -> 명시 | F80: =IF(F84=1,"명시","체감") -> 명시 | G80: =IF(G84=1,"명시","체감") -> 명시 | H80: =IF(H84=1,"명시","체감") -> 명시 | I80: =IF(I84=1,"명시","체감") -> 명시 | J80: =IF(J84=1,"명시","체감") -> 명시 | K80: =IF(K84=1,"명시","체감") -> 체감 | ... R80: =IF(R84=1,"명시","체감") -> 체감
A81: 시작일 | D81: =MAX(DATE(D79,1,1),CfStart) -> 46204 | E81: =MAX(DATE(E79,1,1),CfStart) -> 46388 | F81: =MAX(DATE(F79,1,1),CfStart) -> 46753 | G81: =MAX(DATE(G79,1,1),CfStart) -> 47119 | H81: =MAX(DATE(H79,1,1),CfStart) -> 47484 | I81: =MAX(DATE(I79,1,1),CfStart) -> 47849 | J81: =MAX(DATE(J79,1,1),CfStart) -> 48214 | K81: =MAX(DATE(K79,1,1),CfStart) -> 48580 | ... R81: =MAX(DATE(R79,1,1),CfStart) -> 51136
A82: 종료일 | D82: =DATE(D79,12,31) -> 46387 | E82: =DATE(E79,12,31) -> 46752 | F82: =DATE(F79,12,31) -> 47118 | G82: =DATE(G79,12,31) -> 47483 | H82: =DATE(H79,12,31) -> 47848 | I82: =DATE(I79,12,31) -> 48213 | J82: =DATE(J79,12,31) -> 48579 | K82: =DATE(K79,12,31) -> 48944 | ... R82: =DATE(R79,12,31) -> 51501
A83: 기간 비율(일수 ÷ 365) | D83: =(D82-D81+1)/DaysYr -> 0.50410959 | E83: =(E82-E81+1)/DaysYr -> 1 | F83: =(F82-F81+1)/DaysYr -> 1.0027397 | G83: =(G82-G81+1)/DaysYr -> 1 | H83: =(H82-H81+1)/DaysYr -> 1 | I83: =(I82-I81+1)/DaysYr -> 1 | J83: =(J82-J81+1)/DaysYr -> 1.0027397 | K83: =(K82-K81+1)/DaysYr -> 1 | ... R83: =(R82-R81+1)/DaysYr -> 1.0027397
A84: 명시 구간(1/0) | D84: =IF(D79<=ExplicitEnd,1,0) -> 1 | E84: =IF(E79<=ExplicitEnd,1,0) -> 1 | F84: =IF(F79<=ExplicitEnd,1,0) -> 1 | G84: =IF(G79<=ExplicitEnd,1,0) -> 1 | H84: =IF(H79<=ExplicitEnd,1,0) -> 1 | I84: =IF(I79<=ExplicitEnd,1,0) -> 1 | J84: =IF(J79<=ExplicitEnd,1,0) -> 1 | K84: =IF(K79<=ExplicitEnd,1,0) -> 0 | ... R84: =IF(R79<=ExplicitEnd,1,0) -> 0
A85: 매출 성장률 | B85: % | D85: =IF(D84=1,Forecast!$D$41+(GTermCfg-Forecast!$D$41)*MIN(D79-YEAR(CfStart),FadeTo-YEAR(CfStart))/(FadeTo-YEAR(CfStart)),Forecast!$D$43-(D79-ExplicitEnd)*(Forecast!$D$43-GTermCfg)/FadeYears) -> 0.014420192 | E85: =IF(E84=1,Forecast!$D$41+(GTermCfg-Forecast!$D$41)*MIN(E79-YEAR(CfStart),FadeTo-YEAR(CfStart))/(FadeTo-YEAR(CfStart)),Forecast!$D$43-(E79-ExplicitEnd)*(Forecast!$D$43-GTermCfg)/FadeYears) -> 0.015815144 | F85: =IF(F84=1,Forecast!$D$41+(GTermCfg-Forecast!$D$41)*MIN(F79-YEAR(CfStart),FadeTo-YEAR(CfStart))/(FadeTo-YEAR(CfStart)),Forecast!$D$43-(F79-ExplicitEnd)*(Forecast!$D$43-GTermCfg)/FadeYears) -> 0.017210096 | G85: =IF(G84=1,Forecast!$D$41+(GTermCfg-Forecast!$D$41)*MIN(G79-YEAR(CfStart),FadeTo-YEAR(CfStart))/(FadeTo-YEAR(CfStart)),Forecast!$D$43-(G79-ExplicitEnd)*(Forecast!$D$43-GTermCfg)/FadeYears) -> 0.018605048 | H85: =IF(H84=1,Forecast!$D$41+(GTermCfg-Forecast!$D$41)*MIN(H79-YEAR(CfStart),FadeTo-YEAR(CfStart))/(FadeTo-YEAR(CfStart)),Forecast!$D$43-(H79-ExplicitEnd)*(Forecast!$D$43-GTermCfg)/FadeYears) -> 0.02 | I85: =IF(I84=1,Forecast!$D$41+(GTermCfg-Forecast!$D$41)*MIN(I79-YEAR(CfStart),FadeTo-YEAR(CfStart))/(FadeTo-YEAR(CfStart)),Forecast!$D$43-(I79-ExplicitEnd)*(Forecast!$D$43-GTermCfg)/FadeYears) -> 0.02 | J85: =IF(J84=1,Forecast!$D$41+(GTermCfg-Forecast!$D$41)*MIN(J79-YEAR(CfStart),FadeTo-YEAR(CfStart))/(FadeTo-YEAR(CfStart)),Forecast!$D$43-(J79-ExplicitEnd)*(Forecast!$D$43-GTermCfg)/FadeYears) -> 0.02 | K85: =IF(K84=1,Forecast!$D$41+(GTermCfg-Forecast!$D$41)*MIN(K79-YEAR(CfStart),FadeTo-YEAR(CfStart))/(FadeTo-YEAR(CfStart)),Forecast!$D$43-(K79-ExplicitEnd)*(Forecast!$D$43-GTermCfg)/FadeYears) -> 0.02 | ... R85: =IF(R84=1,Forecast!$D$41+(GTermCfg-Forecast!$D$41)*MIN(R79-YEAR(CfStart),FadeTo-YEAR(CfStart))/(FadeTo-YEAR(CfStart)),Forecast!$D$43-(R79-ExplicitEnd)*(Forecast!$D$43-GTermCfg)/FadeYears) -> 0.02
A86: 회계연도 매출 | B86: 백만원 | D86: =IF(D78=1,RevFY_Last*(1+D85),C86*(1+D85)) -> 3740.1453 | E86: =IF(E78=1,RevFY_Last*(1+E85),D86*(1+E85)) -> 3799.2962 | F86: =IF(F78=1,RevFY_Last*(1+F85),E86*(1+F85)) -> 3864.6825 | G86: =IF(G78=1,RevFY_Last*(1+G85),F86*(1+G85)) -> 3936.5851 | H86: =IF(H78=1,RevFY_Last*(1+H85),G86*(1+H85)) -> 4015.3168 | I86: =IF(I78=1,RevFY_Last*(1+I85),H86*(1+I85)) -> 4095.6231 | J86: =IF(J78=1,RevFY_Last*(1+J85),I86*(1+J85)) -> 4177.5356 | K86: =IF(K78=1,RevFY_Last*(1+K85),J86*(1+K85)) -> 4261.0863 | ... R86: =IF(R78=1,RevFY_Last*(1+R85),Q86*(1+R85)) -> 4894.6488
A87: 기간 매출 | B87: 백만원 | D87: =IF(D78=1,D86-H1Rev,D86) -> 2040.6927 | E87: =IF(E78=1,E86-H1Rev,E86) -> 3799.2962 | F87: =IF(F78=1,F86-H1Rev,F86) -> 3864.6825 | G87: =IF(G78=1,G86-H1Rev,G86) -> 3936.5851 | H87: =IF(H78=1,H86-H1Rev,H86) -> 4015.3168 | I87: =IF(I78=1,I86-H1Rev,I86) -> 4095.6231 | J87: =IF(J78=1,J86-H1Rev,J86) -> 4177.5356 | K87: =IF(K78=1,K86-H1Rev,K86) -> 4261.0863 | ... R87: =IF(R78=1,R86-H1Rev,R86) -> 4894.6488
A88: 영업이익(EBIT) | B88: 백만원 | D88: =D87*(Forecast!$D$42+MarginConvAmt*MIN((D79-YEAR(CfStart))/(ExplicitEnd-YEAR(CfStart)),1)) -> 29.691162 | E88: =E87*(Forecast!$D$42+MarginConvAmt*MIN((E79-YEAR(CfStart))/(ExplicitEnd-YEAR(CfStart)),1)) -> 89.788893 | F88: =F87*(Forecast!$D$42+MarginConvAmt*MIN((F79-YEAR(CfStart))/(ExplicitEnd-YEAR(CfStart)),1)) -> 126.43894 | G88: =G87*(Forecast!$D$42+MarginConvAmt*MIN((G79-YEAR(CfStart))/(ExplicitEnd-YEAR(CfStart)),1)) -> 164.54925 | H88: =H87*(Forecast!$D$42+MarginConvAmt*MIN((H79-YEAR(CfStart))/(ExplicitEnd-YEAR(CfStart)),1)) -> 204.3133 | I88: =I87*(Forecast!$D$42+MarginConvAmt*MIN((I79-YEAR(CfStart))/(ExplicitEnd-YEAR(CfStart)),1)) -> 245.60208 | J88: =J87*(Forecast!$D$42+MarginConvAmt*MIN((J79-YEAR(CfStart))/(ExplicitEnd-YEAR(CfStart)),1)) -> 288.4607 | K88: =K87*(Forecast!$D$42+MarginConvAmt*MIN((K79-YEAR(CfStart))/(ExplicitEnd-YEAR(CfStart)),1)) -> 294.22991 | ... R88: =R87*(Forecast!$D$42+MarginConvAmt*MIN((R79-YEAR(CfStart))/(ExplicitEnd-YEAR(CfStart)),1)) -> 337.97768
A89: 회계연도 영업이익(과세표준) | B89: 백만원 | D89: =IF(D78=1,H1Op+D88,D88) -> -229.58167 | E89: =IF(E78=1,H1Op+E88,E88) -> 89.788893 | F89: =IF(F78=1,H1Op+F88,F88) -> 126.43894 | G89: =IF(G78=1,H1Op+G88,G88) -> 164.54925 | H89: =IF(H78=1,H1Op+H88,H88) -> 204.3133 | I89: =IF(I78=1,H1Op+I88,I88) -> 245.60208 | J89: =IF(J78=1,H1Op+J88,J88) -> 288.4607 | K89: =IF(K78=1,H1Op+K88,K88) -> 294.22991 | ... R89: =IF(R78=1,H1Op+R88,R88) -> 337.97768
A90: D&A = 매출 × 과거 3년 D&A/매출 | B90: 백만원 | D90: =IF(D84=1,D87*DnaRatio,0) -> 49.314845 | E90: =IF(E84=1,E87*DnaRatio,0) -> 91.812796 | F90: =IF(F84=1,F87*DnaRatio,0) -> 93.392903 | G90: =IF(G84=1,G87*DnaRatio,0) -> 95.130482 | H90: =IF(H84=1,H87*DnaRatio,0) -> 97.033092 | I90: =IF(I84=1,I87*DnaRatio,0) -> 98.973754 | J90: =IF(J84=1,J87*DnaRatio,0) -> 100.95323 | K90: =IF(K84=1,K87*DnaRatio,0) -> 0 | ... R90: =IF(R84=1,R87*DnaRatio,0) -> 0
A91: CAPEX = 매출 × 과거 3년 CAPEX/매출 | B91: 백만원 | D91: =IF(D84=1,D87*CapexRatio,0) -> 26.771532 | E91: =IF(E84=1,E87*CapexRatio,0) -> 49.842378 | F91: =IF(F84=1,F87*CapexRatio,0) -> 50.700171 | G91: =IF(G84=1,G87*CapexRatio,0) -> 51.64345 | H91: =IF(H84=1,H87*CapexRatio,0) -> 52.676319 | I91: =IF(I84=1,I87*CapexRatio,0) -> 53.729845 | J91: =IF(J84=1,J87*CapexRatio,0) -> 54.804442 | K91: =IF(K84=1,K87*CapexRatio,0) -> 0 | ... R91: =IF(R84=1,R87*CapexRatio,0) -> 0
A92: 순운전자본(기말) | B92: 백만원 | C92: =NWC_Open -> 304.03032 | D92: =IF(D84=1,D86*DSO/DaysYr+D86*COGSR*DIO/DaysYr-D86*COGSR*DPO/DaysYr,C92) -> 145.95858 | E92: =IF(E84=1,E86*DSO/DaysYr+E86*COGSR*DIO/DaysYr-E86*COGSR*DPO/DaysYr,D92) -> 148.26693 | F92: =IF(F84=1,F86*DSO/DaysYr+F86*COGSR*DIO/DaysYr-F86*COGSR*DPO/DaysYr,E92) -> 150.81862 | G92: =IF(G84=1,G86*DSO/DaysYr+G86*COGSR*DIO/DaysYr-G86*COGSR*DPO/DaysYr,F92) -> 153.62461 | H92: =IF(H84=1,H86*DSO/DaysYr+H86*COGSR*DIO/DaysYr-H86*COGSR*DPO/DaysYr,G92) -> 156.6971 | I92: =IF(I84=1,I86*DSO/DaysYr+I86*COGSR*DIO/DaysYr-I86*COGSR*DPO/DaysYr,H92) -> 159.83104 | J92: =IF(J84=1,J86*DSO/DaysYr+J86*COGSR*DIO/DaysYr-J86*COGSR*DPO/DaysYr,I92) -> 163.02767 | K92: =IF(K84=1,K86*DSO/DaysYr+K86*COGSR*DIO/DaysYr-K86*COGSR*DPO/DaysYr,J92) -> 163.02767 | ... R92: =IF(R84=1,R86*DSO/DaysYr+R86*COGSR*DIO/DaysYr-R86*COGSR*DPO/DaysYr,Q92) -> 163.02767
A93: ΔNWC(증가 = 유출) | B93: 백만원 | D93: =IF(D84=1,D92-C92,0) -> -158.07174 | E93: =IF(E84=1,E92-D92,0) -> 2.3083559 | F93: =IF(F84=1,F92-E92,0) -> 2.5516881 | G93: =IF(G84=1,G92-F92,0) -> 2.8059877 | H93: =IF(H84=1,H92-G92,0) -> 3.0724922 | I93: =IF(I84=1,I92-H92,0) -> 3.1339421 | J93: =IF(J84=1,J92-I92,0) -> 3.1966209 | K93: =IF(K84=1,K92-J92,0) -> 0 | ... R93: =IF(R84=1,R92-Q92,0) -> 0
A94: 실효세율(누진, 회계연도 과세표준) | B94: % | D94: =IF(D89>0,IF(D89>0,SUMPRODUCT((D89>TaxFrom)*(D89-TaxFrom)*TaxDRate),0)/D89,0) -> 0 | E94: =IF(E89>0,IF(E89>0,SUMPRODUCT((E89>TaxFrom)*(E89-TaxFrom)*TaxDRate),0)/E89,0) -> 0.11 | F94: =IF(F89>0,IF(F89>0,SUMPRODUCT((F89>TaxFrom)*(F89-TaxFrom)*TaxDRate),0)/F89,0) -> 0.11 | G94: =IF(G89>0,IF(G89>0,SUMPRODUCT((G89>TaxFrom)*(G89-TaxFrom)*TaxDRate),0)/G89,0) -> 0.11 | H94: =IF(H89>0,IF(H89>0,SUMPRODUCT((H89>TaxFrom)*(H89-TaxFrom)*TaxDRate),0)/H89,0) -> 0.11232223 | I94: =IF(I89>0,IF(I89>0,SUMPRODUCT((I89>TaxFrom)*(I89-TaxFrom)*TaxDRate),0)/I89,0) -> 0.13042421 | J94: =IF(J89>0,IF(J89>0,SUMPRODUCT((J89>TaxFrom)*(J89-TaxFrom)*TaxDRate),0)/J89,0) -> 0.14373311 | K94: =IF(K89>0,IF(K89>0,SUMPRODUCT((K89>TaxFrom)*(K89-TaxFrom)*TaxDRate),0)/K89,0) -> 0.14522854 | ... R94: =IF(R89>0,IF(R89>0,SUMPRODUCT((R89>TaxFrom)*(R89-TaxFrom)*TaxDRate),0)/R89,0) -> 0.15490694
A95: 법인세 | B95: 백만원 | D95: =MAX(D88,0)*D94 -> 0 | E95: =MAX(E88,0)*E94 -> 9.8767783 | F95: =MAX(F88,0)*F94 -> 13.908284 | G95: =MAX(G88,0)*G94 -> 18.100417 | H95: =MAX(H88,0)*H94 -> 22.948925 | I95: =MAX(I88,0)*I94 -> 32.032458 | J95: =MAX(J88,0)*J94 -> 41.461353 | K95: =MAX(K88,0)*K94 -> 42.73058 | ... R95: =MAX(R88,0)*R94 -> 52.35509
A96: NOPAT | B96: 백만원 | D96: =D88-D95 -> 29.691162 | E96: =E88-E95 -> 79.912115 | F96: =F88-F95 -> 112.53066 | G96: =G88-G95 -> 146.44883 | H96: =H88-H95 -> 181.36437 | I96: =I88-I95 -> 213.56962 | J96: =J88-J95 -> 246.99934 | K96: =K88-K95 -> 251.49933 | ... R96: =R88-R95 -> 285.62259
A97: FCFF(체감 재투자 전) | B97: 백만원 | D97: =D96+D90-D91-D93 -> 210.30621 | E97: =E96+E90-E91-E93 -> 119.57418 | F97: =F96+F90-F91-F93 -> 152.67171 | G97: =G96+G90-G91-G93 -> 187.12988 | H97: =H96+H90-H91-H93 -> 222.64865 | I97: =I96+I90-I91-I93 -> 255.67959 | J97: =J96+J90-J91-J93 -> 289.95151 | K97: =K96+K90-K91-K93 -> 251.49933 | ... R97: =R96+R90-R91-R93 -> 285.62259
A99: FY2026 EBIT(정상) | B99: 백만원 | C99: =D86*Forecast!$D$42 -> 54.417432
A100: FY2026 EBIT(혼합) | B100: 백만원 | C100: =D89 -> -229.58167
A101: 출발 NOPAT(선택 규칙) | B101: 백만원 | C101: =IF(RonicStart="normal",C99-IF(C99>0,SUMPRODUCT((C99>TaxFrom)*(C99-TaxFrom)*TaxDRate),0),C100-IF(C100>0,SUMPRODUCT((C100>TaxFrom)*(C100-TaxFrom)*TaxDRate),0)) -> 48.431515
A102: 명시 마지막 연도 EBIT | B102: 백만원 | C102: =INDEX($D$88:$R$88,MATCH(ExplicitEnd,$D$79:$R$79,0)) -> 288.4607
A103: NOPAT | B103: 백만원 | C103: =C102-IF(C102>0,SUMPRODUCT((C102>TaxFrom)*(C102-TaxFrom)*TaxDRate),0) -> 246.99934
A104: 누적 재투자 | B104: 백만원 | C104: =SUMPRODUCT(($D$78:$R$78>1)*$D$84:$R$84*($D$91:$R$91-$D$90:$R$90+$D$93:$R$93)) -> -246.83057
A105: 증분 ROIC(계산값) | C105: =IF(C104>0,(C103-C101)/C104,0) -> 0
A106: 한계세율(세후 Kd) | C106: =T_Kd -> 0.11
A107: 마지막 연도 매출 | B107: 백만원 | C107: =$R$87 -> 4894.6488
A108: 다음 해 NOPAT | B108: 백만원 | C108: =(C107*(1+GTermCfg)*(Forecast!$D$42+MarginConvAmt))-IF((C107*(1+GTermCfg)*(Forecast!$D$42+MarginConvAmt))>0,SUMPRODUCT(((C107*(1+GTermCfg)*(Forecast!$D$42+MarginConvAmt))>TaxFrom)*((C107*(1+GTermCfg)*(Forecast!$D$42+MarginConvAmt))-TaxFrom)*TaxDRate),0) -> 290.89504
...

Sheet Football
A1: Football — 방법별 주당 범위 (원, 가정 하 추정·참고 범위)
A2: 막대 = 낮음~높음, 점 = 대표값, 빨간 점선 = 기준일 종가. 투자 권유 아님. 시세 자료 출처: 한국거래소 통계정보
A4: 그룹 | B4: 항목 | C4: 낮음 | D4: 높음 | E4: 대표 | F4: y | G4: y | H4: 정의
A5: DCF(연결) | B5: DCF 비관 | C5: =MIN(Scenarios!$B$6:$D$6) -> 8690.3282 | D5: =MAX(Scenarios!$B$6:$D$6) -> 8702.4406 | E5: =Scenarios!$B$6 -> 8702.4406 | F5: =ROWS(B5:$B$13) -> 9 | G5: =F5 -> 9 | H5: SRP 2%~0% 범위, 대표 = SRP 0%
A6: DCF(연결) | B6: DCF 기본 | C6: =MIN(Scenarios!$B$7:$D$7) -> 8716.4931 | D6: =MAX(Scenarios!$B$7:$D$7) -> 8733.8645 | E6: =Scenarios!$B$7 -> 8733.8645 | F6: =ROWS(B6:$B$13) -> 8 | G6: =F6 -> 8 | H6: SRP 2%~0% 범위, 대표 = SRP 0%
A7: DCF(연결) | B7: DCF 낙관 | C7: =MIN(Scenarios!$B$8:$D$8) -> 8744.4261 | D7: =MAX(Scenarios!$B$8:$D$8) -> 8767.5065 | E7: =Scenarios!$B$8 -> 8767.5065 | F7: =ROWS(B7:$B$13) -> 7 | G7: =F7 -> 7 | H7: SRP 2%~0% 범위, 대표 = SRP 0%
A8: 상대가치(연결, 피어 LTM) | B8: ="EV/EBITDA (n="&Peers!$C$15&")" -> EV/EBITDA (n=3) | C8: =Peers!$H$15 -> N/M | D8: =Peers!$J$15 -> N/M | E8: =Peers!$I$15 -> N/M | F8: =ROWS(B8:$B$13) -> 6 | G8: =F8 -> 6 | H8: 피어 사분위 × 대상 LTM 지표 + EV 밖 항목
A9: 상대가치(연결, 피어 LTM) | B9: ="PER (n="&Peers!$C$19&")" -> PER (n=5) | C9: =Peers!$H$19 -> N/M | D9: =Peers!$J$19 -> N/M | E9: =Peers!$I$19 -> N/M | F9: =ROWS(B9:$B$13) -> 5 | G9: =F9 -> 5 | H9: 피어 사분위 × 대상 LTM 지표 + EV 밖 항목
A10: 상대가치(연결, 피어 LTM) | B10: ="EV/Sales (n="&Peers!$C$17&")" -> EV/Sales (n=3) | C10: =Peers!$H$17 -> N/M | D10: =Peers!$J$17 -> N/M | E10: =Peers!$I$17 -> N/M | F10: =ROWS(B10:$B$13) -> 4 | G10: =F10 -> 4 | H10: 피어 사분위 × 대상 LTM 지표 + EV 밖 항목
A11: 상대가치(연결, 피어 LTM) | B11: ="PBR (n="&Peers!$C$18&")" -> PBR (n=6) | C11: =Peers!$H$18 -> 2032.8216 | D11: =Peers!$J$18 -> 4204.2034 | E11: =Peers!$I$18 -> 2566.1478 | F11: =ROWS(B11:$B$13) -> 3 | G11: =F11 -> 3 | H11: 피어 사분위 × 대상 LTM 지표 + EV 밖 항목
A12: 블록 거래 가격(참고) | B12: 지배 블록 1주당 | C12: =Block_q1 -> 18206.613 | D12: =Block_q3 -> 27034.985 | E12: =Block_q2 -> 21386.951 | F12: =ROWS(B12:$B$13) -> 2 | G12: =F12 -> 2 | H12: 20일 VWAP × (1 + 프리미엄, D6). 지분 전체 가치 아님
A13: 참고 | B13: 순자산가치(장부) | C13: =NavPerShare -> 4357.6355 | D13: =NavPerShare -> 4357.6355 | E13: =NavPerShare -> 4357.6355 | F13: =ROWS(B13:$B$13) -> 1 | G13: =F13 -> 1 | H13: 지배주주지분 장부 ÷ 주식수(재평가 없음, 자산가치 접근 참고)
B15: 기준일 종가 선 | C15: =Close -> 20000 | D15: =Close -> 20000 | E15: ="기준일 종가 "&TEXT(Close,"#,##0")&"원" -> 기준일 종가 20,000원 | F15: 0 | G15: =ROWS(B5:B13)+1 -> 10

Sheet Convergence
A1: Convergence — 수렴 시험 (사전 고정 기준)
A2: 판정 = 엔진 기록값(회색). 아래 '살아 있는 모델'은 같은 기준을 지금 엑셀 값으로 다시 계산한 것 — 일치 여부는 Checks INFO
A4: 기준(사전 고정) | B4: 기본 DCF 주당가치(SRP 0%)가 피어 EV/EBITDA 사분위 주당 범위 안이면 '수렴'(기록만, P7-B 성공 기준 아님)
A6: 엔진 기록 | B6: DCF 주당(원) | C6: 사분위 q25(원) | D6: 사분위 q75(원) | E6: n | F6: 판정 | G6: 비고
A7: C2 — 사전 고정 1차 판정 | B7: 8733.8645 | C7: n/a | D7: n/a | E7: 3 | F7: 판정 불가(대상 지표 ≤ 0) | G7: 보완 전 피어 표(EBITDA n=5)
A8: C3 — 공통 규칙 수정 후 | B8: 8733.8645 | C8: n/a | D8: n/a | E8: 3 | F8: 판정 불가(대상 지표 ≤ 0) | G8: D&A 보완 후 피어 표
A9: 같은 기준, 보완 전 표로 본 C3 | C9: n/a | D9: n/a | E9: 3
A11: 살아 있는 모델(현재 입력)
A12: 항목 | B12: DCF 주당(원) | C12: 사분위 q25(원) | D12: 사분위 q75(원) | E12: n | F12: 판정
A13: 기본 DCF(SRP 열 1) vs 피어 EV/EBITDA 사분위 | B13: =INDEX(ScenGridPS,MATCH("기본",ScenNames,0),1) -> 8733.8645 | C13: =Peers!$H$15 -> N/M | D13: =Peers!$J$15 -> N/M | E13: =Peers!$C$15 -> 3 | F13: =IF(COUNT(C13,D13)<2,"판정 불가(대상 지표 ≤ 0)",IF(AND(B13>=C13,B13<=D13),"수렴","미수렴 → 원인 분해")) -> 판정 불가(대상 지표 ≤ 0)
A14: 기본 DCF(SRP 열 1) vs 보완 전 표 사분위 | B14: =INDEX(ScenGridPS,MATCH("기본",ScenNames,0),1) -> 8733.8645 | C14: =Peers!$H$16 -> N/M | D14: =Peers!$J$16 -> N/M | E14: =Peers!$C$16 -> 3 | F14: =IF(COUNT(C14,D14)<2,"판정 불가(대상 지표 ≤ 0)",IF(AND(B14>=C14,B14<=D14),"수렴","미수렴 → 원인 분해")) -> 판정 불가(대상 지표 ≤ 0)
A16: 범위 밖 거리(원, 0 = 안) | B16: =IFERROR(IF(Convergence!$B$13>Convergence!$D$13,Convergence!$B$13-Convergence!$D$13,IF(Convergence!$B$13<Convergence!$C$13,Convergence!$B$13-Convergence!$C$13,0)),"N/M") -> N/M
A17: 기준일 종가 대비 기본 DCF(표시만) | B17: =Convergence!$B$13/Close-1 -> -0.56330678

Sheet Checks
A1: Checks — 모델 점검
A2: ERR(또는 이 표 안 수식 오류)가 하나라도 있으면 master check = ERR. WARN은 주의 표시, INFO는 엔진 값 대조(입력을 바꾸면 달라지는 것이 정상). N/M = 양쪽 모두 숫자가 아님(일치), 한쪽만 N/M이면 DIFF
B3: MASTER CHECK | C3: =IF(AND(COUNTIF($C$6:$C$74,"ERR")=0,SUMPRODUCT(ISERROR($C$6:$E$74)*1)=0),"OK","ERR") -> OK | D3: ="ERR "&COUNTIF($C$6:$C$74,"ERR")&" / WARN "&COUNTIF($C$6:$C$74,"WARN")&" / INFO 차이 "&COUNTIF($C$6:$C$74,"DIFF")&IF(SUMPRODUCT(ISERROR($C$6:$E$74)*1)>0," / 수식 오류 "&SUMPRODUCT(ISERROR($C$6:$E$74)*1),"") -> ERR 0 / WARN 3 / INFO 차이 0
A5: # | B5: 항목 | C5: 상태 | D5: 값 | E5: 기준·비교 | F5: 종류 | G5: 설명
A6: 1 | B6: SOTP 이중 계산 점검: '종속' 투자 줄은 비영업 분류에 없음(시가·장부로 바꿔 넣음) | C6: =IF(COUNTIFS(BsClass,"non_operating",BsName,"*종속*")=0,"OK","ERR") -> OK | D6: =SotpSubLines -> 70894.006 | E6: =SotpBook -> 51166 | F6: CHECK
A7: 2 | B7: SOTP 단위 점검: 피투자회사 장부가 합계 ≤ '종속' 줄 × 1.02 | C7: =IF(SotpBook<=SotpSubLines*1.02+0.01,"OK","WARN") -> OK | D7: =SotpBook -> 51166 | E7: =SotpSubLines -> 70894.006 | F7: WARN | G7: 출자현황 금액 단위나 이름 일치가 맞지 않으면 WARN
A8: 3 | B8: SOTP 상장 지분 = 보유 주식수 × 종가(직접 보유) | C8: =IF(ABS(SotpListed-SUMPRODUCT(SubShares,SubClose,SubListedDirect)/MnToWon)<0.001,"OK","ERR") -> OK | D8: =SotpListed -> 142764 | F8: CHECK
A9: 4 | B9: 상장 관계기업 시가 = 보유 주식수 × 종가 × (1 − 할인) | C9: =IF(ABS(AssocValue-SUMPRODUCT(AssocShares,AssocClose)/MnToWon*(1-AssocDiscount))<0.001,"OK","ERR") -> OK | D9: =AssocValue -> 51936 | F9: CHECK
A10: 5 | B10: 상장 관계기업 이중 계산 점검: 빼는 장부 ≤ 관계기업 줄(또는 SOTP 나머지)·장부 합 | C10: =IF(AND(AssocReplaced<=SUM(AssocBook)+0.001,AssocReplaced<=MAX(AssocLines,SotpRemainder)+0.001),"OK","ERR") -> OK | D10: =AssocReplaced -> 12262 | E10: =AssocLines -> 13228.925 | F10: CHECK
A11: 6 | B11: 주식가치 = EV − 순차입금 + 비영업 − 비지배(+ 대여금 조정) | C11: =IF(ABS(Equity-(EV_930-NetDebt+Bridge!$C$9-Bridge!$C$20))<0.001,"OK","ERR") -> OK | D11: =Equity -> 238836.23 | F11: CHECK
A12: 7 | B12: 순차입금 = 차입금 + 리스 − 현금성 | C12: =IF(ABS(NetDebt-(Bridge!$C$5+Bridge!$C$6-Bridge!$C$7))<0.001,"OK","ERR") -> OK | D12: =NetDebt -> -1055.9909 | F12: CHECK
A13: 8 | B13: EV ↔ 주식가치 왕복(주당 × 주식수 − EV 밖 항목 = EV) | C13: =IF(ABS(PerShare*Shares/MnToWon-BridgeAdj-EV_930)<0.01,"OK","ERR") -> OK | D13: =PerShare*Shares/MnToWon-BridgeAdj -> 2729.9032 | E13: =EV_930 -> 2729.9032 | F13: CHECK
A14: 9 | B14: 시나리오 표 선택 칸 = 살아 있는 모델(Bridge 주당) | C14: =IF(ABS(ScenSelPS-PerShare)<0.5,"OK","ERR") -> OK | D14: =ScenSelPS -> 8733.8645 | E14: =PerShare -> 8733.8645 | F14: CHECK
A15: 10 | B15: WACC > g (모든 시나리오·SRP, Gordon 조건) | C15: =IF(MIN(Scenarios!$B$12:$D$14)>MAX(GTermCfg),"OK","ERR") -> OK | D15: =MIN(Scenarios!$B$12:$D$14) -> 0.092121243 | E15: =MAX(GTermCfg) -> 0.02 | F15: CHECK
A16: 11 | B16: 구조 판단 규칙 = 설정한 평가 구조 | C16: =IF(StructureRule=StructureChoice,"OK","ERR") -> OK | D16: =StructureRule -> consolidated | E16: =StructureChoice -> consolidated | F16: CHECK
A17: 12 | B17: 법인세 구간 연속(0에서 시작, 상한 = 다음 하한, 마지막 상한 없음) | C17: =IF(AND(Inputs!$B$98=0,Inputs!$B$99=Inputs!$C$98,Inputs!$B$100=Inputs!$C$99,Inputs!$B$101=Inputs!$C$100,ISBLANK(Inputs!$C$101)),"OK","ERR") -> OK | F17: CHECK
A18: 13 | B18: 시나리오 선택이 목록 값 | C18: =IF(ISNUMBER(ScenIdx),"OK","ERR") -> OK | D18: =ScenSel -> 기본 | F18: CHECK
A19: 14 | B19: SRP 선택이 목록 값 | C19: =IF(ISNUMBER(MATCH(SRP_Sel,SRP_List,0)),"OK","ERR") -> OK | D19: =SRP_Sel -> 0 | F19: CHECK
A20: 15 | B20: 기간 열 수 = 명시 끝 + 체감 연수(생성 시 고정) | C20: =IF(Forecast!$R$49=ExplicitEnd+FadeYears,"OK","ERR") -> OK | D20: =Forecast!$R$49 -> 2040 | E20: =ExplicitEnd+FadeYears -> 2040 | F20: CHECK
A21: 16 | B21: 체감 마지막 연도 성장률 = 영구성장률 | C21: =IF(ABS(Forecast!$R$55-GTerm_Sel)<1E-12,"OK","ERR") -> OK | D21: =Forecast!$R$55 -> 0.02 | E21: =GTerm_Sel -> 0.02 | F21: CHECK
A22: 17 | B22: 명시 기간 첫 연도 = 현금흐름 시작 연도 | C22: =IF(Forecast!$D$49=YEAR(CfStart),"OK","ERR") -> OK | F22: CHECK
A23: 18 | B23: 유통주식수 > 0 | C23: =IF(Shares>0,"OK","ERR") -> OK | D23: =Shares -> 27345997 | F23: CHECK
A24: 19 | B24: 구조 판단 비율 단위 점검: 시장 주식가치 ÷ (종가 × 주식수 ÷ 단위)가 0.5~2배 | C24: =IF(AND(MarketEquity/(Close*Shares/MnToWon)>0.5,MarketEquity/(Close*Shares/MnToWon)<2),"OK","ERR") -> OK | D24: =MarketEquity/(Close*Shares/MnToWon) -> 1 | E24: 1 | F24: CHECK | G24: P4-X: 우선주 가격 차이로 정확히 1은 아님. 단위 오류면 100만 배
A25: 20 | B25: 수식 오류 0개: Cover | C25: =IF(SUMPRODUCT(ISERROR(Cover!$A$1:$B$2)*1)=0,"OK","ERR") -> OK | D25: =SUMPRODUCT(ISERROR(Cover!$A$1:$B$2)*1) -> 0 | E25: 0 | F25: CHECK | G25: #REF!·#DIV/0!·#NAME?·#VALUE! 등
A26: 21 | B26: 수식 오류 0개: Forecast | C26: =IF(SUMPRODUCT(ISERROR(Forecast!$A$1:$R$95)*1)=0,"OK","ERR") -> OK | D26: =SUMPRODUCT(ISERROR(Forecast!$A$1:$R$95)*1) -> 0 | E26: 0 | F26: CHECK | G26: #REF!·#DIV/0!·#NAME?·#VALUE! 등
A27: 22 | B27: 수식 오류 0개: WACC | C27: =IF(SUMPRODUCT(ISERROR(WACC!$A$1:$E$33)*1)=0,"OK","ERR") -> OK | D27: =SUMPRODUCT(ISERROR(WACC!$A$1:$E$33)*1) -> 0 | E27: 0 | F27: CHECK | G27: #REF!·#DIV/0!·#NAME?·#VALUE! 등
A28: 23 | B28: 수식 오류 0개: DCF | C28: =IF(SUMPRODUCT(ISERROR(DCF!$A$1:$R$59)*1)=0,"OK","ERR") -> OK | D28: =SUMPRODUCT(ISERROR(DCF!$A$1:$R$59)*1) -> 0 | E28: 0 | F28: CHECK | G28: #REF!·#DIV/0!·#NAME?·#VALUE! 등
A29: 24 | B29: 수식 오류 0개: Bridge | C29: =IF(SUMPRODUCT(ISERROR(Bridge!$A$1:$D$37)*1)=0,"OK","ERR") -> OK | D29: =SUMPRODUCT(ISERROR(Bridge!$A$1:$D$37)*1) -> 0 | E29: 0 | F29: CHECK | G29: #REF!·#DIV/0!·#NAME?·#VALUE! 등
A30: 25 | B30: 수식 오류 0개: Peers | C30: =IF(SUMPRODUCT(ISERROR(Peers!$A$1:$N$20)*1)=0,"OK","ERR") -> OK | D30: =SUMPRODUCT(ISERROR(Peers!$A$1:$N$20)*1) -> 0 | E30: 0 | F30: CHECK | G30: #REF!·#DIV/0!·#NAME?·#VALUE! 등
A31: 26 | B31: 수식 오류 0개: Premium | C31: =IF(SUMPRODUCT(ISERROR(Premium!$A$1:$F$33)*1)=0,"OK","ERR") -> OK | D31: =SUMPRODUCT(ISERROR(Premium!$A$1:$F$33)*1) -> 0 | E31: 0 | F31: CHECK | G31: #REF!·#DIV/0!·#NAME?·#VALUE! 등
A32: 27 | B32: 수식 오류 0개: Scenarios | C32: =IF(SUMPRODUCT(ISERROR(Scenarios!$A$1:$T$138)*1)=0,"OK","ERR") -> OK | D32: =SUMPRODUCT(ISERROR(Scenarios!$A$1:$T$138)*1) -> 0 | E32: 0 | F32: CHECK | G32: #REF!·#DIV/0!·#NAME?·#VALUE! 등
A33: 28 | B33: 수식 오류 0개: Scen_Calc | C33: =IF(SUMPRODUCT(ISERROR(Scen_Calc!$A$1:$R$220)*1)=0,"OK","ERR") -> OK | D33: =SUMPRODUCT(ISERROR(Scen_Calc!$A$1:$R$220)*1) -> 0 | E33: 0 | F33: CHECK | G33: #REF!·#DIV/0!·#NAME?·#VALUE! 등
A34: 29 | B34: 수식 오류 0개: Football | C34: =IF(SUMPRODUCT(ISERROR(Football!$A$1:$H$15)*1)=0,"OK","ERR") -> OK | D34: =SUMPRODUCT(ISERROR(Football!$A$1:$H$15)*1) -> 0 | E34: 0 | F34: CHECK | G34: #REF!·#DIV/0!·#NAME?·#VALUE! 등
A35: 30 | B35: 수식 오류 0개: Convergence | C35: =IF(SUMPRODUCT(ISERROR(Convergence!$A$1:$G$17)*1)=0,"OK","ERR") -> OK | D35: =SUMPRODUCT(ISERROR(Convergence!$A$1:$G$17)*1) -> 0 | E35: 0 | F35: CHECK | G35: #REF!·#DIV/0!·#NAME?·#VALUE! 등
A36: 31 | B36: 피어 표본 수: EV/Sales | C36: =IF(Peers!$C$17>=PeerNWarn,"OK","WARN") -> WARN | D36: =Peers!$C$17 -> 3 | E36: =PeerNWarn -> 5 | F36: WARN
A37: 32 | B37: 피어 표본 수: EV/EBITDA | C37: =IF(Peers!$C$15>=PeerNWarn,"OK","WARN") -> WARN | D37: =Peers!$C$15 -> 3 | E37: =PeerNWarn -> 5 | F37: WARN
A38: 33 | B38: 피어 표본 수: PER | C38: =IF(Peers!$C$19>=PeerNWarn,"OK","WARN") -> OK | D38: =Peers!$C$19 -> 5 | E38: =PeerNWarn -> 5 | F38: WARN
A39: 34 | B39: 피어 표본 수: PBR | C39: =IF(Peers!$C$18>=PeerNWarn,"OK","WARN") -> OK | D39: =Peers!$C$18 -> 6 | E39: =PeerNWarn -> 5 | F39: WARN
A40: 35 | B40: 베타 신뢰성(피어 R² 중앙값 ≥ 기준) | C40: =IF(NOT(ISNUMBER(BetaR2Median)),"WARN",IF(BetaR2Median>=BetaR2Warn,"OK","WARN")) -> OK | D40: =BetaR2Median -> 0.15 | E40: =BetaR2Warn -> 0.1 | F40: WARN | G40: 표시만(경로 불변)
A41: 36 | B41: RONIC 계산값 사용(대체 없음) | C41: =IF(DCF!$C$25="계산값 사용","OK","WARN") -> WARN | D41: =RONIC -> 0.092121243 | F41: WARN
A42: 37 | B42: 블록 프리미엄 적용 표본 수 ≥ 10 | C42: =IF(OR(PremN="회귀",N(PremN)>=PremNWarn),"OK","WARN") -> OK | D42: =PremN -> 회귀 | E42: =PremNWarn -> 10 | F42: WARN
A43: 38 | B43: 엔진 대조(선택 칸): 주당 가치(원, Gordon) | C43: =IF(RfTenor<>5,"N/A",IF(AND(ISNUMBER(PerShare),ISNUMBER(INDEX(Scenarios!$B$32:$D$34,ScenIdx,MATCH(SRP_Sel,SRP_List,0)))),IF(ABS(PerShare-INDEX(Scenarios!$B$32:$D$34,ScenIdx,MATCH(SRP_Sel,SRP_List,0)))<=1,"OK","DIFF"),IF(AND(NOT(ISNUMBER(PerShare)),NOT(ISNUMBER(INDEX(Scenarios!$B$32:$D$34,ScenIdx,MATCH(SRP_Sel,SRP_List,0))))),"N/M","DIFF"))) -> OK | D43: =PerShare -> 8733.8645 | E43: =INDEX(Scenarios!$B$32:$D$34,ScenIdx,MATCH(SRP_Sel,SRP_List,0)) -> 8733.8645 | F43: INFO | G43: 허용 오차 1. Rf 10년 선택이면 N/A(아래 Rf 10년 대조)
A44: 39 | B44: 엔진 대조(선택 칸): WACC | C44: =IF(RfTenor<>5,"N/A",IF(AND(ISNUMBER(WACC),ISNUMBER(INDEX(Scenarios!$B$37:$D$39,ScenIdx,MATCH(SRP_Sel,SRP_List,0)))),IF(ABS(WACC-INDEX(Scenarios!$B$37:$D$39,ScenIdx,MATCH(SRP_Sel,SRP_List,0)))<=1e-06,"OK","DIFF"),IF(AND(NOT(ISNUMBER(WACC)),NOT(ISNUMBER(INDEX(Scenarios!$B$37:$D$39,ScenIdx,MATCH(SRP_Sel,SRP_List,0))))),"N/M","DIFF"))) -> OK | D44: =WACC -> 0.092121243 | E44: =INDEX(Scenarios!$B$37:$D$39,ScenIdx,MATCH(SRP_Sel,SRP_List,0)) -> 0.092121243 | F44: INFO | G44: 허용 오차 1e-06
A45: 40 | B45: 엔진 대조(선택 칸): RONIC | C45: =IF(RfTenor<>5,"N/A",IF(AND(ISNUMBER(RONIC),ISNUMBER(INDEX(Scenarios!$B$42:$D$44,ScenIdx,MATCH(SRP_Sel,SRP_List,0)))),IF(ABS(RONIC-INDEX(Scenarios!$B$42:$D$44,ScenIdx,MATCH(SRP_Sel,SRP_List,0)))<=1e-06,"OK","DIFF"),IF(AND(NOT(ISNUMBER(RONIC)),NOT(ISNUMBER(INDEX(Scenarios!$B$42:$D$44,ScenIdx,MATCH(SRP_Sel,SRP_List,0))))),"N/M","DIFF"))) -> OK | D45: =RONIC -> 0.092121243 | E45: =INDEX(Scenarios!$B$42:$D$44,ScenIdx,MATCH(SRP_Sel,SRP_List,0)) -> 0.092121243 | F45: INFO | G45: 허용 오차 1e-06
A46: 41 | B46: 엔진 대조(선택 칸): 영구가치 비중 | C46: =IF(RfTenor<>5,"N/A",IF(AND(ISNUMBER(TVShare),ISNUMBER(INDEX(Scenarios!$B$47:$D$49,ScenIdx,MATCH(SRP_Sel,SRP_List,0)))),IF(ABS(TVShare-INDEX(Scenarios!$B$47:$D$49,ScenIdx,MATCH(SRP_Sel,SRP_List,0)))<=1e-06,"OK","DIFF"),IF(AND(NOT(ISNUMBER(TVShare)),NOT(ISNUMBER(INDEX(Scenarios!$B$47:$D$49,ScenIdx,MATCH(SRP_Sel,SRP_List,0))))),"N/M","DIFF"))) -> OK | D46: =TVShare -> 0.34395924 | E46: =INDEX(Scenarios!$B$47:$D$49,ScenIdx,MATCH(SRP_Sel,SRP_List,0)) -> 0.34395924 | F46: INFO | G46: 허용 오차 1e-06
A47: 42 | B47: 엔진 대조(선택 칸): Gordon 함의 EV/EBITDA | C47: =IF(RfTenor<>5,"N/A",IF(AND(ISNUMBER(ImpliedMultiple),ISNUMBER(INDEX(Scenarios!$B$52:$D$54,ScenIdx,MATCH(SRP_Sel,SRP_List,0)))),IF(ABS(ImpliedMultiple-INDEX(Scenarios!$B$52:$D$54,ScenIdx,MATCH(SRP_Sel,SRP_List,0)))<=0.0001,"OK","DIFF"),IF(AND(NOT(ISNUMBER(ImpliedMultiple)),NOT(ISNUMBER(INDEX(Scenarios!$B$52:$D$54,ScenIdx,MATCH(SRP_Sel,SRP_List,0))))),"N/M","DIFF"))) -> OK | D47: =ImpliedMultiple -> 7.2326776 | E47: =INDEX(Scenarios!$B$52:$D$54,ScenIdx,MATCH(SRP_Sel,SRP_List,0)) -> 7.2326776 | F47: INFO | G47: 허용 오차 0.0001
A48: 43 | B48: 엔진 대조(선택 칸): 주당 가치(원, Exit) | C48: =IF(RfTenor<>5,"N/A",IF(AND(ISNUMBER(PerShareExit),ISNUMBER(INDEX(Scenarios!$B$57:$D$59,ScenIdx,MATCH(SRP_Sel,SRP_List,0)))),IF(ABS(PerShareExit-INDEX(Scenarios!$B$57:$D$59,ScenIdx,MATCH(SRP_Sel,SRP_List,0)))<=1,"OK","DIFF"),IF(AND(NOT(ISNUMBER(PerShareExit)),NOT(ISNUMBER(INDEX(Scenarios!$B$57:$D$59,ScenIdx,MATCH(SRP_Sel,SRP_List,0))))),"N/M","DIFF"))) -> N/M | D48: =PerShareExit -> N/M | E48: =INDEX(Scenarios!$B$57:$D$59,ScenIdx,MATCH(SRP_Sel,SRP_List,0)) -> n/a | F48: INFO | G48: 허용 오차 1
A49: 44 | B49: 엔진 대조(선택 칸): EV(평가기준일, 백만원) | C49: =IF(RfTenor<>5,"N/A",IF(AND(ISNUMBER(EV_930),ISNUMBER(INDEX(Scenarios!$B$62:$D$64,ScenIdx,MATCH(SRP_Sel,SRP_List,0)))),IF(ABS(EV_930-INDEX(Scenarios!$B$62:$D$64,ScenIdx,MATCH(SRP_Sel,SRP_List,0)))<=0.01,"OK","DIFF"),IF(AND(NOT(ISNUMBER(EV_930)),NOT(ISNUMBER(INDEX(Scenarios!$B$62:$D$64,ScenIdx,MATCH(SRP_Sel,SRP_List,0))))),"N/M","DIFF"))) -> OK | D49: =EV_930 -> 2729.9032 | E49: =INDEX(Scenarios!$B$62:$D$64,ScenIdx,MATCH(SRP_Sel,SRP_List,0)) -> 2729.9032 | F49: INFO | G49: 허용 오차 0.01
A50: 45 | B50: 엔진 대조(선택 칸): Exit 함의 영구성장률 | C50: =IF(RfTenor<>5,"N/A",IF(AND(ISNUMBER(ImpliedG_Exit),ISNUMBER(INDEX(Scenarios!$B$67:$D$69,ScenIdx,MATCH(SRP_Sel,SRP_List,0)))),IF(ABS(ImpliedG_Exit-INDEX(Scenarios!$B$67:$D$69,ScenIdx,MATCH(SRP_Sel,SRP_List,0)))<=1e-06,"OK","DIFF"),IF(AND(NOT(ISNUMBER(ImpliedG_Exit)),NOT(ISNUMBER(INDEX(Scenarios!$B$67:$D$69,ScenIdx,MATCH(SRP_Sel,SRP_List,0))))),"N/M","DIFF"))) -> N/M | D50: =ImpliedG_Exit -> N/M | E50: =INDEX(Scenarios!$B$67:$D$69,ScenIdx,MATCH(SRP_Sel,SRP_List,0)) -> n/a | F50: INFO | G50: 허용 오차 1e-06
A51: 46 | B51: 엔진 대조(선택 칸): 영구가치 비중(Exit) | C51: =IF(RfTenor<>5,"N/A",IF(AND(ISNUMBER(TVShare_Exit),ISNUMBER(INDEX(Scenarios!$B$72:$D$74,ScenIdx,MATCH(SRP_Sel,SRP_List,0)))),IF(ABS(TVShare_Exit-INDEX(Scenarios!$B$72:$D$74,ScenIdx,MATCH(SRP_Sel,SRP_List,0)))<=1e-06,"OK","DIFF"),IF(AND(NOT(ISNUMBER(TVShare_Exit)),NOT(ISNUMBER(INDEX(Scenarios!$B$72:$D$74,ScenIdx,MATCH(SRP_Sel,SRP_List,0))))),"N/M","DIFF"))) -> N/M | D51: =TVShare_Exit -> N/M | E51: =INDEX(Scenarios!$B$72:$D$74,ScenIdx,MATCH(SRP_Sel,SRP_List,0)) -> n/a | F51: INFO | G51: 허용 오차 1e-06
A52: 47 | B52: 엔진 대조: 시나리오 4 × SRP 3 주당 최대 차이(원) | C52: =IF(RfTenor<>5,"N/A",IF(MAX(ABS(MAX(ScenDiff)),ABS(MIN(ScenDiff)))<=1,"OK","DIFF")) -> OK | D52: =MAX(ABS(MAX(ScenDiff)),ABS(MIN(ScenDiff))) -> 3.6379788e-12 | E52: 1 | F52: INFO | G52: 허용 오차 1원
A53: 48 | B53: 엔진 대조(Rf 10년 선택 시): 시나리오 × SRP 주당 최대 차이(원) | C53: =IF(RfTenor<>10,"N/A",IF(MAX(ABS(MAX(Rf10Diff)),ABS(MIN(Rf10Diff)))<=1,"OK","DIFF")) -> N/A | D53: =IF(RfTenor<>10,"",MAX(ABS(MAX(Rf10Diff)),ABS(MIN(Rf10Diff)))) | E53: 1 | F53: INFO | G53: P6-A. Inputs 'Rf 만기 선택' = 10일 때 A 표 = G-2
A54: 49 | B54: Rf 만기 선택이 5 또는 10 | C54: =IF(OR(RfTenor=5,RfTenor=10),"OK","ERR") -> OK | D54: =RfTenor -> 5 | F54: CHECK
A55: 50 | B55: 엔진 대조: βu 중앙값 | C55: =IF(AND(ISNUMBER(BetaU),ISNUMBER(WACC!$E$6)),IF(ABS(BetaU-WACC!$E$6)<=1E-9,"OK","DIFF"),IF(AND(NOT(ISNUMBER(BetaU)),NOT(ISNUMBER(WACC!$E$6))),"N/M","DIFF")) -> OK | D55: =BetaU -> 0.62399371 | E55: =WACC!$E$6 -> 0.62399371 | F55: INFO
A56: 51 | B56: 엔진 대조: EV/Sales 주당 사분위 | C56: =IFERROR(IF(MAX(ABS(Peers!$H$17-Peers!$L$17),ABS(Peers!$I$17-Peers!$M$17),ABS(Peers!$J$17-Peers!$N$17))<=1,"OK","DIFF"),IF(COUNT(Peers!$H$17:$J$17,Peers!$L$17:$N$17)=0,"OK","DIFF")) -> OK | D56: =Peers!$I$17 -> N/M | E56: =Peers!$M$17 -> n/a | F56: INFO | G56: 허용 오차 1원
A57: 52 | B57: 엔진 대조: EV/EBITDA 주당 사분위 | C57: =IFERROR(IF(MAX(ABS(Peers!$H$15-Peers!$L$15),ABS(Peers!$I$15-Peers!$M$15),ABS(Peers!$J$15-Peers!$N$15))<=1,"OK","DIFF"),IF(COUNT(Peers!$H$15:$J$15,Peers!$L$15:$N$15)=0,"OK","DIFF")) -> OK | D57: =Peers!$I$15 -> N/M | E57: =Peers!$M$15 -> n/a | F57: INFO | G57: 허용 오차 1원
A58: 53 | B58: 엔진 대조: PER 주당 사분위 | C58: =IFERROR(IF(MAX(ABS(Peers!$H$19-Peers!$L$19),ABS(Peers!$I$19-Peers!$M$19),ABS(Peers!$J$19-Peers!$N$19))<=1,"OK","DIFF"),IF(COUNT(Peers!$H$19:$J$19,Peers!$L$19:$N$19)=0,"OK","DIFF")) -> OK | D58: =Peers!$I$19 -> N/M | E58: =Peers!$M$19 -> n/a | F58: INFO | G58: 허용 오차 1원
A59: 54 | B59: 엔진 대조: PBR 주당 사분위 | C59: =IFERROR(IF(MAX(ABS(Peers!$H$18-Peers!$L$18),ABS(Peers!$I$18-Peers!$M$18),ABS(Peers!$J$18-Peers!$N$18))<=1,"OK","DIFF"),IF(COUNT(Peers!$H$18:$J$18,Peers!$L$18:$N$18)=0,"OK","DIFF")) -> OK | D59: =Peers!$I$18 -> 2566.1478 | E59: =Peers!$M$18 -> 2566.1478 | F59: INFO | G59: 허용 오차 1원
A60: 55 | B60: 엔진 대조: 블록 1주당 띠 | C60: =IF(AND(ISNUMBER(Block_q1),ISNUMBER(Premium!$E$23),ISNUMBER(Block_q2),ISNUMBER(Premium!$E$24),ISNUMBER(Block_q3),ISNUMBER(Premium!$E$25)),IF(MAX(ABS(Block_q1-Premium!$E$23),ABS(Block_q2-Premium!$E$24),ABS(Block_q3-Premium!$E$25))<=1,"OK","DIFF"),IF(AND(NOT(ISNUMBER(Block_q1)),NOT(ISNUMBER(Premium!$E$23)),NOT(ISNUMBER(Block_q2)),NOT(ISNUMBER(Premium!$E$24)),NOT(ISNUMBER(Block_q3)),NOT(ISNUMBER(Premium!$E$25))),"N/M","DIFF")) -> OK | D60: =Block_q2 -> 21386.951 | E60: =Premium!$E$24 -> 21386.951 | F60: INFO
A61: 56 | B61: 엔진 대조: D6 method·이유 | C61: =IF(AND(PremMethod=Premium!$E$10,PremReason=Premium!$E$11),"OK","DIFF") -> OK | D61: =PremMethod -> regression | E61: =Premium!$E$10 -> regression | F61: INFO
A62: 57 | B62: 데이터 표 C: 엑셀 계산 값 − 엔진 격자 최대 차이(기본·SRP 0%일 때만) | C62: =IF(AND(ScenSel="기본",SRP_Sel=SRP_1,RonicStart="normal",RfTenor=5),IF(MAX(ABS(MAX(Scenarios!$P$89:$T$93)),ABS(MIN(Scenarios!$P$89:$T$93)))<=1,"OK","DIFF"),"N/A") -> OK | D62: =MAX(ABS(MAX(Scenarios!$P$89:$T$93)),ABS(MIN(Scenarios!$P$89:$T$93))) -> 0 | E62: 1 | F62: INFO | G62: 엑셀이 데이터 표를 다시 계산한 뒤 의미가 있다(formulas 재계산은 데이터 표 미지원 → 저장된 엔진 값)
A63: 58 | B63: 데이터 표 C: 중심 칸 = 살아 있는 모델 주당(기본·SRP 0%일 때만) | C63: =IF(AND(ScenSel="기본",SRP_Sel=SRP_1,RonicStart="normal",RfTenor=5),IF(AND(ISNUMBER(Scenarios!$D$91),ISNUMBER(PerShare)),IF(ABS(Scenarios!$D$91-PerShare)<=1,"OK","DIFF"),IF(AND(NOT(ISNUMBER(Scenarios!$D$91)),NOT(ISNUMBER(PerShare))),"N/M","DIFF")),"N/A") -> OK | D63: =Scenarios!$D$91 -> 8733.8645 | E63: =PerShare -> 8733.8645 | F63: INFO
A64: 59 | B64: 데이터 표 D: 엑셀 계산 값 − 엔진 격자 최대 차이(기본·SRP 0%일 때만) | C64: =IF(AND(ScenSel="기본",SRP_Sel=SRP_1,RonicStart="normal",RfTenor=5),IF(MAX(ABS(MAX(Scenarios!$P$98:$T$102)),ABS(MIN(Scenarios!$P$98:$T$102)))<=1,"OK","DIFF"),"N/A") -> OK | D64: =MAX(ABS(MAX(Scenarios!$P$98:$T$102)),ABS(MIN(Scenarios!$P$98:$T$102))) -> 0 | E64: 1 | F64: INFO | G64: 엑셀이 데이터 표를 다시 계산한 뒤 의미가 있다(formulas 재계산은 데이터 표 미지원 → 저장된 엔진 값)
A65: 60 | B65: 데이터 표 D: 중심 칸 = 살아 있는 모델 주당(기본·SRP 0%일 때만) | C65: =IF(AND(ScenSel="기본",SRP_Sel=SRP_1,RonicStart="normal",RfTenor=5),IF(AND(ISNUMBER(Scenarios!$D$100),ISNUMBER(PerShare)),IF(ABS(Scenarios!$D$100-PerShare)<=1,"OK","DIFF"),IF(AND(NOT(ISNUMBER(Scenarios!$D$100)),NOT(ISNUMBER(PerShare))),"N/M","DIFF")),"N/A") -> OK | D65: =Scenarios!$D$100 -> 8733.8645 | E65: =PerShare -> 8733.8645 | F65: INFO
A66: 61 | B66: 데이터 표 M: 엑셀 계산 값 − 엔진 격자 최대 차이(기본·SRP 0%일 때만) | C66: =IF(AND(ScenSel="기본",SRP_Sel=SRP_1,RonicStart="normal",RfTenor=5),IF(MAX(ABS(MAX(Scenarios!$L$107:$N$109)),ABS(MIN(Scenarios!$L$107:$N$109)))<=1,"OK","DIFF"),"N/A") -> OK | D66: =MAX(ABS(MAX(Scenarios!$L$107:$N$109)),ABS(MIN(Scenarios!$L$107:$N$109))) -> 0 | E66: 1 | F66: INFO | G66: 엑셀이 데이터 표를 다시 계산한 뒤 의미가 있다(formulas 재계산은 데이터 표 미지원 → 저장된 엔진 값)
A67: 62 | B67: 데이터 표 M: 중심 칸 = 살아 있는 모델 주당(기본·SRP 0%일 때만) | C67: =IF(AND(ScenSel="기본",SRP_Sel=SRP_1,RonicStart="normal",RfTenor=5),IF(AND(ISNUMBER(Scenarios!$B$108),ISNUMBER(PerShare)),IF(ABS(Scenarios!$B$108-PerShare)<=1,"OK","DIFF"),IF(AND(NOT(ISNUMBER(Scenarios!$B$108)),NOT(ISNUMBER(PerShare))),"N/M","DIFF")),"N/A") -> OK | D67: =Scenarios!$B$108 -> 8733.8645 | E67: =PerShare -> 8733.8645 | F67: INFO
A68: 63 | B68: 데이터 표 G: 엑셀 계산 값 − 엔진 격자 최대 차이(기본·SRP 0%일 때만) | C68: =IF(AND(ScenSel="기본",SRP_Sel=SRP_1,RonicStart="normal",RfTenor=5),IF(MAX(ABS(MAX(Scenarios!$N$121:$Q$122)),ABS(MIN(Scenarios!$N$121:$Q$122)))<=1,"OK","DIFF"),"N/A") -> OK | D68: =MAX(ABS(MAX(Scenarios!$N$121:$Q$122)),ABS(MIN(Scenarios!$N$121:$Q$122))) -> 0 | E68: 1 | F68: INFO | G68: 엑셀이 데이터 표를 다시 계산한 뒤 의미가 있다(formulas 재계산은 데이터 표 미지원 → 저장된 엔진 값)
A69: 64 | B69: 데이터 표 G: 중심 칸 = 살아 있는 모델 주당(기본·SRP 0%일 때만) | C69: =IF(AND(ScenSel="기본",SRP_Sel=SRP_1,RonicStart="normal",RfTenor=5),IF(AND(ISNUMBER(Scenarios!$B$121),ISNUMBER(PerShare)),IF(ABS(Scenarios!$B$121-PerShare)<=1,"OK","DIFF"),IF(AND(NOT(ISNUMBER(Scenarios!$B$121)),NOT(ISNUMBER(PerShare))),"N/M","DIFF")),"N/A") -> OK | D69: =Scenarios!$B$121 -> 8733.8645 | E69: =PerShare -> 8733.8645 | F69: INFO
A70: 65 | B70: 수렴 시험: 살아 있는 C3 판정 = 엔진 기록(C3 — 공통 규칙 수정 후) | C70: =IF(Convergence!$F$13=Convergence!$F$8,"OK","DIFF") -> OK | D70: =Convergence!$F$13 -> 판정 불가(대상 지표 ≤ 0) | E70: =Convergence!$F$8 -> 판정 불가(대상 지표 ≤ 0) | F70: INFO
A71: 66 | B71: 수렴 시험: 살아 있는 기본 DCF = 엔진 C3 주당 | C71: =IF(AND(ISNUMBER(Convergence!$B$13),ISNUMBER(Convergence!$B$8)),IF(ABS(Convergence!$B$13-Convergence!$B$8)<=1,"OK","DIFF"),IF(AND(NOT(ISNUMBER(Convergence!$B$13)),NOT(ISNUMBER(Convergence!$B$8))),"N/M","DIFF")) -> OK | D71: =Convergence!$B$13 -> 8733.8645 | E71: =Convergence!$B$8 -> 8733.8645 | F71: INFO
A72: 67 | B72: 수렴 시험: 피어 EV/EBITDA 사분위 = 엔진 범위 | C72: =IFERROR(IF(MAX(ABS(Convergence!$C$13-Convergence!$C$8),ABS(Convergence!$D$13-Convergence!$D$8))<=1,"OK","DIFF"),IF(COUNT(Convergence!$C$13,Convergence!$D$13,Convergence!$C$8,Convergence!$D$8)=0,"OK","DIFF")) -> OK | D72: =Convergence!$C$13 -> N/M | E72: =Convergence!$C$8 -> n/a | F72: INFO
A73: 68 | B73: 수렴 시험: 보완 전 표 사분위 = 엔진 C2 범위 | C73: =IFERROR(IF(MAX(ABS(Convergence!$C$14-Convergence!$C$7),ABS(Convergence!$D$14-Convergence!$D$7))<=1,"OK","DIFF"),IF(COUNT(Convergence!$C$14,Convergence!$D$14,Convergence!$C$7,Convergence!$D$7)=0,"OK","DIFF")) -> OK | D73: =Convergence!$C$14 -> N/M | E73: =Convergence!$C$7 -> n/a | F73: INFO
A74: 69 | B74: 엔진 표 중심값(WACC×g) = 살아 있는 표 기본·SRP 0% | C74: =IF(RfTenor<>5,"N/A",IF(AND(ISNUMBER(Scenarios!$K$91),ISNUMBER(INDEX(ScenGridPS,MATCH("기본",ScenNames,0),1))),IF(ABS(Scenarios!$K$91-INDEX(ScenGridPS,MATCH("기본",ScenNames,0),1))<=1,"OK","DIFF"),IF(AND(NOT(ISNUMBER(Scenarios!$K$91)),NOT(ISNUMBER(INDEX(ScenGridPS,MATCH("기본",ScenNames,0),1)))),"N/M","DIFF"))) -> OK | D74: =Scenarios!$K$91 -> 8733.8645 | E74: =INDEX(ScenGridPS,MATCH("기본",ScenNames,0),1) -> 8733.8645 | F74: INFO

Sheet Diagnostics
A1: Diagnostics — 결과 신뢰도 진단과 사람 판단 우선순위 (값은 바꾸지 않음)
A2: 회색 = 엔진 계산값(config/p7b2.yaml diagnostics · src/pipeline/diagnose.py), 신호등은 살아 있는 수식. 대안은 후보·민감도일 뿐 기본값은 그대로(사전 고정 0dad3cc)
A4: A. 신호등(기본 시나리오 · SRP 열 1)
A5: DCF 주당(원, Scenarios A-1 기본 · SRP 열 1) | B5: =INDEX(ScenGridPS,MATCH("기본",ScenNames,0),1) -> 8733.8645
A6: 엔진 기록 DCF 주당(원) | B6: 8733.8645
A7: 피어 범위 기준 배수 | B7: EV/EBITDA | C7: EV/EBITDA n < 3이면 EV/Sales
A8: 피어 사분위 q25 주당(원) | B8: n/a | C8: Peers 시트와 같은 정의(엔진 값)
A9: 피어 중앙값 주당(원) | B9: n/a
A10: 피어 사분위 q75 주당(원) | B10: n/a
A11: 피어 n | B11: 3
A12: 피어 범위 유효(1 = 해석 가능, 0 = 해석 불가) | B12: 1 | C12: config/p7b3.yaml peer_validity
A13: 기준일 종가(원) | B13: =Close -> 20000 | C13: 한국거래소 통계정보
A14: DCF ÷ 종가 | B14: =DiagDcf/Close -> 0.43669322
A15: 임계값: 피어 노랑 하한 배수(× q25) | B15: 0.67 | C15: 사전 고정
A16: 임계값: 피어 노랑 상한 배수(× q75) | B16: 1.5 | C16: 사전 고정
A17: 임계값: 시장 초록 [하한, 상한] | B17: 0.67 | C17: 상한 1.5
A18: 시장 초록 상한 | B18: 1.5
A19: 임계값: 시장 노랑 [하한, 상한] | B19: 0.5 | C19: 상한 2.0
A20: 시장 노랑 상한 | B20: 2
A21: 신호: DCF vs 피어 범위 | B21: =IF(OR(DiagPeerValid=0,NOT(ISNUMBER(DiagQ25)),NOT(ISNUMBER(DiagQ75)),N(DiagPeerN)<3),"회색",IF(AND(DiagDcf>=DiagQ25,DiagDcf<=DiagQ75),"초록",IF(OR(AND(DiagDcf>=DiagThPLo*DiagQ25,DiagDcf<DiagQ25),AND(DiagDcf>DiagQ75,DiagDcf<=DiagThPHi*DiagQ75)),"노랑","빨강"))) -> 회색 | C21: 초록 = 사분위 안
A22: 신호: DCF ÷ 종가 | B22: =IF(AND(DiagMktRatio>=DiagThMGLo,DiagMktRatio<=DiagThMGHi),"초록",IF(AND(DiagMktRatio>=DiagThMYLo,DiagMktRatio<=DiagThMYHi),"노랑","빨강")) -> 빨강
A23: 종합 신호(나쁜 쪽) | B23: =IF(OR(DiagLightPeer="빨강",DiagLightMkt="빨강"),"빨강",IF(OR(DiagLightPeer="노랑",DiagLightMkt="노랑"),"노랑",IF(AND(DiagLightPeer="회색",DiagLightMkt="회색"),"회색","초록"))) -> 빨강
A24: 엔진 판정 | B24: 빨강
A25: 엔진 판정 = 살아 있는 판정 | B25: =IF(DiagLight=DiagLightEngine,"OK","DIFF") -> OK | C25: OK / DIFF
A27: B. 역산 — 피어 중앙값 주당을 맞추려면(하나만 움직임, 엔진 값)
A28: 항목 | B28: 기본 값 | C28: 필요 값 | D28: 차이
A29: 목표 주당(원) — EV/EBITDA | B29: n/a | C29: n/a | D29: n/a
A30: 정상 영업이익률 | B30: n/a | C30: 범위 안 해 없음 | D30: n/a
A31: 출발 성장률 | B31: n/a | C31: 범위 안 해 없음 | D31: n/a
A32: WACC | B32: n/a | C32: 범위 안 해 없음 | D32: n/a
A33: 역산 정확도: 다시 계산한 주당 − 목표(원, 최대 절댓값) | B33: n/a | C33: 범위 안 해 없음 | D33: n/a
A35: C. 주식가치 구성(백만원, 평가기준일)
A36: 항목 | B36: 금액(백만원) | C36: 주식가치 대비
A37: EV | B37: 2729.9032 | C37: 0.011430021
A38: 영구가치 현재가치(Gordon) | B38: 938.97544 | C38: 0.0039314615
A39: 명시·체감 기간 현재가치 | B39: 1790.9278 | C39: 0.00749856
A40: + 현금성 | B40: 1111.4503 | C40: 0.0046536086
A41: + 비영업자산 | B41: 235050.34 | C41: 0.98414858
A42: − 총차입금(리스 포함) | B42: -55.459414 | C42: -0.00023220687
A43: − 비지배지분 | B43: 0 | C43: 0
A44: = 주식가치 | B44: 238836.23 | C44: 1
A46: D. 데이터 이상 신호(사전 고정 기준)
A47: 신호 | B47: 해당 | C47: 값
A48: 정상 이익률 계산 연도(FY2023~2025)에 영업손실 연도 포함 | B48: 해당 | C48: 15억, 1억, -18억
A49: FY2021~2025 영업이익률 표준편차 > 2 × 시나리오 이익률 폭(2%p) = 4%p | B49: 해당 | C49: 0.35876018
A50: FY2021~2025 매출 성장률 표준편차 > 2 × 시나리오 성장률 폭(2%p) = 4%p | B50: 해당 | C50: 0.24502482
A51: 과거 3년 ROIC(RONIC 상한) < 기본 WACC | B51: 해당 | C51: -0.65198267
A52: 영구가치 비중 > 75% 또는 < 0% | B52: - | C52: 0.34395924
A53: 브리지 항목 하나의 절댓값 > 주식가치의 50% | B53: 해당 | C53: 0.98414858
A54: 시나리오 × SRP 9칸 중 주당 < 0인 칸이 있음 | B54: - | C54: 0
A56: E. 정상 이익률 후보(표시만, 기본값은 과거 3년 평균 그대로)
A57: 후보 | B57: 이익률 | C57: 주당(원) | D57: 기본 대비(원)
A58: 손실 연도 제외 3년 평균(FY2023~2025 중 영업이익 > 0인 해) | B58: 0.16717076 | C58: 8944.4271 | D58: 210.56265
A59: 5년 중앙값(FY2021~2025) | B59: 0.01454955 | C59: 8733.8645 | D59: 0
A60: 피어 LTM 영업이익률 중앙값(포함 피어) | B60: 0.12355134 | C60: 8885.451 | D60: 151.58655
A62: F. 민감도(기본값 그대로, 다른 선택의 주당)
A63: 항목 | B63: 값 | C63: 주당(원) | D63: 기본 대비(원)
A64: 고객 자금 성격 부채(백만원): 예수금 8 | B64: 8.484 | C64: n/a | D64: n/a
A65: 영업용 현금 = min(현금성, 고객 자금 부채) → 브리지에서 뺌(백만원) | B65: 8.484 | C65: 8733.5542 | D65: -0.31024651
A66: 비지배 장부(백만원) — 기본 | B66: 0 | C66: n/a | D66: n/a
A67: (a) 비례법: 비지배 장부 ÷ 자본총계 | B67: 0 | C67: 8733.8645 | D67: 0
A68: (b) 비지배 장부 × 피어 P/B 중앙값 | B68: 0.58888537 | C68: 8733.8645 | D68: 0
A70: G. 사람 판단 목록 — 다른 선택의 주당 영향이 큰 순(★ = 상위 5)
A71: 순위 | B71: 범주 | C71: 항목 | D71: 다른 선택 | F71: 주당 차이(원) | G71: 기본 대비
A72: 1 ★ | B72: 상장 관계기업 | C72: 지주회사(별도 매출 ÷ 연결 매출 3% < 25%(지주형)): 상장 관계기업 1곳을 시가로 반영 | D72: 구조 확인(상장 관계기업 시가·지분 할인) | F72: n/a | G72: n/a
A73: 2 ★ | B73: 실적 전환 | C73: LTM 영업이익률 -101.4% vs 5년 중앙값 1.5% | D73: 후보 없음(범위 밖: -101.40%) | F73: n/a | G73: n/a
A74: 3 ★ | B74: SOTP | C74: 상장 종속회사 지분 할인 | D74: 상장 종속회사 지분 할인 50%(기본 30%) | F74: -1044.1309 | G74: -0.1195497
A75: 4 ★ | B75: 상장 관계기업 | C75: 상장 관계기업 시가 반영 | D75: 상장 관계기업을 장부가로 둠(시가 반영 안 함) | F75: -1450.8156 | G75: -0.16611383
A76: 5 ★ | B76: 상장 관계기업 | C76: 상장 관계기업 지분 할인(기본 0%) | D76: 상장 관계기업 지분 할인 50%(기본 0%) | F76: -949.60882 | G76: -0.10872722
A77: 6 | B77: 비경상 손익 | C77: 정상화 조정 필요 여부 | D77: 정상 이익률 손실 연도 제외 3년 평균(FY2023~2025 중 영업이익 > 0인 해) 16.72%(기본 1.45%) | F77: 210.56265 | G77: 0.024108761
A78: 7 | B78: 기본 경로 | C78: 기본 경로 v1(대안) | D78: 기본 경로 v1(3년 평균 이익률 -5.08%, 매출 CAGR 0.81%) | F78: -174.18057 | G78: -0.019943127
A79: 8 | B79: 이익률 수렴 | C79: 피어 쪽 수렴 비율 | D79: 수렴 비율 0%(기본 50%, 피어 이익률 중앙값 12.4% 쪽) | F79: -63.583069 | G79: -0.0072800613
A80: 9 | B80: 시나리오 폭 | C80: ±2%p(성장·이익률) 기본값, g 2% | D80: 낙관(+2%p) | F80: 33.642093 | G80: 0.0038519137
A81: 10 | B81: 할인율 | C81: SRP 열 | D81: SRP 2% | F81: -17.371309 | G81: -0.0019889602
A82: 11 | B82: 할인율 | C82: MRP | D82: MRP 7%(기본 8%, 한공회 가이던스 7~9%) | F82: 7.1061857 | G82: 0.0008136359
A83: 12 | B83: 이익률 수렴 | C83: 수렴 도달 연도 | D83: 도달 연도 2030(기본 2032) | F83: 5.0089839 | G83: 0.00057351289
A84: 13 | B84: 재투자 비율 | C84: D&A ÷ 매출(3년 평균) | D84: D&A ÷ 매출 5년 평균 2.92%(FY2021~2025, 기본 3년 평균 2.42%) | F84: 3.7138789 | G84: 0.00042522745
A85: 14 | B85: 재투자 비율 | C85: CAPEX ÷ 매출(3년 평균) | D85: CAPEX ÷ 매출 5년 평균 0.84%(FY2021~2025, 기본 3년 평균 1.31%) | F85: 3.470543 | G85: 0.00039736625
... A90: 19 | B90: Kd 근거 | C90: 신용등급 자동 탐색 안 함 | D90: 세전 Kd 4.70%(AA- 3년, 기본 10.51%) | F90: 0.23326833 | G90: 2.6708489e-05
A91: 상위 5 항목 주당 영향 비중(영향 값 있는 항목 기준, P7-B5) | G91: 0.96539247
A92: 계산할 수 없는 항목(원래 순서)
B93: 우선주 처리 | C93: 우선주 없음 | D93: 주식의 총수 표에 우선주 없음 — 확인만
B94: 피어 유사성 | C94: KT나스미디어 | D94: 자동: KSIC 71310(앞 2자리 71), 시가총액 대상의 (공개 비표시)배, FY2023~2025 영업이익 흑자 — 사업 유사성 사람 검토 | 사업 개요: 2단계 피어 카드의 공시 인용 참고
B95: 피어 유사성 | C95: HS애드 | D95: 자동: KSIC 71310(앞 2자리 71), 시가총액 대상의 (공개 비표시)배, FY2023~2025 영업이익 흑자 — 사업 유사성 사람 검토 | 사업 개요: 2단계 피어 카드의 공시 인용 참고
B96: 피어 유사성 | C96: 에코아이 | D96: 자동: KSIC 716(앞 2자리 71), 시가총액 대상의 (공개 비표시)배, FY2023~2025 영업이익 흑자 — 사업 유사성 사람 검토 | 사업 개요: 2단계 피어 카드의 공시 인용 참고
B97: 피어 유사성 | C97: 인크로스 | D97: 자동: KSIC 71310(앞 2자리 71), 시가총액 대상의 (공개 비표시)배, FY2023~2025 영업이익 흑자 — 사업 유사성 사람 검토 | 사업 개요: 2단계 피어 카드의 공시 인용 참고
B98: 피어 유사성 | C98: 오리콤 | D98: 자동: KSIC 71310(앞 2자리 71), 시가총액 대상의 (공개 비표시)배, FY2023~2025 영업이익 흑자 — 사업 유사성 사람 검토 | 사업 개요: 2단계 피어 카드의 공시 인용 참고
B99: 피어 유사성 | C99: 레뷰코퍼레이션 | D99: 자동: KSIC 71310(앞 2자리 71), 시가총액 대상의 (공개 비표시)배, FY2023~2025 영업이익 흑자 — 사업 유사성 사람 검토 | 사업 개요: 2단계 피어 카드의 공시 인용 참고
B100: SOTP | C100: 상장 종속회사 지분 할인(기본 0%) | D100: 지주회사 할인 30%·50% 민감도 — 평가 목적에 맞는 할인을 사람이 정함
B101: SOTP | C101: 비상장 종속회사 장부가 | D101: 장부가(취득원가 기준일 수 있음) — 공정가치와 다를 수 있음(P/B 민감도 참고)
B102: 기준일 뒤 주요 공시 | C102: 2026-07-01~기준일 공시 7건(제목만, 주요 단어 0건) | D102: 반기보고서 (2026.06); 임원ㆍ주요주주특정증권등소유상황보고서; 주식등의대량보유상황보고서(일반)
B103: 비경상 손익 | C103: 정상화 조정 필요 여부 | D103: FY2022 세전이익 − 영업이익 = -110억(영업이익 -3억의 30% 초과): 영업외 손익 확인
B104: 비경상 손익 | C104: 정상화 조정 필요 여부 | D104: FY2023 세전이익 − 영업이익 = 34억(영업이익 15억의 30% 초과): 영업외 손익 확인
... B117: 재투자 비율 | C117: 운전자본 회전일수(3년 평균) | D117: 자동 진단(config/p7b2.yaml ranking)
A119: H. 대표값 판정(유효성 가드, 사전 고정 91a84dd)
A120: 대표값 | B120: 표시 | C120: 보류면 화면·요약에는 숫자 대신 사유와 1순위 판단
A122: I. 기본 경로 v2 vs v1(대안) — 기본 시나리오·SRP 열 1
A123: v2 주당(원, 이 모델) | B123: 8733.8645
A124: v1 주당(원, 3년 평균 이익률·5년 CAGR) | B124: 8559.6839
A125: v2 출발 이익률(5년 중앙값) | B125: 0.01454955
...

Sheet Judgements
A1: Judgements — 사람 판단 반영 내역 (평가 세션 035610_20260930_001, 확정 v1)
A2: 자동 초안 값 → 사람 확정값. 확정값은 Inputs '사람 확정값' 또는 각 입력 칸에 들어가 계산 시트가 읽는다(살아 있는 수식)
A4: # | B4: 항목 | C4: 가정 | D4: 자동값 | E4: 확정값 | F4: 이유 | G4: 버전 | H4: 시각
A5: 1 | B5: 상장 종속회사 지분 할인 | C5: 상장 지분 할인 | D5: 0.00% | E5: 30.00% | F5: 예시: 후보 있는 최상위 판단의 첫 후보 채택 | G5: v1 | H5: 2026-10-24T02:02:27
A8: 그대로 유지한 판단 0건 · 남은 미처리 43건
A10: 자동 초안 대표값 판정(기록): 표시
